Workbook
Name Adj_closing_price: OFFSET(#REF!,1,0,COUNT(#REF!),1)
Name cmdOK2_click: [1]!cmdOK2_click
Name Date: OFFSET(#REF!,1,0,COUNT(#REF!),1)
Name PAGE1: [2]GROMM!#REF!
Name PAGE2: #REF!
Name PE_band_1: OFFSET(#REF!,1,0,COUNT(#REF!),1)
Name PE_band_2: OFFSET(#REF!,1,0,COUNT(#REF!),1)
Name PE_band_3: OFFSET(#REF!,1,0,COUNT(#REF!),1)
Name PE_band_4: OFFSET(#REF!,1,0,COUNT(#REF!),1)
Name PE_band_5: OFFSET(#REF!,1,0,COUNT(#REF!),1)
Name Price: [1]Template!#REF!
Name Print_Area_MI: #REF!
Name startCompany: [1]Sheet1!#REF!
Name Units: #REF!

Sheet Dashboard
A1: [Britannia LTD.]
A2: Ratio Snapshot
A3: (In INR Crores, unless otherwise stated)
A5: COMPANY DETAILS | H5: Expectations in 5 Years: 2021 - 2025 | O5: Cash vs PAT 2021 - 2025
A6: Industry | B6: [FMCG]
A7: Sector | B7: Packaged Foods
A8: Current Market Price | B8: 3270
A9: Market Capitalization | B9: =B8*'Income Statement'!D46 -> 78741.6
A10: Year end | B10: [2021]
A12: COMPANY DESCRIPTION
A13: Britannia is among the most trusted food brands, and manufactures India’s favorite brands like Good Day, Tiger, NutriChoice, Milk Bikis and Marie Gold which are household names in India. Britannia’s product portfolio includes Biscuits, Bread, Cakes, Rusk, and Dairy products including Cheese, Beverages, Milk and Yoghurt.
A24: Financial Year | B24: =Assumptions!E5 -> FY2022 E | C24: =Assumptions!F5 -> FY2023 E | D24: =Assumptions!G5 -> FY2024 E | E24: =Assumptions!H5 -> FY2025 E | F24: =Assumptions!I5 -> FY2026 E | H24: DEBT and Market Cap
A26: Revenue | B26: ='Income Statement'!E7 -> 14318.24 | C26: ='Income Statement'!F7 -> 15606.882 | D26: ='Income Statement'!G7 -> 17011.501 | E26: ='Income Statement'!H7 -> 18542.536 | F26: ='Income Statement'!I7 -> 20211.364
A27: COGS | B27: ='Income Statement'!E13 -> -8454.1093 | C27: ='Income Statement'!F13 -> -9198.8653 | D27: ='Income Statement'!G13 -> -9982.3272 | E27: ='Income Statement'!H13 -> -10919.408 | F27: ='Income Statement'!I13 -> -11891.652
A28: Gross Profit | B28: ='Income Statement'!E14 -> 5864.1307 | C28: ='Income Statement'!F14 -> 6408.0163 | D28: ='Income Statement'!G14 -> 7029.1737 | E28: ='Income Statement'!H14 -> 7623.1276 | F28: ='Income Statement'!I14 -> 8319.7125
A29: Gross Margin (%) | B29: ='Income Statement'!E63 -> 0.40955667 | C29: ='Income Statement'!F63 -> 0.41058916 | D29: ='Income Statement'!G63 -> 0.41320127 | E29: ='Income Statement'!H63 -> 0.4111157 | F29: ='Income Statement'!I63 -> 0.41163537
A31: Net Profit / EBITDA | B31: ='Income Statement'!E23 -> 2419.2442 | C31: ='Income Statement'!F23 -> 2699.433 | D31: ='Income Statement'!G23 -> 3022.4029 | E31: ='Income Statement'!H23 -> 3211.5357 | F31: ='Income Statement'!I23 -> 3529.1116
A32: Net Margin (%) | B32: ='Income Statement'!E83 -> 0.12451785 | C32: ='Income Statement'!F83 -> 0.12739417 | D32: ='Income Statement'!G83 -> 0.12959685 | E32: ='Income Statement'!H83 -> 0.12584282 | F32: ='Income Statement'!I83 -> 0.1263738
A33: Tax Expenses | B33: =SUM('Income Statement'!E32:E34) -> -607.27005 | C33: =SUM('Income Statement'!F32:F34) -> -677.2146 | D33: =SUM('Income Statement'!G32:G34) -> -763.67629 | E33: =SUM('Income Statement'!H32:H34) -> -799.28575 | F33: =SUM('Income Statement'!I32:I34) -> -876.53716
A34: Profit After Tax | B34: ='Income Statement'!E41 -> 1782.8765 | C34: ='Income Statement'!F41 -> 1988.2258 | D34: ='Income Statement'!G41 -> 2204.637 | E34: ='Income Statement'!H41 -> 2333.445 | F34: ='Income Statement'!I41 -> 2554.187
A35: Net Profit (%) | B35: =Dashboard!B32 -> 0.12451785 | C35: =Dashboard!C32 -> 0.12739417 | D35: =Dashboard!D32 -> 0.12959685 | E35: =Dashboard!E32 -> 0.12584282 | F35: =Dashboard!F32 -> 0.1263738
A36: Cash | B36: ='Balance Sheet'!E8 -> 1480.3768 | C36: ='Balance Sheet'!F8 -> 2931.1837 | D36: ='Balance Sheet'!G8 -> 4469.8027 | E36: ='Balance Sheet'!H8 -> 6149.6658 | F36: ='Balance Sheet'!I8 -> 7972.567
A38: ROA | B38: ='Company Overview'!E41 -> 8.9117246 | C38: ='Company Overview'!F41 -> 9.7660565 | D38: ='Company Overview'!G41 -> 10.688108 | E38: ='Company Overview'!H41 -> 11.746376 | F38: ='Company Overview'!I41 -> 12.85429
A39: Financial Leverage | B39: ='Company Overview'!B47 -> 0.02437744 | C39: ='Company Overview'!C47 -> 0.18890476 | D39: ='Company Overview'!D47 -> 0.22614676 | E39: ='Company Overview'!E47 -> 0.16835872 | F39: ='Company Overview'!F47 -> 0.131022
A40: Net Margin (%) | B40: =B32 -> 0.12451785 | C40: =C32 -> 0.12739417 | D40: =D32 -> 0.12959685 | E40: =E32 -> 0.12584282 | F40: =F32 -> 0.1263738
A41: ROE | B41: ='Company Overview'!E42 -> 0.37033819 | C41: ='Company Overview'!F42 -> 0.32140419 | D41: ='Company Overview'!G42 -> 0.28604679 | E41: ='Company Overview'!H42 -> 0.25044119 | F41: ='Company Overview'!I42 -> 0.23052799
A43: Enterprise Value | B43: =B24 -> FY2022 E | C43: =C24 -> FY2023 E | D43: =D24 -> FY2024 E | E43: =E24 -> FY2025 E | F43: =F24 -> FY2026 E
A44: Net Debt
A45: Market Capitalisation
A46: Cash and Cash Equivalent
A47: Enterprise Value (EV)

Sheet Company Overview
A1: =Dashboard!A1 -> [Britannia LTD.]
A2: Ratio Snapshot
A3: (In INR Crores, unless otherwise stated)
A6: HIGHLIGHTS FROM INCOME STATEMENT | B6: =Assumptions!B5 -> FY2019 A | C6: =Assumptions!C5 -> FY2020 A | D6: =Assumptions!D5 -> FY2021 A | E6: =Assumptions!E5 -> FY2022 E | F6: =Assumptions!F5 -> FY2023 E | G6: =Assumptions!G5 -> FY2024 E | H6: =Assumptions!H5 -> FY2025 E | I6: =Assumptions!I5 -> FY2026 E | ... L6: =Assumptions!L5 -> FY2029 E
A7: Revenue | B7: ='Income Statement'!B7 -> 11054 | C7: ='Income Statement'!C7 -> 11599 | D7: ='Income Statement'!D7 -> 13136 | E7: ='Income Statement'!E7 -> 14318.24 | F7: ='Income Statement'!F7 -> 15606.882 | G7: ='Income Statement'!G7 -> 17011.501 | H7: ='Income Statement'!H7 -> 18542.536 | I7: ='Income Statement'!I7 -> 20211.364 | ... L7: ='Income Statement'!L7 -> 26174.303
A8: EBITDA | B8: ='Income Statement'!B23 -> 1735 | C8: ='Income Statement'!C23 -> 1842.53 | D8: ='Income Statement'!D23 -> 2510 | E8: ='Income Statement'!E23 -> 2419.2442 | F8: ='Income Statement'!F23 -> 2699.433 | G8: ='Income Statement'!G23 -> 3022.4029 | H8: ='Income Statement'!H23 -> 3211.5357 | I8: ='Income Statement'!I23 -> 3529.1116 | ... L8: ='Income Statement'!L23 -> 4572.5781
A9: EBIT | B9: ='Income Statement'!B25 -> 1573.12 | C9: ='Income Statement'!C25 -> 1657.72 | D9: ='Income Statement'!D25 -> 2312.15 | E9: ='Income Statement'!E25 -> 2194.27 | F9: ='Income Statement'!F25 -> 2463.118 | G9: ='Income Statement'!G25 -> 2767.8803 | H9: ='Income Statement'!H25 -> 2933.1867 | I9: ='Income Statement'!I25 -> 3229.9577 | ... L9: ='Income Statement'!L25 -> 4192.1964
A10: PBT | B10: ='Income Statement'!B31 -> 1769.51 | C10: ='Income Statement'!C31 -> 1843.65 | D10: ='Income Statement'!D31 -> 2514.45 | E10: ='Income Statement'!E31 -> 2390.1465 | F10: ='Income Statement'!F31 -> 2665.4404 | G10: ='Income Statement'!G31 -> 2968.3133 | H10: ='Income Statement'!H31 -> 3132.7307 | I10: ='Income Statement'!I31 -> 3430.7242 | ... L10: ='Income Statement'!L31 -> 4392.5966
A11: PAT | B11: ='Income Statement'!B35 -> 1157.04 | C11: ='Income Statement'!C35 -> 1392.95 | D11: ='Income Statement'!D35 -> 1851.43 | E11: ='Income Statement'!E35 -> 1782.8765 | F11: ='Income Statement'!F35 -> 1988.2258 | G11: ='Income Statement'!G35 -> 2204.637 | H11: ='Income Statement'!H35 -> 2333.445 | I11: ='Income Statement'!I35 -> 2554.187 | ... L11: ='Income Statement'!L35 -> 3269.5517
A13: HIGHLIGHTS FROM BALANCE SHEET | B13: =B6 -> FY2019 A | C13: =C6 -> FY2020 A | D13: =D6 -> FY2021 A | E13: =E6 -> FY2022 E | F13: =F6 -> FY2023 E | G13: =G6 -> FY2024 E | H13: =H6 -> FY2025 E | I13: =I6 -> FY2026 E | ... L13: =L6 -> FY2029 E
A14: Fixed Assets | B14: ='Balance Sheet'!B20 -> 1535.58 | C14: ='Balance Sheet'!C20 -> 1716.37 | D14: ='Balance Sheet'!D20 -> 1634.3 | E14: ='Balance Sheet'!E20 -> 1606.6744 | F14: ='Balance Sheet'!F20 -> 1598.0741 | G14: ='Balance Sheet'!G20 -> 1591.6288 | H14: ='Balance Sheet'!H20 -> 1578.5751 | I14: ='Balance Sheet'!I20 -> 1572.3439 | ... L14: ='Balance Sheet'!L20 -> 1559.715
A15: Cash & Cash Equivalents | B15: ='Balance Sheet'!B8 -> 60.32 | C15: ='Balance Sheet'!C8 -> 81.23 | D15: ='Balance Sheet'!D8 -> 142.74 | E15: ='Balance Sheet'!E8 -> 1480.3768 | F15: ='Balance Sheet'!F8 -> 2931.1837 | G15: ='Balance Sheet'!G8 -> 4469.8027 | H15: ='Balance Sheet'!H8 -> 6149.6658 | I15: ='Balance Sheet'!I8 -> 7972.567 | ... L15: ='Balance Sheet'!L8 -> 14405.129
A16: Working Capital | B16: ='Balance Sheet'!B18-'Balance Sheet'!B43 -> 1674.93 | C16: ='Balance Sheet'!C18-'Balance Sheet'!C43 -> 1109.67 | D16: ='Balance Sheet'!D18-'Balance Sheet'!D43 -> 805.41 | E16: ='Balance Sheet'!E18-'Balance Sheet'!E43 -> 2050.9429 | F16: ='Balance Sheet'!F18-'Balance Sheet'!F43 -> 3418.2579 | G16: ='Balance Sheet'!G18-'Balance Sheet'!G43 -> 4931.883 | H16: ='Balance Sheet'!H18-'Balance Sheet'!H43 -> 6539.9787 | I16: ='Balance Sheet'!I18-'Balance Sheet'!I43 -> 8291.9186 | ... L16: ='Balance Sheet'!L18-'Balance Sheet'!L43 -> 14491.418
A17: Long Term Debts and Borrowing | B17: ='Balance Sheet'!B45 -> 61.92 | C17: ='Balance Sheet'!C45 -> 766.06 | D17: ='Balance Sheet'!D45 -> 747.75 | E17: ='Balance Sheet'!E45 -> 747.75 | F17: ='Balance Sheet'!F45 -> 747.75 | G17: ='Balance Sheet'!G45 -> 747.75 | H17: ='Balance Sheet'!H45 -> 747.75 | I17: ='Balance Sheet'!I45 -> 747.75 | ... L17: ='Balance Sheet'!L45 -> 747.75
A18: Equity | B18: ='Balance Sheet'!B55 -> 24.03 | C18: ='Balance Sheet'!C55 -> 24.05 | D18: ='Balance Sheet'!D55 -> 24.09 | E18: ='Balance Sheet'!E55 -> 24.09 | F18: ='Balance Sheet'!F55 -> 24.09 | G18: ='Balance Sheet'!G55 -> 24.09 | H18: ='Balance Sheet'!H55 -> 24.09 | I18: ='Balance Sheet'!I55 -> 24.09 | ... L18: ='Balance Sheet'!L55 -> 24.09
A19: Share holders fund | B19: ='Balance Sheet'!B56 -> 4229.22 | C19: ='Balance Sheet'!C56 -> 4378.78 | D19: ='Balance Sheet'!D56 -> 3523.57 | E19: ='Balance Sheet'!E56 -> 4753.7548 | F19: ='Balance Sheet'!F56 -> 6125.6305 | G19: ='Balance Sheet'!G56 -> 7646.8301 | H19: ='Balance Sheet'!H56 -> 9256.9071 | I19: ='Balance Sheet'!I56 -> 11019.296 | ... L19: ='Balance Sheet'!L56 -> 17265.323
A21: GROWTH | B21: =B13 -> FY2019 A | C21: =C13 -> FY2020 A | D21: =D13 -> FY2021 A | E21: =E13 -> FY2022 E | F21: =F13 -> FY2023 E | G21: =G13 -> FY2024 E | H21: =H13 -> FY2025 E | I21: =I13 -> FY2026 E | ... L21: =L13 -> FY2029 E
A22: Revenue Growth y-o-y | C22: =Assumptions!C7 -> 0.04930342 | D22: =Assumptions!D7 -> 0.13251142 | E22: =Assumptions!E7 -> 0.09 | F22: =Assumptions!F7 -> 0.09 | G22: =Assumptions!G7 -> 0.09 | H22: =Assumptions!H7 -> 0.09 | I22: =Assumptions!I7 -> 0.09 | J22: =Assumptions!J7 -> 0.09 | ... L22: =Assumptions!L7 -> 0.09
A23: EBIT Growth y-o-y | C23: =('Income Statement'!C25/'Income Statement'!B25)-1 -> 0.053778478 | D23: =('Income Statement'!D25/'Income Statement'!C25)-1 -> 0.39477716 | E23: =('Income Statement'!E25/'Income Statement'!D25)-1 -> -0.050982862 | F23: =('Income Statement'!F25/'Income Statement'!E25)-1 -> 0.12252274 | G23: =('Income Statement'!G25/'Income Statement'!F25)-1 -> 0.1237303 | H23: =('Income Statement'!H25/'Income Statement'!G25)-1 -> 0.059723117 | I23: =('Income Statement'!I25/'Income Statement'!H25)-1 -> 0.10117698 | J23: =('Income Statement'!J25/'Income Statement'!I25)-1 -> 0.094383433 | ... L23: =('Income Statement'!L25/'Income Statement'!K25)-1 -> 0.093288089
A24: PAT growth y-o-y | C24: =('Income Statement'!C35/'Income Statement'!B35)-1 -> 0.20389096 | D24: =('Income Statement'!D35/'Income Statement'!C35)-1 -> 0.32914319 | E24: =('Income Statement'!E35/'Income Statement'!D35)-1 -> -0.03702734 | F24: =('Income Statement'!F35/'Income Statement'!E35)-1 -> 0.11517865 | G24: =('Income Statement'!G35/'Income Statement'!F35)-1 -> 0.10884639 | H24: =('Income Statement'!H35/'Income Statement'!G35)-1 -> 0.058425934 | I24: =('Income Statement'!I35/'Income Statement'!H35)-1 -> 0.094599205 | J24: =('Income Statement'!J35/'Income Statement'!I35)-1 -> 0.088014834 | ... L24: =('Income Statement'!L35/'Income Statement'!K35)-1 -> 0.088519699
A26: MARGINS | B26: =B6 -> FY2019 A | C26: =C6 -> FY2020 A | D26: =D6 -> FY2021 A | E26: =E6 -> FY2022 E | F26: =F6 -> FY2023 E | G26: =G6 -> FY2024 E | H26: =H6 -> FY2025 E | I26: =I6 -> FY2026 E | ... L26: =L6 -> FY2029 E
A27: Gross Profit Margin (%) | B27: ='Income Statement'!B63 -> 0.4064592 | C27: ='Income Statement'!C63 -> 0.40275282 | D27: ='Income Statement'!D63 -> 0.41945798 | E27: ='Income Statement'!E63 -> 0.40955667 | F27: ='Income Statement'!F63 -> 0.41058916 | G27: ='Income Statement'!G63 -> 0.41320127 | H27: ='Income Statement'!H63 -> 0.4111157 | I27: ='Income Statement'!I63 -> 0.41163537 | ... L27: ='Income Statement'!L63 -> 0.41173263
A28: EBITDA Margin (%) | B28: ='Income Statement'!B72 -> 0.15695676 | C28: ='Income Statement'!C72 -> 0.15885249 | D28: ='Income Statement'!D72 -> 0.19107795 | E28: ='Income Statement'!E72 -> 0.1689624 | F28: ='Income Statement'!F72 -> 0.17296428 | G28: ='Income Statement'!G72 -> 0.17766821 | H28: ='Income Statement'!H72 -> 0.1731983 | I28: ='Income Statement'!I72 -> 0.17461026 | ... L28: ='Income Statement'!L72 -> 0.17469723
A29: EBIT Margin (%) | B29: ='Income Statement'!B74 -> 0.14231229 | C29: ='Income Statement'!C74 -> 0.14291922 | D29: ='Income Statement'!D74 -> 0.17601629 | E29: ='Income Statement'!E74 -> 0.15324998 | F29: ='Income Statement'!F74 -> 0.15782256 | G29: ='Income Statement'!G74 -> 0.16270641 | H29: ='Income Statement'!H74 -> 0.15818692 | I29: ='Income Statement'!I74 -> 0.15980899 | ... L29: ='Income Statement'!L74 -> 0.16016459
A30: Pre-Tax Margin (%) | B30: ='Income Statement'!B79 -> 0.1600787 | C30: ='Income Statement'!C79 -> 0.15894905 | D30: ='Income Statement'!D79 -> 0.19141672 | E30: ='Income Statement'!E79 -> 0.16693019 | F30: ='Income Statement'!F79 -> 0.17078622 | G30: ='Income Statement'!G79 -> 0.17448862 | H30: ='Income Statement'!H79 -> 0.16894834 | I30: ='Income Statement'!I79 -> 0.16974233 | ... L30: ='Income Statement'!L79 -> 0.16782096
A31: PAT Margin (%) | B31: ='Income Statement'!B83 -> 0.10467161 | C31: ='Income Statement'!C83 -> 0.12009225 | D31: ='Income Statement'!D83 -> 0.14094321 | E31: ='Income Statement'!E83 -> 0.12451785 | F31: ='Income Statement'!F83 -> 0.12739417 | G31: ='Income Statement'!G83 -> 0.12959685 | H31: ='Income Statement'!H83 -> 0.12584282 | I31: ='Income Statement'!I83 -> 0.1263738 | ... L31: ='Income Statement'!L83 -> 0.12491457
A33: EXPENDITURE RATIOS | B33: =B26 -> FY2019 A | C33: =C26 -> FY2020 A | D33: =D26 -> FY2021 A | E33: =E26 -> FY2022 E | F33: =F26 -> FY2023 E | G33: =G26 -> FY2024 E | H33: =H26 -> FY2025 E | I33: =I26 -> FY2026 E | ... L33: =L26 -> FY2029 E
A34: Cost of Goods Sold as % of Revenue | B34: =ABS('Income Statement'!B62) -> 0.5935408 | C34: =ABS('Income Statement'!C62) -> 0.59724718 | D34: =ABS('Income Statement'!D62) -> 0.58054202 | E34: =ABS('Income Statement'!E62) -> 0.59044333 | F34: =ABS('Income Statement'!F62) -> 0.58941084 | G34: =ABS('Income Statement'!G62) -> 0.58679873 | H34: =ABS('Income Statement'!H62) -> 0.5888843 | I34: =ABS('Income Statement'!I62) -> 0.58836463 | ... L34: =ABS('Income Statement'!L62) -> 0.58826737
A35: Employee Expenses as % of Revenue | B35: ='Income Statement'!B67 -> 0.04640854 | C35: ='Income Statement'!C67 -> 0.043796879 | D35: ='Income Statement'!D67 -> 0.043316078 | E35: ='Income Statement'!E67 -> 0.044507166 | F35: ='Income Statement'!F67 -> 0.043873374 | G35: ='Income Statement'!G67 -> 0.043898873 | H35: ='Income Statement'!H67 -> 0.044093137 | I35: ='Income Statement'!I67 -> 0.043955128 | ... L35: ='Income Statement'!L67 -> 0.043982574
A36: Advertisement Expenses as % of Revenue | B36: ='Income Statement'!B66 -> 0.04532296 | C36: ='Income Statement'!C66 -> 0.040951806 | D36: ='Income Statement'!D66 -> 0.034409257 | E36: ='Income Statement'!E66 -> 0.040228008 | F36: ='Income Statement'!F66 -> 0.03852969 | G36: ='Income Statement'!G66 -> 0.037722318 | H36: ='Income Statement'!H66 -> 0.038826672 | I36: ='Income Statement'!I66 -> 0.03835956 | ... L36: ='Income Statement'!L66 -> 0.038386257
A39: RETURNS | B39: =B6 -> FY2019 A | C39: =C6 -> FY2020 A | D39: =D6 -> FY2021 A | E39: =E6 -> FY2022 E | F39: =F6 -> FY2023 E | G39: =G6 -> FY2024 E | H39: =H6 -> FY2025 E | I39: =I6 -> FY2026 E | ... L39: =L6 -> FY2029 E
A40: Return on Avg Cap Employed (%) | B40: ='Income Statement'!B25/('Balance Sheet'!B33-'Balance Sheet'!B43) -> 0.35830822 | C40: ='Income Statement'!C25/('Balance Sheet'!C33-'Balance Sheet'!C43) -> 0.31414478 | D40: ='Income Statement'!D25/('Balance Sheet'!D33-'Balance Sheet'!D43) -> 0.52614512 | E40: ='Income Statement'!E25/('Balance Sheet'!E33-'Balance Sheet'!E43) -> 0.39020241 | F40: ='Income Statement'!F25/('Balance Sheet'!F33-'Balance Sheet'!F43) -> 0.35211089 | G40: ='Income Statement'!G25/('Balance Sheet'!G33-'Balance Sheet'!G43) -> 0.32500247 | H40: ='Income Statement'!H25/('Balance Sheet'!H33-'Balance Sheet'!H43) -> 0.28965262 | I40: ='Income Statement'!I25/('Balance Sheet'!I33-'Balance Sheet'!I43) -> 0.27167715 | ... L40: ='Income Statement'!L25/('Balance Sheet'!L33-'Balance Sheet'!L43) -> 0.23116627
A41: Return on Assets | B41: ='Income Statement'!B7/('Balance Sheet'!B20) -> 7.1985829 | C41: ='Income Statement'!C7/('Balance Sheet'!C20) -> 6.7578669 | D41: ='Income Statement'!D7/('Balance Sheet'!D20) -> 8.037692 | E41: ='Income Statement'!E7/('Balance Sheet'!E20) -> 8.9117246 | F41: ='Income Statement'!F7/('Balance Sheet'!F20) -> 9.7660565 | G41: ='Income Statement'!G7/('Balance Sheet'!G20) -> 10.688108 | H41: ='Income Statement'!H7/('Balance Sheet'!H20) -> 11.746376 | I41: ='Income Statement'!I7/('Balance Sheet'!I20) -> 12.85429 | ... L41: ='Income Statement'!L7/('Balance Sheet'!L20) -> 16.781466
A42: Return On Equity (%) | B42: ='Income Statement'!B41/'Balance Sheet'!B59 -> 0.27085837 | C42: ='Income Statement'!C41/'Balance Sheet'!C59 -> 0.31498846 | D42: ='Income Statement'!D41/'Balance Sheet'!D59 -> 0.5161635 | E42: ='Income Statement'!E41/'Balance Sheet'!E59 -> 0.37033819 | F42: ='Income Statement'!F41/'Balance Sheet'!F59 -> 0.32140419 | G42: ='Income Statement'!G41/'Balance Sheet'!G59 -> 0.28604679 | H42: ='Income Statement'!H41/'Balance Sheet'!H59 -> 0.25044119 | I42: ='Income Statement'!I41/'Balance Sheet'!I59 -> 0.23052799 | ... L42: ='Income Statement'!L41/'Balance Sheet'!L59 -> 0.18871051
A44: DuPONT ANALYSIS | B44: =B6 -> FY2019 A | C44: =C6 -> FY2020 A | D44: =D6 -> FY2021 A | E44: =E6 -> FY2022 E | F44: =F6 -> FY2023 E | G44: =G6 -> FY2024 E | H44: =H6 -> FY2025 E | I44: =I6 -> FY2026 E | ... L44: =L6 -> FY2029 E
A45: PAT Margin (%) | B45: ='Income Statement'!B83 -> 0.10467161 | C45: ='Income Statement'!C83 -> 0.12009225 | D45: ='Income Statement'!D83 -> 0.14094321 | E45: ='Income Statement'!E83 -> 0.12451785 | F45: ='Income Statement'!F83 -> 0.12739417 | G45: ='Income Statement'!G83 -> 0.12959685 | H45: ='Income Statement'!H83 -> 0.12584282 | I45: ='Income Statement'!I83 -> 0.1263738 | ... L45: ='Income Statement'!L83 -> 0.12491457
A46: Asset Turnover (x) | B46: =B41 -> 7.1985829 | C46: =C41 -> 6.7578669 | D46: =D41 -> 8.037692 | E46: =E41 -> 8.9117246 | F46: =F41 -> 9.7660565 | G46: =G41 -> 10.688108 | H46: =H41 -> 11.746376 | I46: =I41 -> 12.85429 | ... L46: =L41 -> 16.781466
A47: Financial Leverage | B47: ='Balance Sheet'!B51/'Balance Sheet'!B59 -> 0.02437744 | C47: ='Balance Sheet'!C51/'Balance Sheet'!C59 -> 0.18890476 | D47: ='Balance Sheet'!D51/'Balance Sheet'!D59 -> 0.22614676 | E47: ='Balance Sheet'!E51/'Balance Sheet'!E59 -> 0.16835872 | F47: ='Balance Sheet'!F51/'Balance Sheet'!F59 -> 0.131022 | G47: ='Balance Sheet'!G51/'Balance Sheet'!G59 -> 0.10516189 | H47: ='Balance Sheet'!H51/'Balance Sheet'!H59 -> 0.086989447 | I47: ='Balance Sheet'!I51/'Balance Sheet'!I59 -> 0.07315253 | ... L47: ='Balance Sheet'!L51/'Balance Sheet'!L59 -> 0.046780651
A48: Return On Equity (%) | B48: =B42 -> 0.27085837 | C48: =C42 -> 0.31498846 | D48: =D42 -> 0.5161635 | E48: =E42 -> 0.37033819 | F48: =F42 -> 0.32140419 | G48: =G42 -> 0.28604679 | H48: =H42 -> 0.25044119 | I48: =I42 -> 0.23052799 | ... L48: =L42 -> 0.18871051
A50: LIQUIDITY | B50: =B6 -> FY2019 A | C50: =C6 -> FY2020 A | D50: =D6 -> FY2021 A | E50: =E6 -> FY2022 E | F50: =F6 -> FY2023 E | G50: =G6 -> FY2024 E | H50: =H6 -> FY2025 E | I50: =I6 -> FY2026 E | ... L50: =L6 -> FY2029 E
A51: Receivable Days | B51: =365/('Income Statement'!B7/'Balance Sheet'!B11) -> 13.017695 | C51: =365/('Income Statement'!C7/'Balance Sheet'!C11) -> 10.081162 | D51: =365/('Income Statement'!D7/'Balance Sheet'!D11) -> 7.148565 | E51: =365/('Income Statement'!E7/'Balance Sheet'!E11) -> 9.4966268 | F51: =365/('Income Statement'!F7/'Balance Sheet'!F11) -> 8.7112143 | G51: =365/('Income Statement'!G7/'Balance Sheet'!G11) -> 8.3337194 | H51: =365/('Income Statement'!H7/'Balance Sheet'!H11) -> 8.8212062 | I51: =365/('Income Statement'!I7/'Balance Sheet'!I11) -> 8.6169215 | ... L51: =365/('Income Statement'!L7/'Balance Sheet'!L11) -> 8.6252841
A52: Inventory Days | B52: =(ABS('Balance Sheet'!B12/'Income Statement'!B13)*365) -> 43.469547 | C52: =(ABS('Balance Sheet'!C12/'Income Statement'!C13)*365) -> 39.040285 | D52: =(ABS('Balance Sheet'!D12/'Income Statement'!D13)*365) -> 52.241522 | E52: =(ABS('Balance Sheet'!E12/'Income Statement'!E13)*365) -> 44.273229 | F52: =(ABS('Balance Sheet'!F12/'Income Statement'!F13)*365) -> 44.547767 | G52: =(ABS('Balance Sheet'!G12/'Income Statement'!G13)*365) -> 46.745945 | H52: =(ABS('Balance Sheet'!H12/'Income Statement'!H13)*365) -> 45.16232 | I52: =(ABS('Balance Sheet'!I12/'Income Statement'!I13)*365) -> 45.466673 | ... L52: =(ABS('Balance Sheet'!L12/'Income Statement'!L13)*365) -> 45.571812
A53: Payable Days | B53: =365/('Income Statement'!B7/'Balance Sheet'!B37) -> 37.659322 | C53: =365/('Income Statement'!C7/'Balance Sheet'!C37) -> 35.127356 | D53: =365/('Income Statement'!D7/'Balance Sheet'!D37) -> 36.531954 | E53: =365/('Income Statement'!E7/'Balance Sheet'!E37) -> 36.406308 | F53: =365/('Income Statement'!F7/'Balance Sheet'!F37) -> 36.004196 | G53: =365/('Income Statement'!G7/'Balance Sheet'!G37) -> 36.31171 | H53: =365/('Income Statement'!H7/'Balance Sheet'!H37) -> 36.239913 | I53: =365/('Income Statement'!I7/'Balance Sheet'!I37) -> 36.184592 | ... L53: =365/('Income Statement'!L7/'Balance Sheet'!L37) -> 36.217677
A54: Cash Operating Cycle (Days) | B54: =B52+B51-B53 -> 18.82792 | C54: =C52+C51-C53 -> 13.994091 | D54: =D52+D51-D53 -> 22.858133 | E54: =E52+E51-E53 -> 17.363547 | F54: =F52+F51-F53 -> 17.254786 | G54: =G52+G51-G53 -> 18.767955 | H54: =H52+H51-H53 -> 17.743613 | I54: =I52+I51-I53 -> 17.899003 | ... L54: =L52+L51-L53 -> 17.979419
A56: SOLVENCY RATIOS | B56: =B6 -> FY2019 A | C56: =C6 -> FY2020 A | D56: =D6 -> FY2021 A | E56: =E6 -> FY2022 E | F56: =F6 -> FY2023 E | G56: =G6 -> FY2024 E | H56: =H6 -> FY2025 E | I56: =I6 -> FY2026 E | ... L56: =L6 -> FY2029 E
A57: Interest Coverage Ration | B57: =ABS(('Income Statement'!B23)/'Income Statement'!B26) -> 190.86909 | C57: =ABS(('Income Statement'!C23)/'Income Statement'!C26) -> 23.960078 | D57: =ABS(('Income Statement'!D23)/'Income Statement'!D26) -> 22.633003 | E57: =ABS(('Income Statement'!E23)/'Income Statement'!E26) -> 20.480643 | F57: =ABS(('Income Statement'!F23)/'Income Statement'!F26) -> 24.171664 | G57: =ABS(('Income Statement'!G23)/'Income Statement'!G26) -> 26.613388 | H57: =ABS(('Income Statement'!H23)/'Income Statement'!H26) -> 28.059125 | I57: =ABS(('Income Statement'!I23)/'Income Statement'!I26) -> 31.166665 | ... L57: =ABS(('Income Statement'!L23)/'Income Statement'!L26) -> 40.251611
A58: Net Debt/Equity | B58: =B47 -> 0.02437744 | C58: =C47 -> 0.18890476 | D58: =D47 -> 0.22614676 | E58: =E47 -> 0.16835872 | F58: =F47 -> 0.131022 | G58: =G47 -> 0.10516189 | H58: =H47 -> 0.086989447 | I58: =I47 -> 0.07315253 | ... L58: =L47 -> 0.046780651
A60: TURNOVER RATIOS | B60: =B6 -> FY2019 A | C60: =C6 -> FY2020 A | D60: =D6 -> FY2021 A | E60: =E6 -> FY2022 E | F60: =F6 -> FY2023 E | G60: =G6 -> FY2024 E | H60: =H6 -> FY2025 E | I60: =I6 -> FY2026 E | ... L60: =L6 -> FY2029 E
A61: Working Capital Turnover Ratio | B61: ='Income Statement'!B7/'Company Overview'!B16 -> 6.5996788 | C61: ='Income Statement'!C7/'Company Overview'!C16 -> 10.452657 | D61: ='Income Statement'!D7/'Company Overview'!D16 -> 16.309706 | E61: ='Income Statement'!E7/'Company Overview'!E16 -> 6.9812964 | F61: ='Income Statement'!F7/'Company Overview'!F16 -> 4.5657414 | G61: ='Income Statement'!G7/'Company Overview'!G16 -> 3.4492913 | H61: ='Income Statement'!H7/'Company Overview'!H16 -> 2.8352594 | I61: ='Income Statement'!I7/'Company Overview'!I16 -> 2.4374774 | ... L61: ='Income Statement'!L7/'Company Overview'!L16 -> 1.8061933

Sheet Assumptions
A1: =Dashboard!A1 -> [Britannia LTD.]
A2: Assumptions
A5: Particular | B5: FY2019 A | C5: FY2020 A | D5: FY2021 A | E5: FY2022 E | F5: FY2023 E | G5: FY2024 E | H5: FY2025 E | I5: FY2026 E | J5: FY2027 E | K5: FY2028 E | L5: FY2029 E
A6: Income Statement
A7: Revenue Growth | C7: =('Income Statement'!C7/'Income Statement'!B7)-1 -> 0.04930342 | D7: =('Income Statement'!D7/'Income Statement'!C7)-1 -> 0.13251142 | E7: 0.09 | F7: 0.09 | G7: 0.09 | H7: 0.09 | I7: 0.09 | J7: 0.09 | K7: 0.09 | L7: 0.09
A8: COGS | B8: =ABS('Income Statement'!B13/'Income Statement'!B7) -> 0.5935408 | C8: =ABS('Income Statement'!C13/'Income Statement'!C7) -> 0.59724718 | D8: =ABS('Income Statement'!D13/'Income Statement'!D7) -> 0.58054202 | E8: =AVERAGE(B8:D8) -> 0.59044333 | F8: =AVERAGE(C8:E8) -> 0.58941084 | G8: =AVERAGE(D8:F8) -> 0.58679873 | H8: =AVERAGE(E8:G8) -> 0.5888843 | I8: =AVERAGE(F8:H8) -> 0.58836463 | J8: =AVERAGE(G8:I8) -> 0.58801589 | K8: =AVERAGE(H8:J8) -> 0.58842161 | L8: =AVERAGE(I8:K8) -> 0.58826737
A9: ='Income Statement'!A15 -> Employment Benefit Expenses | B9: ='Income Statement'!B15/'Income Statement'!B$7 -> 0.039895061 | C9: ='Income Statement'!C15/'Income Statement'!C$7 -> 0.041986378 | D9: ='Income Statement'!D15/'Income Statement'!D$7 -> 0.040118758 | E9: =AVERAGE(B9:D9) -> 0.040666732 | F9: =AVERAGE(C9:E9) -> 0.040923956 | G9: =AVERAGE(D9:F9) -> 0.040569815 | H9: =AVERAGE(E9:G9) -> 0.040720168 | I9: =AVERAGE(F9:H9) -> 0.04073798 | J9: =AVERAGE(G9:I9) -> 0.040675988 | K9: =AVERAGE(H9:J9) -> 0.040711378 | L9: =AVERAGE(I9:K9) -> 0.040708449
A10: ='Income Statement'!A16 -> Carriage, freight and distribution | B10: ='Income Statement'!B16/'Income Statement'!B$7 -> 0.050027139 | C10: ='Income Statement'!C16/'Income Statement'!C$7 -> 0.051728597 | D10: ='Income Statement'!D16/'Income Statement'!D$7 -> 0.049862972 | E10: =AVERAGE(B10:D10) -> 0.05053957 | F10: =AVERAGE(C10:E10) -> 0.05071038 | G10: =AVERAGE(D10:F10) -> 0.050370974 | H10: =AVERAGE(E10:G10) -> 0.050540308 | I10: =AVERAGE(F10:H10) -> 0.050540554 | J10: =AVERAGE(G10:I10) -> 0.050483945 | K10: =AVERAGE(H10:J10) -> 0.050521602 | L10: =AVERAGE(I10:K10) -> 0.050515367
A11: ='Income Statement'!A17 -> Advertising and sales promotion | B11: ='Income Statement'!B17/'Income Statement'!B$7 -> 0.04532296 | C11: ='Income Statement'!C17/'Income Statement'!C$7 -> 0.040951806 | D11: ='Income Statement'!D17/'Income Statement'!D$7 -> 0.034409257 | E11: =AVERAGE(B11:D11) -> 0.040228008 | F11: =AVERAGE(C11:E11) -> 0.03852969 | G11: =AVERAGE(D11:F11) -> 0.037722318 | H11: =AVERAGE(E11:G11) -> 0.038826672 | I11: =AVERAGE(F11:H11) -> 0.03835956 | J11: =AVERAGE(G11:I11) -> 0.03830285 | K11: =AVERAGE(H11:J11) -> 0.038496361 | L11: =AVERAGE(I11:K11) -> 0.038386257
A12: ='Income Statement'!A18 -> Conversion charges | B12: ='Income Statement'!B18/'Income Statement'!B$7 -> 0.04640854 | C12: ='Income Statement'!C18/'Income Statement'!C$7 -> 0.043796879 | D12: ='Income Statement'!D18/'Income Statement'!D$7 -> 0.043316078 | E12: =AVERAGE(B12:D12) -> 0.044507166 | F12: =AVERAGE(C12:E12) -> 0.043873374 | G12: =AVERAGE(D12:F12) -> 0.043898873 | H12: =AVERAGE(E12:G12) -> 0.044093137 | I12: =AVERAGE(F12:H12) -> 0.043955128 | J12: =AVERAGE(G12:I12) -> 0.043982379 | K12: =AVERAGE(H12:J12) -> 0.044010215 | L12: =AVERAGE(I12:K12) -> 0.043982574
A13: ='Income Statement'!A19 -> Other Expenses | B13: ='Income Statement'!B19/'Income Statement'!B$7 -> 0.067848743 | C13: ='Income Statement'!C19/'Income Statement'!C$7 -> 0.065436676 | D13: ='Income Statement'!D19/'Income Statement'!D$7 -> 0.06067296 | E13: =AVERAGE(B13:D13) -> 0.064652793 | F13: =AVERAGE(C13:E13) -> 0.063587476 | G13: =AVERAGE(D13:F13) -> 0.062971076 | H13: =AVERAGE(E13:G13) -> 0.063737115 | I13: =AVERAGE(F13:H13) -> 0.063431889 | J13: =AVERAGE(G13:I13) -> 0.063380027 | K13: =AVERAGE(H13:J13) -> 0.063516344 | L13: =AVERAGE(I13:K13) -> 0.063442753
A14: Statutory Tax Rate | B14: =('Income Statement'!B32+'Income Statement'!B33)/'Income Statement'!B31 -> -0.34612407 | C14: =('Income Statement'!C32+'Income Statement'!C33)/'Income Statement'!C31 -> -0.24446072 | D14: =('Income Statement'!D32+'Income Statement'!D33)/'Income Statement'!D31 -> -0.26368391 | E14: =AVERAGE(C14:D14) -> -0.25407231 | F14: =AVERAGE(C14:E14) -> -0.25407231 | G14: =AVERAGE(D14:F14) -> -0.25727618 | H14: =AVERAGE(E14:G14) -> -0.25514027 | I14: =AVERAGE(F14:H14) -> -0.25549625 | J14: =AVERAGE(G14:I14) -> -0.2559709 | K14: =AVERAGE(H14:J14) -> -0.25553581 | L14: =AVERAGE(I14:K14) -> -0.25566765
A16: Balance Sheet
A17: Effective Interest Rate | B17: ='Income Statement'!B26/('Balance Sheet'!B38+'Balance Sheet'!B45) *-1 -> 0.06586002 | C17: ='Income Statement'!C26/('Balance Sheet'!C38+'Balance Sheet'!C45) *-1 -> 0.050790925 | D17: ='Income Statement'!D26/('Balance Sheet'!D38+'Balance Sheet'!D45) *-1 -> 0.053134148 | E17: =AVERAGE(B17:D17) -> 0.056595031 | F17: =AVERAGE(C17:E17) -> 0.053506701 | G17: =AVERAGE(D17:F17) -> 0.05441196 | H17: =AVERAGE(E17:G17) -> 0.054837898 | I17: =AVERAGE(F17:H17) -> 0.054252186 | J17: =AVERAGE(G17:I17) -> 0.054500681 | K17: =AVERAGE(H17:J17) -> 0.054530255 | L17: =AVERAGE(I17:K17) -> 0.054427708
A18: Accounts Receivable Turnover | B18: ='Income Statement'!B8/'Balance Sheet'!B11 -> 28.038758 | C18: ='Income Statement'!C8/'Balance Sheet'!C11 -> 36.206143 | D18: ='Income Statement'!D8/'Balance Sheet'!D11 -> 51.059199 | E18: =AVERAGE(B18:D18) -> 38.4347 | F18: =AVERAGE(C18:E18) -> 41.900014 | G18: =AVERAGE(D18:F18) -> 43.797971 | H18: =AVERAGE(E18:G18) -> 41.377561 | I18: =AVERAGE(F18:H18) -> 42.358515 | J18: =AVERAGE(G18:I18) -> 42.511349 | K18: =AVERAGE(H18:J18) -> 42.082475 | L18: =AVERAGE(I18:K18) -> 42.317447
A19: Inventory Turnover | B19: ='Income Statement'!B13/'Balance Sheet'!B12 * -1 -> 8.3966828 | C19: ='Income Statement'!C13/'Balance Sheet'!C12 * -1 -> 9.3493171 | D19: ='Income Statement'!D13/'Balance Sheet'!D12 * -1 -> 6.9867795 | E19: =AVERAGE(B19:D19) -> 8.2442598 | F19: =AVERAGE(C19:E19) -> 8.1934522 | G19: =AVERAGE(D19:F19) -> 7.8081638 | H19: =AVERAGE(E19:G19) -> 8.0819586 | I19: =AVERAGE(F19:H19) -> 8.0278582 | J19: =AVERAGE(G19:I19) -> 7.9726602 | K19: =AVERAGE(H19:J19) -> 8.0274923 | L19: =AVERAGE(I19:K19) -> 8.0093369
A20: Accounts Payable Turnover | B20: ='Income Statement'!B13/'Balance Sheet'!B37 * -1 -> 5.7526896 | C20: ='Income Statement'!C13/'Balance Sheet'!C37 * -1 -> 6.2058534 | D20: ='Income Statement'!D13/'Balance Sheet'!D37 * -1 -> 5.8003423 | E20: =AVERAGE(B20:D20) -> 5.9196284 | F20: =AVERAGE(C20:E20) -> 5.9752747 | G20: =AVERAGE(D20:F20) -> 5.8984151 | H20: =AVERAGE(E20:G20) -> 5.9311061 | I20: =AVERAGE(F20:H20) -> 5.934932 | J20: =AVERAGE(G20:I20) -> 5.9214844 | K20: =AVERAGE(H20:J20) -> 5.9291741 | L20: =AVERAGE(I20:K20) -> 5.9285302
A21: Depreciation as % of Gross Block | B21: =B44/B39 -> 0.08770924 | C21: =C44/C39 -> 0.08187946 | D21: =D44/D39 -> 0.077828987 | E21: =AVERAGE(B21:D21) -> 0.082472562 | F21: =AVERAGE(C21:E21) -> 0.080727003 | G21: =AVERAGE(D21:F21) -> 0.080342851 | H21: =AVERAGE(E21:G21) -> 0.081180805 | I21: =AVERAGE(F21:H21) -> 0.08075022 | J21: =AVERAGE(G21:I21) -> 0.080757959 | K21: =AVERAGE(H21:J21) -> 0.080896328 | L21: =AVERAGE(I21:K21) -> 0.080801502
A22: Ammortisation as a % of Gross Block | B22: =B59/B55 -> 0.045989758 | C22: =C59/C55 -> 0.017880027 | D22: =D59/D55 -> 0.016474465 | E22: =AVERAGE(B22:D22) -> 0.026781417 | F22: =AVERAGE(C22:E22) -> 0.020378636 | G22: =AVERAGE(D22:F22) -> 0.021211506 | H22: =AVERAGE(E22:G22) -> 0.022790519 | I22: =AVERAGE(F22:H22) -> 0.02146022 | J22: =AVERAGE(G22:I22) -> 0.021820749 | K22: =AVERAGE(H22:J22) -> 0.022023829 | L22: =AVERAGE(I22:K22) -> 0.021768266
A23: Revenue / Gross Block (Tangible) | B23: ='Income Statement'!B8/Assumptions!B32 -> 7.2775393 | C23: ='Income Statement'!C8/Assumptions!C32 -> 5.7367684 | D23: ='Income Statement'!D8/Assumptions!D32 -> 5.4018711 | E23: =AVERAGE(B23:D23) -> 6.1387263 | F23: =AVERAGE(C23:E23) -> 5.7591219 | G23: =AVERAGE(D23:F23) -> 5.7665731 | H23: =AVERAGE(E23:G23) -> 5.8881404 | I23: =AVERAGE(F23:H23) -> 5.8046118 | J23: =AVERAGE(G23:I23) -> 5.8197751 | K23: =AVERAGE(H23:J23) -> 5.8375091 | L23: =AVERAGE(I23:K23) -> 5.820632
A24: Revenue / Gross Block (Intangible) | B24: ='Income Statement'!B8/B50 -> 74.257692 | C24: ='Income Statement'!C8/C50 -> 73.537057 | D24: ='Income Statement'!D8/D50 -> 77.266043 | E24: =AVERAGE(B24:D24) -> 75.020264 | F24: =AVERAGE(C24:E24) -> 75.274455 | G24: =AVERAGE(D24:F24) -> 75.853587 | H24: =AVERAGE(E24:G24) -> 75.382769 | I24: =AVERAGE(F24:H24) -> 75.503604 | J24: =AVERAGE(G24:I24) -> 75.579987 | K24: =AVERAGE(H24:J24) -> 75.488786 | L24: =AVERAGE(I24:K24) -> 75.524125
A26: Debt/Equity | B26: ='Balance Sheet'!B45/'Balance Sheet'!B59 -> 0.014447273 | C26: ='Balance Sheet'!C45/'Balance Sheet'!C59 -> 0.17259512 | D26: ='Balance Sheet'!D45/'Balance Sheet'!D59 -> 0.2086356 | E26: =AVERAGE(B26:D26) -> 0.13189267 | F26: =AVERAGE(C26:E26) -> 0.17104113 | G26: =AVERAGE(D26:F26) -> 0.17052313 | H26: =AVERAGE(E26:G26) -> 0.15781898 | I26: =AVERAGE(F26:H26) -> 0.16646108 | J26: =AVERAGE(G26:I26) -> 0.1649344 | K26: =AVERAGE(H26:J26) -> 0.16307148 | L26: =AVERAGE(I26:K26) -> 0.16482232
A27: Other Liabilities turnover | B27: ='Income Statement'!B13/'Balance Sheet'!B39 *-1 -> 18.003951 | C27: ='Income Statement'!C13/'Balance Sheet'!C39 *-1 -> 14.994848 | D27: ='Income Statement'!D13/'Balance Sheet'!D39 *-1 -> 15.35797 | E27: =AVERAGE(B27:D27) -> 16.118923 | F27: =AVERAGE(C27:E27) -> 15.490581 | G27: =AVERAGE(D27:F27) -> 15.655825 | H27: =AVERAGE(E27:G27) -> 15.755109 | I27: =AVERAGE(F27:H27) -> 15.633838 | J27: =AVERAGE(G27:I27) -> 15.681591 | K27: =AVERAGE(H27:J27) -> 15.690179 | L27: =AVERAGE(I27:K27) -> 15.668536
A28: Dividend payout ratio | B28: ='Income Statement'!B51/'Income Statement'!B41 -> -0.30526842 | C28: ='Income Statement'!C51/'Income Statement'!C41 -> -0.3093765 | D28: ='Income Statement'!D51/'Income Statement'!D41 -> -1.5264091 | E28: =0.31*-1 -> -0.31 | F28: =0.31*-1 -> -0.31 | G28: =0.31*-1 -> -0.31 | H28: =0.31*-1 -> -0.31 | I28: =0.31*-1 -> -0.31 | J28: =0.31*-1 -> -0.31 | K28: =0.31*-1 -> -0.31 | L28: =0.31*-1 -> -0.31
A30: ASSET SCHEDULE
A31: Tangible Assets
A32: Gross Assets (Opening) | B32: 1518.92 | C32: 2021.87 | D32: 2431.75 | E32: =D38 -> 2573.84 | F32: =E38 -> 2766.4272 | G32: =F38 -> 2990.1838 | H32: =G38 -> 3233.7634 | I32: =H38 -> 3493.7835 | J32: =I38 -> 3781.2839 | K32: =J38 -> 4093.8428 | L32: =K38 -> 4433.4971
A33: Acquisitions | B33: 493.18 | C33: 320.93 | D33: 111.35 | E33: =('Income Statement'!E8-'Income Statement'!D8)/E23 -> 192.58718 | F33: =('Income Statement'!F8-'Income Statement'!E8)/F23 -> 223.75661 | G33: =('Income Statement'!G8-'Income Statement'!F8)/G23 -> 243.57956 | H33: =('Income Statement'!H8-'Income Statement'!G8)/H23 -> 260.02014 | I33: =('Income Statement'!I8-'Income Statement'!H8)/I23 -> 287.5004 | J33: =('Income Statement'!J8-'Income Statement'!I8)/J23 -> 312.55895 | K33: =('Income Statement'!K8-'Income Statement'!J8)/K23 -> 339.65426 | L33: =('Income Statement'!L8-'Income Statement'!K8)/L23 -> 371.29662
A34: Transitions | C34: 37.87 | E34: 0 | F34: 0 | G34: 0 | H34: 0 | I34: 0 | J34: 0 | K34: 0 | L34: 0
A35: Exchange Difference | B35: 23.42 | C35: 56.47 | D35: 47.28 | E35: 0 | F35: 0 | G35: 0 | H35: 0 | I35: 0 | J35: 0 | K35: 0 | L35: 0
A36: Adjustments | C36: 0 | D36: 2.29 | E36: 0 | F36: 0 | G36: 0 | H36: 0 | I36: 0 | J36: 0 | K36: 0 | L36: 0
A37: Disposal | B37: 13.65 | C37: 5.39 | D37: 18.83 | E37: 0 | F37: 0 | G37: 0 | H37: 0 | I37: 0 | J37: 0 | K37: 0 | L37: 0
A38: Gross Assets (Ending) | B38: =SUM(B32:B36)-B37 -> 2021.87 | C38: =SUM(C32:C36)-C37 -> 2431.75 | D38: =SUM(D32:D36)-D37 -> 2573.84 | E38: =SUM(E32:E36)-E37 -> 2766.4272 | F38: =SUM(F32:F36)-F37 -> 2990.1838 | G38: =SUM(G32:G36)-G37 -> 3233.7634 | H38: =SUM(H32:H36)-H37 -> 3493.7835 | I38: =SUM(I32:I36)-I37 -> 3781.2839 | ... L38: =SUM(L32:L36)-L37 -> 4804.7937
A39: Average Gross Block | B39: =AVERAGE(B32,B38) -> 1770.395 | C39: =AVERAGE(C32,C38) -> 2226.81 | D39: =AVERAGE(D32,D38) -> 2502.795 | E39: =AVERAGE(E32,E38) -> 2670.1336 | F39: =AVERAGE(F32,F38) -> 2878.3055 | G39: =AVERAGE(G32,G38) -> 3111.9736 | H39: =AVERAGE(H32,H38) -> 3363.7734 | I39: =AVERAGE(I32,I38) -> 3637.5337 | ... L39: =AVERAGE(L32,L38) -> 4619.1454
A41: Depreciation
A42: Accumulated Depreciation (Opening) | B42: 324.48 | C42: 486.29 | D42: 715.38 | E42: =D46 -> 939.54 | F42: =E46 -> 1159.7528 | G42: =F46 -> 1392.1097 | H42: =G46 -> 1642.1346 | I42: =H46 -> 1915.2084 | J42: =I46 -> 2208.94 | K42: =J46 -> 2526.9296 | L42: =K46 -> 2871.8449
A43: Accumulated Depreciation On Acquisitions During The Year/exchange difference | B43: 19.33 | C43: 51.53 | D43: 46.36 | E43: 0 | F43: 0 | G43: 0 | H43: 0 | I43: 0 | J43: 0 | K43: 0 | L43: 0
A44: Depreciation For The Year | B44: 155.28 | C44: 182.33 | D44: 194.79 | E44: =E21*E39 -> 220.21276 | F44: =F21*F39 -> 232.35698 | G44: =G21*G39 -> 250.02483 | H44: =H21*H39 -> 273.07384 | I44: =I21*I39 -> 293.73165 | J44: =J21*J39 -> 317.98958 | K44: =K21*K39 -> 344.91524 | L44: =L21*L39 -> 373.23389
A45: Disposal | B45: 12.8 | C45: 4.77 | D45: 16.99 | E45: 0 | F45: 0 | G45: 0 | H45: 0 | I45: 0 | J45: 0 | K45: 0 | L45: 0
A46: Accumulated Depreciation (Ending) | B46: =SUM(B42:B44)-B45 -> 486.29 | C46: =SUM(C42:C44)-C45 -> 715.38 | D46: =SUM(D42:D44)-D45 -> 939.54 | E46: =SUM(E42:E44)-E45 -> 1159.7528 | F46: =SUM(F42:F44)-F45 -> 1392.1097 | G46: =SUM(G42:G44)-G45 -> 1642.1346 | H46: =SUM(H42:H44)-H45 -> 1915.2084 | I46: =SUM(I42:I44)-I45 -> 2208.94 | ... L46: =SUM(L42:L44)-L45 -> 3245.0788
A47: Net Block | B47: =B38-B46 -> 1535.58 | C47: =C38-C46 -> 1716.37 | D47: =D38-D46 -> 1634.3 | E47: =E38-E46 -> 1606.6744 | F47: =F38-F46 -> 1598.0741 | G47: =G38-G46 -> 1591.6288 | H47: =H38-H46 -> 1578.5751 | I47: =I38-I46 -> 1572.3439 | ... L47: =L38-L46 -> 1559.715
A49: Intangible Assets
A50: Gross Assets (Opening) | B50: 148.86 | C50: =B54 -> 157.73 | D50: =C54 -> 170.01 | E50: =D54 -> 169.91 | F50: =E54 -> 185.66894 | G50: =F54 -> 202.78818 | H50: =G54 -> 221.30569 | I50: =H54 -> 241.61584 | J50: =I54 -> 263.71847 | ... L50: =K54 -> 314.05128
A51: Acquisitions | B51: 3.17 | C51: 3.68 | D51: 2.97 | E51: =('Income Statement'!E8-'Income Statement'!D8)/E24 -> 15.758942 | F51: =('Income Statement'!F8-'Income Statement'!E8)/F24 -> 17.119242 | G51: =('Income Statement'!G8-'Income Statement'!F8)/G24 -> 18.517507 | H51: =('Income Statement'!H8-'Income Statement'!G8)/H24 -> 20.310147 | I51: =('Income Statement'!I8-'Income Statement'!H8)/I24 -> 22.10263 | J51: =('Income Statement'!J8-'Income Statement'!I8)/J24 -> 24.067519 | K51: =('Income Statement'!K8-'Income Statement'!J8)/K24 -> 26.26529 | L51: =('Income Statement'!L8-'Income Statement'!K8)/L24 -> 28.61577
A52: Exchange Difference | B52: 5.7 | C52: 8.6 | D52: -3.07 | E52: 0 | F52: 0 | G52: 0 | H52: 0 | I52: 0 | J52: 0 | K52: 0 | L52: 0
A53: Disposal | E53: 0 | F53: 0 | G53: 0 | H53: 0 | I53: 0 | J53: 0 | K53: 0 | L53: 0
A54: Gross Assets (Ending) | B54: =SUM(B50:B53) -> 157.73 | C54: =SUM(C50:C53) -> 170.01 | D54: =SUM(D50:D53) -> 169.91 | E54: =SUM(E50:E52)-E53 -> 185.66894 | F54: =SUM(F50:F52)-F53 -> 202.78818 | G54: =SUM(G50:G52)-G53 -> 221.30569 | H54: =SUM(H50:H52)-H53 -> 241.61584 | I54: =SUM(I50:I52)-I53 -> 263.71847 | J54: =SUM(J50:J52)-J53 -> 287.78599 | K54: =SUM(K50:K52)-K53 -> 314.05128 | L54: =SUM(L50:L52)-L53 -> 342.66705
A55: Average Gross Assets | B55: =AVERAGE(B50,B54) -> 153.295 | C55: =AVERAGE(C50,C54) -> 163.87 | D55: =AVERAGE(D50,D54) -> 169.96 | E55: =AVERAGE(E50,E54) -> 177.78947 | F55: =AVERAGE(F50,F54) -> 194.22856 | G55: =AVERAGE(G50,G54) -> 212.04694 | H55: =AVERAGE(H50,H54) -> 231.46076 | I55: =AVERAGE(I50,I54) -> 252.66715 | ... L55: =AVERAGE(L50,L54) -> 328.35916
A56: Amortization
A57: Accumulated Amortization (Opening) | B57: 12.69 | C57: =B61 -> 19.74 | D57: =C61 -> 22.67 | E57: =D61 -> 25.47 | F57: =E61 -> 30.231454 | G57: =F61 -> 34.189567 | H57: =G61 -> 38.687402 | I57: =H61 -> 43.962513 | J57: =I61 -> 49.384806 | ... L57: =K61 -> 62.029306
A58: Accumulated Amortization On Acquisitions During The Year | E58: 0 | F58: 0 | G58: 0 | H58: 0 | I58: 0 | J58: 0 | K58: 0 | L58: 0
A59: Amortization For The Year | B59: 7.05 | C59: 2.93 | D59: 2.8 | E59: =E22*E55 -> 4.7614539 | F59: =F22*F55 -> 3.9581132 | G59: =G22*G55 -> 4.4978348 | H59: =H22*H55 -> 5.2751111 | I59: =I22*I55 -> 5.4222928 | J59: =J22*J55 -> 6.01712 | K59: =K22*K55 -> 6.6273806 | L59: =L22*L55 -> 7.1478096
A60: Disposal | E60: 0 | F60: 0 | G60: 0 | H60: 0 | I60: 0 | J60: 0 | K60: 0 | L60: 0
A61: Accumulated Depreciation (Ending) | B61: =SUM(B57:B60) -> 19.74 | C61: =SUM(C57:C60) -> 22.67 | D61: =SUM(D57:D60) -> 25.47 | E61: =SUM(E57:E59)-E60 -> 30.231454 | F61: =SUM(F57:F59)-F60 -> 34.189567 | G61: =SUM(G57:G59)-G60 -> 38.687402 | H61: =SUM(H57:H59)-H60 -> 43.962513 | I61: =SUM(I57:I59)-I60 -> 49.384806 | J61: =SUM(J57:J59)-J60 -> 55.401926 | K61: =SUM(K57:K59)-K60 -> 62.029306 | L61: =SUM(L57:L59)-L60 -> 69.177116
A62: Net Block | B62: =B54-B61 -> 137.99 | C62: =C54-C61 -> 147.34 | D62: =D54-D61 -> 144.44 | E62: =E54-E61 -> 155.43749 | F62: =F54-F61 -> 168.59862 | G62: =G54-G61 -> 182.61829 | H62: =H54-H61 -> 197.65332 | I62: =I54-I61 -> 214.33366 | ... L62: =L54-L61 -> 273.48993

Sheet Income Statement
A1: Britannia Limited
A2: INCOME STATEMENTS
A6: Particulars | B6: =Assumptions!B5 -> FY2019 A | C6: =Assumptions!C5 -> FY2020 A | D6: =Assumptions!D5 -> FY2021 A | E6: =Assumptions!E5 -> FY2022 E | F6: =Assumptions!F5 -> FY2023 E | G6: =Assumptions!G5 -> FY2024 E | H6: =Assumptions!H5 -> FY2025 E | I6: =Assumptions!I5 -> FY2026 E | ... L6: =Assumptions!L5 -> FY2029 E
A7: Revenue from Operation | B7: 11054 | C7: 11599 | D7: 13136 | E7: =D7+D7*Assumptions!E7 -> 14318.24 | F7: =E7+E7*Assumptions!F7 -> 15606.882 | G7: =F7+F7*Assumptions!G7 -> 17011.501 | H7: =G7+G7*Assumptions!H7 -> 18542.536 | I7: =H7+H7*Assumptions!I7 -> 20211.364 | J7: =I7+I7*Assumptions!J7 -> 22030.387 | K7: =J7+J7*Assumptions!K7 -> 24013.122 | L7: =K7+K7*Assumptions!L7 -> 26174.303
A8: Total Income | B8: =SUM(B7:B7) -> 11054 | C8: =SUM(C7:C7) -> 11599 | D8: =SUM(D7:D7) -> 13136 | E8: =SUM(E7:E7) -> 14318.24 | F8: =SUM(F7:F7) -> 15606.882 | G8: =SUM(G7:G7) -> 17011.501 | H8: =SUM(H7:H7) -> 18542.536 | I8: =SUM(I7:I7) -> 20211.364 | ... L8: =SUM(L7:L7) -> 26174.303
A9: Cost of materials consumed | B9: -5513 | C9: -5901.16 | D9: -6502 | E9: =E8*Assumptions!E8*-1 -> -8454.1093 | F9: =F8*Assumptions!F8*-1 -> -9198.8653 | G9: =G8*Assumptions!G8*-1 -> -9982.3272 | H9: =H8*Assumptions!H8*-1 -> -10919.408 | I9: =I8*Assumptions!I8*-1 -> -11891.652 | J9: =J8*Assumptions!J8*-1 -> -12954.218 | K9: =K8*Assumptions!K8*-1 -> -14129.84 | L9: =L8*Assumptions!L8*-1 -> -15397.488
A10: Purchase | B10: -1103 | C10: -973.74 | D10: -1161 | E10: 0 | F10: 0 | G10: 0 | H10: 0 | I10: 0 | J10: 0 | K10: 0 | L10: 0
A11: Excise Duty | B11: 0 | C11: 0 | D11: 0
A12: Changes in stock | B12: 55 | C12: -52.57 | D12: 37 | E12: 0 | F12: 0 | G12: 0 | H12: 0 | I12: 0 | J12: 0 | K12: 0 | L12: 0
A13: Cost of Goods Sold | B13: =SUM(B9:B12) -> -6561 | C13: =SUM(C9:C12) -> -6927.47 | D13: =SUM(D9:D12) -> -7626 | E13: =SUM(E9:E12) -> -8454.1093 | F13: =SUM(F9:F12) -> -9198.8653 | G13: =SUM(G9:G12) -> -9982.3272 | H13: =SUM(H9:H12) -> -10919.408 | I13: =SUM(I9:I12) -> -11891.652 | ... L13: =SUM(L9:L12) -> -15397.488
A14: Gross Profit | B14: =B8+B13 -> 4493 | C14: =C8+C13 -> 4671.53 | D14: =D8+D13 -> 5510 | E14: =E8+E13 -> 5864.1307 | F14: =F8+F13 -> 6408.0163 | G14: =G8+G13 -> 7029.1737 | H14: =H8+H13 -> 7623.1276 | I14: =I8+I13 -> 8319.7125 | ... L14: =L8+L13 -> 10776.814
A15: Employment Benefit Expenses | B15: 441 | C15: 487 | D15: 527 | E15: =E$7*Assumptions!E9 -> 582.27603 | F15: =F$7*Assumptions!F9 -> 638.69534 | G15: =G$7*Assumptions!G9 -> 690.15345 | H15: =H$7*Assumptions!H9 -> 755.05518 | I15: =I$7*Assumptions!I9 -> 823.37015 | J15: =J$7*Assumptions!J9 -> 896.10775 | K15: =K$7*Assumptions!K9 -> 977.60729 | L15: =L$7*Assumptions!L9 -> 1065.5153
A16: Carriage, freight and distribution | B16: 553 | C16: 600 | D16: 655 | E16: =E$7*Assumptions!E10 -> 723.63769 | F16: =F$7*Assumptions!F10 -> 791.43089 | G16: =G$7*Assumptions!G10 -> 856.88587 | H16: =H$7*Assumptions!H10 -> 937.14548 | I16: =I$7*Assumptions!I10 -> 1021.4935 | J16: =J$7*Assumptions!J10 -> 1112.1808 | K16: =K$7*Assumptions!K10 -> 1213.1814 | L16: =L$7*Assumptions!L10 -> 1322.2045
A17: Advertising and sales promotion | B17: 501 | C17: 475 | D17: 452 | E17: =E$7*Assumptions!E11 -> 575.99427 | F17: =F$7*Assumptions!F11 -> 601.32831 | G17: =G$7*Assumptions!G11 -> 641.71325 | H17: =H$7*Assumptions!H11 -> 719.94497 | I17: =I$7*Assumptions!I11 -> 775.29905 | J17: =J$7*Assumptions!J11 -> 843.82662 | K17: =K$7*Assumptions!K11 -> 924.41781 | L17: =L$7*Assumptions!L11 -> 1004.7335
A18: Conversion charges | B18: 513 | C18: 508 | D18: 569 | E18: =E$7*Assumptions!E12 -> 637.26428 | F18: =F$7*Assumptions!F12 -> 684.72656 | G18: =G$7*Assumptions!G12 -> 746.78571 | H18: =H$7*Assumptions!H12 -> 817.59859 | I18: =I$7*Assumptions!I12 -> 888.39311 | J18: =J$7*Assumptions!J12 -> 968.94884 | K18: =K$7*Assumptions!K12 -> 1056.8227 | L18: =L$7*Assumptions!L12 -> 1151.2132
A19: Other Expenses | B19: =2317 -SUM(B16:B18) -> 750 | C19: =2342-SUM(C16:C18) -> 759 | D19: =2473-SUM(D16:D18) -> 797 | E19: =E$7*Assumptions!E13 -> 925.7142 | F19: =F$7*Assumptions!F13 -> 992.40221 | G19: =G$7*Assumptions!G13 -> 1071.2325 | H19: =H$7*Assumptions!H13 -> 1181.8478 | I19: =I$7*Assumptions!I13 -> 1282.045 | J19: =J$7*Assumptions!J13 -> 1396.2865 | K19: =K$7*Assumptions!K13 -> 1525.2257 | L19: =L$7*Assumptions!L13 -> 1660.5698
A20: Other Expense 2 | B20: 0 | C20: 0 | D20: 0 | E20: 0 | F20: 0 | G20: 0 | H20: 0 | I20: 0 | J20: 0 | K20: 0 | L20: 0
A21: Other Expense 3 | B21: 0 | C21: 0 | D21: 0 | E21: 0 | F21: 0 | G21: 0 | H21: 0 | I21: 0 | J21: 0 | K21: 0 | L21: 0
A22: Total Expenditure | B22: =SUM(B15:B21) -> 2758 | C22: =SUM(C15:C21) -> 2829 | D22: =SUM(D15:D21) -> 3000 | E22: =SUM(E15:E21) -> 3444.8865 | F22: =SUM(F15:F21) -> 3708.5833 | G22: =SUM(G15:G21) -> 4006.7708 | H22: =SUM(H15:H21) -> 4411.592 | I22: =SUM(I15:I21) -> 4790.6009 | ... L22: =SUM(L15:L21) -> 6204.2363
A23: EBITDA | B23: =B14-B22 -> 1735 | C23: =C14-C22 -> 1842.53 | D23: =D14-D22 -> 2510 | E23: =E14-E22 -> 2419.2442 | F23: =F14-F22 -> 2699.433 | G23: =G14-G22 -> 3022.4029 | H23: =H14-H22 -> 3211.5357 | I23: =I14-I22 -> 3529.1116 | ... L23: =L14-L22 -> 4572.5781
A24: Depreciation & Ammortization | B24: -161.88 | C24: -184.81 | D24: -197.85 | E24: =(Assumptions!E44+Assumptions!E59)*-1 -> -224.97421 | F24: =(Assumptions!F44+Assumptions!F59)*-1 -> -236.31509 | G24: =(Assumptions!G44+Assumptions!G59)*-1 -> -254.52266 | H24: =(Assumptions!H44+Assumptions!H59)*-1 -> -278.34895 | I24: =(Assumptions!I44+Assumptions!I59)*-1 -> -299.15394 | J24: =(Assumptions!J44+Assumptions!J59)*-1 -> -324.0067 | K24: =(Assumptions!K44+Assumptions!K59)*-1 -> -351.54263 | L24: =(Assumptions!L44+Assumptions!L59)*-1 -> -380.3817
A25: EBIT | B25: =B23+B24 -> 1573.12 | C25: =C23+C24 -> 1657.72 | D25: =D23+D24 -> 2312.15 | E25: =E23+E24 -> 2194.27 | F25: =F23+F24 -> 2463.118 | G25: =G23+G24 -> 2767.8803 | H25: =H23+H24 -> 2933.1867 | I25: =I23+I24 -> 3229.9577 | ... L25: =L23+L24 -> 4192.1964
A26: Interest | B26: -9.09 | C26: -76.9 | D26: -110.9 | E26: =Assumptions!E17*('Balance Sheet'!E45+'Balance Sheet'!E38) *-1 -> -118.12345 | F26: =Assumptions!F17*('Balance Sheet'!F45+'Balance Sheet'!F38) *-1 -> -111.67758 | G26: =Assumptions!G17*('Balance Sheet'!G45+'Balance Sheet'!G38) *-1 -> -113.56701 | H26: =Assumptions!H17*('Balance Sheet'!H45+'Balance Sheet'!H38) *-1 -> -114.45601 | I26: =Assumptions!I17*('Balance Sheet'!I45+'Balance Sheet'!I38) *-1 -> -113.23354 | J26: =Assumptions!J17*('Balance Sheet'!J45+'Balance Sheet'!J38) *-1 -> -113.75219 | K26: =Assumptions!K17*('Balance Sheet'!K45+'Balance Sheet'!K38) *-1 -> -113.81391 | L26: =Assumptions!L17*('Balance Sheet'!L45+'Balance Sheet'!L38) *-1 -> -113.59988
A27: Other Income | B27: 206.45 | C27: 279.4 | D27: 313 | E27: =D27 -> 313 | F27: =E27 -> 313 | G27: =F27 -> 313 | H27: =G27 -> 313 | I27: =H27 -> 313 | J27: =I27 -> 313 | K27: =J27 -> 313 | L27: =K27 -> 313
A28: Profit before Prior Period Items and Tax | B28: =B25+B26+B27 -> 1770.48 | C28: =C25+C26+C27 -> 1860.22 | D28: =D25+D26+D27 -> 2514.25 | E28: =E25+E26+E27 -> 2389.1465 | F28: =F25+F26+F27 -> 2664.4404 | G28: =G25+G26+G27 -> 2967.3133 | H28: =H25+H26+H27 -> 3131.7307 | I28: =I25+I26+I27 -> 3429.7242 | ... L28: =L25+L26+L27 -> 4391.5966
A29: Exceptional Items | B29: 0 | C29: -17.01 | D29: -0.61 | E29: 0 | F29: 0 | G29: 0 | H29: 0 | I29: 0 | J29: 0 | K29: 0 | L29: 0
A30: Share of loss/profits of associates | B30: -0.97 | C30: 0.44 | D30: 0.81 | E30: 1 | F30: 1 | G30: 1 | H30: 1 | I30: 1 | J30: 1 | K30: 1 | L30: 1
A31: Profit/Loss before Taxation | B31: =B28+B29+B30 -> 1769.51 | C31: =C28+C29+C30 -> 1843.65 | D31: =D28+D29+D30 -> 2514.45 | E31: =E28+E29+E30 -> 2390.1465 | F31: =F28+F29+F30 -> 2665.4404 | G31: =G28+G29+G30 -> 2968.3133 | H31: =H28+H29+H30 -> 3132.7307 | I31: =I28+I29+I30 -> 3430.7242 | ... L31: =L28+L29+L30 -> 4392.5966
A32: Current Tax | B32: -599.78 | C32: -447.69 | D32: -657.12 | E32: =E31*Assumptions!E14 -> -607.27005 | F32: =F31*Assumptions!F14 -> -677.2146 | G32: =G31*Assumptions!G14 -> -763.67629 | H32: =H31*Assumptions!H14 -> -799.28575 | I32: =I31*Assumptions!I14 -> -876.53716 | J32: =J31*Assumptions!J14 -> -956.06666 | K32: =K31*Assumptions!K14 -> -1031.0028 | L32: =L31*Assumptions!L14 -> -1123.0448
A33: Provision for Deferred tax | B33: -12.69 | C33: -3.01 | D33: -5.9 | E33: 0 | F33: 0 | G33: 0 | H33: 0 | I33: 0 | J33: 0 | K33: 0 | L33: 0
A34: Other Tax | B34: 0 | C34: 0 | D34: 0 | E34: 0 | F34: 0 | G34: 0 | H34: 0 | I34: 0 | J34: 0 | K34: 0 | L34: 0
A35: Profit/Loss after Tax | B35: =SUM(B31:B34) -> 1157.04 | C35: =SUM(C31:C34) -> 1392.95 | D35: =SUM(D31:D34) -> 1851.43 | E35: =E31+E32 -> 1782.8765 | F35: =F31+F32 -> 1988.2258 | G35: =G31+G32 -> 2204.637 | H35: =H31+H32 -> 2333.445 | I35: =I31+I32 -> 2554.187 | J35: =J31+J32 -> 2778.9933 | K35: =K31+K32 -> 3003.6679 | L35: =L31+L32 -> 3269.5517
A36: Other Comprehensive Income
A37: Reassesment of defined benefit | B37: -4.09 | C37: -6.5 | D37: 3.5 | E37: 0 | F37: 0 | G37: 0 | H37: 0 | I37: 0 | J37: 0 | K37: 0 | L37: 0
A38: Income tax related income | B38: 1.43 | C38: 1.57 | D38: -0.92 | E38: 0 | F38: 0 | G38: 0 | H38: 0 | I38: 0 | J38: 0 | K38: 0 | L38: 0
A39: Foreign Currency translation reserve | B39: 6.5 | C39: 10.05 | D39: -4.08 | E39: 0 | F39: 0 | G39: 0 | H39: 0 | I39: 0 | J39: 0 | K39: 0 | L39: 0
A40: Item #4 | B40: 0 | C40: 0 | D40: 0 | E40: 0 | F40: 0 | G40: 0 | H40: 0 | I40: 0 | J40: 0 | K40: 0 | L40: 0
A41: Total Comprehensive Income to common shareholders | B41: =SUM(B37:B40)+B35 -> 1160.88 | C41: =SUM(C37:C40)+C35 -> 1398.07 | D41: =SUM(D37:D40)+D35 -> 1849.93 | E41: =SUM(E37:E40)+E35 -> 1782.8765 | F41: =SUM(F37:F40)+F35 -> 1988.2258 | G41: =SUM(G37:G40)+G35 -> 2204.637 | H41: =SUM(H37:H40)+H35 -> 2333.445 | I41: =SUM(I37:I40)+I35 -> 2554.187 | ... L41: =SUM(L37:L40)+L35 -> 3269.5517
A42: Minority Interests | B42: 3.66 | C42: 9.03 | D42: 13.31 | E42: =D42 -> 13.31 | F42: =E42 -> 13.31 | G42: =F42 -> 13.31 | H42: =G42 -> 13.31 | I42: =H42 -> 13.31 | J42: =I42 -> 13.31 | K42: =J42 -> 13.31 | L42: =K42 -> 13.31
A44: Number of Shares Issued:
A45: Basic | B45: 24.02 | C45: 24.03 | D45: 24.07 | E45: =D45 -> 24.07 | F45: =E45 -> 24.07 | G45: =F45 -> 24.07 | H45: =G45 -> 24.07 | I45: =H45 -> 24.07 | J45: =I45 -> 24.07 | K45: =J45 -> 24.07 | L45: =K45 -> 24.07
A46: Diluted | B46: 24.04 | C46: 24.04 | D46: 24.08 | E46: =D46 -> 24.08 | F46: =E46 -> 24.08 | G46: =F46 -> 24.08 | H46: =G46 -> 24.08 | I46: =H46 -> 24.08 | J46: =I46 -> 24.08 | K46: =J46 -> 24.08 | L46: =K46 -> 24.08
A48: Earnings per share :
A49: Basic | B49: =B41/B45 -> 48.329725 | C49: =C41/C45 -> 58.180191 | D49: =D41/D45 -> 76.856253 | E49: =E41/E45 -> 74.070481 | F49: =F41/F45 -> 82.601819 | G49: =G41/G45 -> 91.592729 | H49: =H41/H45 -> 96.944119 | I49: =I41/I45 -> 106.11496 | ... L49: =L41/L45 -> 135.83514
A50: Diluted | B50: =B41/B46 -> 48.289517 | C50: =C41/C46 -> 58.15599 | D50: =D41/D46 -> 76.824336 | E50: =E41/E46 -> 74.039721 | F50: =F41/F46 -> 82.567516 | G50: =G41/G46 -> 91.554692 | H50: =H41/H46 -> 96.90386 | I50: =I41/I46 -> 106.07089 | ... L50: =L41/L46 -> 135.77873
A51: Dividends | B51: -354.38 | C51: -432.53 | D51: -2823.75 | E51: =E41*Assumptions!E28 -> -552.69171 | F51: =F41*Assumptions!F28 -> -616.34999 | G51: =G41*Assumptions!G28 -> -683.43746 | H51: =H41*Assumptions!H28 -> -723.36794 | I51: =I41*Assumptions!I28 -> -791.79797 | J51: =J41*Assumptions!J28 -> -861.48793 | K51: =K41*Assumptions!K28 -> -931.13706 | L51: =L41*Assumptions!L28 -> -1013.561
A53: Common size Income Statement
A55: =A6 -> Particulars | B55: =B6 -> FY2019 A | C55: =C6 -> FY2020 A | D55: =D6 -> FY2021 A | E55: =E6 -> FY2022 E | F55: =F6 -> FY2023 E | G55: =G6 -> FY2024 E | H55: =H6 -> FY2025 E | ... L55: =L6 -> FY2029 E
A56: =A7 -> Revenue from Operation | B56: =B7/B$7 -> 1 | C56: =C7/C$7 -> 1 | D56: =D7/D$7 -> 1 | E56: =E7/E$7 -> 1 | F56: =F7/F$7 -> 1 | G56: =G7/G$7 -> 1 | H56: =H7/H$7 -> 1 | I56: =I7/I$7 -> 1 | ... L56: =L7/L$7 -> 1
A57: =A8 -> Total Income | B57: =B8/B$7 -> 1 | C57: =C8/C$7 -> 1 | D57: =D8/D$7 -> 1 | E57: =E8/E$7 -> 1 | F57: =F8/F$7 -> 1 | G57: =G8/G$7 -> 1 | H57: =H8/H$7 -> 1 | I57: =I8/I$7 -> 1 | ... L57: =L8/L$7 -> 1
A58: =A9 -> Cost of materials consumed | B58: =B9/B$7 -> -0.49873349 | C58: =C9/C$7 -> -0.50876455 | D58: =D9/D$7 -> -0.49497564 | E58: =E9/E$7 -> -0.59044333 | F58: =F9/F$7 -> -0.58941084 | G58: =G9/G$7 -> -0.58679873 | H58: =H9/H$7 -> -0.5888843 | I58: =I9/I$7 -> -0.58836463 | ... L58: =L9/L$7 -> -0.58826737
A59: =A10 -> Purchase | B59: =B10/B$7 -> -0.099782884 | C59: =C10/C$7 -> -0.083950341 | D59: =D10/D$7 -> -0.088383069 | E59: =E10/E$7 -> 0 | F59: =F10/F$7 -> 0 | G59: =G10/G$7 -> 0 | H59: =H10/H$7 -> 0 | I59: =I10/I$7 -> 0 | ... L59: =L10/L$7 -> 0
A60: =A11 -> Excise Duty | B60: =B11/B$7 -> 0 | C60: =C11/C$7 -> 0 | D60: =D11/D$7 -> 0 | E60: =E11/E$7 -> 0 | F60: =F11/F$7 -> 0 | G60: =G11/G$7 -> 0 | H60: =H11/H$7 -> 0 | I60: =I11/I$7 -> 0 | ... L60: =L11/L$7 -> 0
A61: =A12 -> Changes in stock | B61: =B12/B$7 -> 0.0049755745 | C61: =C12/C$7 -> -0.0045322873 | D61: =D12/D$7 -> 0.002816687 | E61: =E12/E$7 -> 0 | F61: =F12/F$7 -> 0 | G61: =G12/G$7 -> 0 | H61: =H12/H$7 -> 0 | I61: =I12/I$7 -> 0 | ... L61: =L12/L$7 -> 0
A62: =A13 -> Cost of Goods Sold | B62: =B13/B$7 -> -0.5935408 | C62: =C13/C$7 -> -0.59724718 | D62: =D13/D$7 -> -0.58054202 | E62: =E13/E$7 -> -0.59044333 | F62: =F13/F$7 -> -0.58941084 | G62: =G13/G$7 -> -0.58679873 | H62: =H13/H$7 -> -0.5888843 | I62: =I13/I$7 -> -0.58836463 | ... L62: =L13/L$7 -> -0.58826737
A63: =A14 -> Gross Profit | B63: =B14/B$7 -> 0.4064592 | C63: =C14/C$7 -> 0.40275282 | D63: =D14/D$7 -> 0.41945798 | E63: =E14/E$7 -> 0.40955667 | F63: =F14/F$7 -> 0.41058916 | G63: =G14/G$7 -> 0.41320127 | H63: =H14/H$7 -> 0.4111157 | I63: =I14/I$7 -> 0.41163537 | ... L63: =L14/L$7 -> 0.41173263
A64: =A15 -> Employment Benefit Expenses | B64: =B15/B$7 -> 0.039895061 | C64: =C15/C$7 -> 0.041986378 | D64: =D15/D$7 -> 0.040118758 | E64: =E15/E$7 -> 0.040666732 | F64: =F15/F$7 -> 0.040923956 | G64: =G15/G$7 -> 0.040569815 | H64: =H15/H$7 -> 0.040720168 | I64: =I15/I$7 -> 0.04073798 | ... L64: =L15/L$7 -> 0.040708449
A65: =A16 -> Carriage, freight and distribution | B65: =B16/B$7 -> 0.050027139 | C65: =C16/C$7 -> 0.051728597 | D65: =D16/D$7 -> 0.049862972 | E65: =E16/E$7 -> 0.05053957 | F65: =F16/F$7 -> 0.05071038 | G65: =G16/G$7 -> 0.050370974 | H65: =H16/H$7 -> 0.050540308 | I65: =I16/I$7 -> 0.050540554 | ... L65: =L16/L$7 -> 0.050515367
A66: =A17 -> Advertising and sales promotion | B66: =B17/B$7 -> 0.04532296 | C66: =C17/C$7 -> 0.040951806 | D66: =D17/D$7 -> 0.034409257 | E66: =E17/E$7 -> 0.040228008 | F66: =F17/F$7 -> 0.03852969 | G66: =G17/G$7 -> 0.037722318 | H66: =H17/H$7 -> 0.038826672 | I66: =I17/I$7 -> 0.03835956 | ... L66: =L17/L$7 -> 0.038386257
A67: =A18 -> Conversion charges | B67: =B18/B$7 -> 0.04640854 | C67: =C18/C$7 -> 0.043796879 | D67: =D18/D$7 -> 0.043316078 | E67: =E18/E$7 -> 0.044507166 | F67: =F18/F$7 -> 0.043873374 | G67: =G18/G$7 -> 0.043898873 | H67: =H18/H$7 -> 0.044093137 | I67: =I18/I$7 -> 0.043955128 | ... L67: =L18/L$7 -> 0.043982574
... A75: =A26 -> Interest | B75: =B26/B$7 -> -0.00082232676 | C75: =C26/C$7 -> -0.0066298819 | D75: =D26/D$7 -> -0.0084424482 | E75: =E26/E$7 -> -0.0082498583 | F75: =F26/F$7 -> -0.0071556628 | G75: =G26/G$7 -> -0.006675896 | H75: =H26/H$7 -> -0.0061726192 | I75: =I26/I$7 -> -0.0056024687 | ... L75: =L26/L$7 -> -0.0043401301
A76: =A28 -> Profit before Prior Period Items and Tax | B76: =B28/B$7 -> 0.16016646 | C76: =C28/C$7 -> 0.16037762 | D76: =D28/D$7 -> 0.19140149 | E76: =E28/E$7 -> 0.16686035 | F76: =F28/F$7 -> 0.17072215 | G76: =G28/G$7 -> 0.17442983 | H76: =H28/H$7 -> 0.16889441 | I76: =I28/I$7 -> 0.16969286 | ... L76: =L28/L$7 -> 0.16778275
A77: =A29 -> Exceptional Items | B77: =B29/B$7 -> 0 | C77: =C29/C$7 -> -0.0014665057 | D77: =D29/D$7 -> -4.6437272e-05 | E77: =E29/E$7 -> 0 | F77: =F29/F$7 -> 0 | G77: =G29/G$7 -> 0 | H77: =H29/H$7 -> 0 | I77: =I29/I$7 -> 0 | ... L77: =L29/L$7 -> 0
A78: =A30 -> Share of loss/profits of associates | B78: =B30/B$7 -> -8.775104e-05 | C78: =C30/C$7 -> 3.7934305e-05 | D78: =D30/D$7 -> 6.1662607e-05 | E78: =E30/E$7 -> 6.9840986e-05 | F78: =F30/F$7 -> 6.4074299e-05 | G78: =G30/G$7 -> 5.8783761e-05 | H78: =H30/H$7 -> 5.3930056e-05 | I78: =I30/I$7 -> 4.9477115e-05 | ... L78: =L30/L$7 -> 3.8205411e-05
A79: =A31 -> Profit/Loss before Taxation | B79: =B31/B$7 -> 0.1600787 | C79: =C31/C$7 -> 0.15894905 | D79: =D31/D$7 -> 0.19141672 | E79: =E31/E$7 -> 0.16693019 | F79: =F31/F$7 -> 0.17078622 | G79: =G31/G$7 -> 0.17448862 | H79: =H31/H$7 -> 0.16894834 | I79: =I31/I$7 -> 0.16974233 | ... L79: =L31/L$7 -> 0.16782096
A80: =A32 -> Current Tax | B80: =B32/B$7 -> -0.054259092 | C80: =C32/C$7 -> -0.038597293 | D80: =D32/D$7 -> -0.050024361 | E80: =E32/E$7 -> -0.042412339 | F80: =F32/F$7 -> -0.043392051 | G80: =G32/G$7 -> -0.044891764 | H80: =H32/H$7 -> -0.043105525 | I80: =I32/I$7 -> -0.04336853 | ... L80: =L32/L$7 -> -0.04290639
A81: =A33 -> Provision for Deferred tax | B81: =B33/B$7 -> -0.0011480007 | C81: =C33/C$7 -> -0.00025950513 | D81: =D33/D$7 -> -0.00044914738 | E81: =E33/E$7 -> 0 | F81: =F33/F$7 -> 0 | G81: =G33/G$7 -> 0 | H81: =H33/H$7 -> 0 | I81: =I33/I$7 -> 0 | ... L81: =L33/L$7 -> 0
A82: =A34 -> Other Tax | B82: =B34/B$7 -> 0 | C82: =C34/C$7 -> 0 | D82: =D34/D$7 -> 0 | E82: =E34/E$7 -> 0 | F82: =F34/F$7 -> 0 | G82: =G34/G$7 -> 0 | H82: =H34/H$7 -> 0 | I82: =I34/I$7 -> 0 | ... L82: =L34/L$7 -> 0
A83: =A35 -> Profit/Loss after Tax | B83: =B35/B$7 -> 0.10467161 | C83: =C35/C$7 -> 0.12009225 | D83: =D35/D$7 -> 0.14094321 | E83: =E35/E$7 -> 0.12451785 | F83: =F35/F$7 -> 0.12739417 | G83: =G35/G$7 -> 0.12959685 | H83: =H35/H$7 -> 0.12584282 | I83: =I35/I$7 -> 0.1263738 | ... L83: =L35/L$7 -> 0.12491457
A85: =A37 -> Reassesment of defined benefit | B85: =B37/B$7 -> -0.00037000181 | C85: =C37/C$7 -> -0.00056039314 | D85: =D37/D$7 -> 0.00026644336 | E85: =E37/E$7 -> 0 | F85: =F37/F$7 -> 0 | G85: =G37/G$7 -> 0 | H85: =H37/H$7 -> 0 | I85: =I37/I$7 -> 0 | ... L85: =L37/L$7 -> 0
A86: =A38 -> Income tax related income | B86: =B38/B$7 -> 0.00012936494 | C86: =C38/C$7 -> 0.0001353565 | D86: =D38/D$7 -> -7.0036541e-05 | E86: =E38/E$7 -> 0 | F86: =F38/F$7 -> 0 | G86: =G38/G$7 -> 0 | H86: =H38/H$7 -> 0 | I86: =I38/I$7 -> 0 | ... L86: =L38/L$7 -> 0
A87: =A39 -> Foreign Currency translation reserve | B87: =B39/B$7 -> 0.00058802244 | C87: =C39/C$7 -> 0.000866454 | D87: =D39/D$7 -> -0.00031059683 | E87: =E39/E$7 -> 0 | F87: =F39/F$7 -> 0 | G87: =G39/G$7 -> 0 | H87: =H39/H$7 -> 0 | I87: =I39/I$7 -> 0 | ... L87: =L39/L$7 -> 0
A88: =A40 -> Item #4 | B88: =B40/B$7 -> 0 | C88: =C40/C$7 -> 0 | D88: =D40/D$7 -> 0 | E88: =E40/E$7 -> 0 | F88: =F40/F$7 -> 0 | G88: =G40/G$7 -> 0 | H88: =H40/H$7 -> 0 | I88: =I40/I$7 -> 0 | ... L88: =L40/L$7 -> 0
... A90: =A42 -> Minority Interests | B90: =B42/B$7 -> 0.00033110186 | C90: =C42/C$7 -> 0.00077851539 | D90: =D42/D$7 -> 0.001013246 | E90: =E42/E$7 -> 0.00092958352 | F90: =F42/F$7 -> 0.00085282892 | G90: =G42/G$7 -> 0.00078241185 | H90: =H42/H$7 -> 0.00071780904 | I90: =I42/I$7 -> 0.0006585404 | ... L90: =L42/L$7 -> 0.00050851402

Sheet Balance Sheet
A1: =Dashboard!A1 -> [Britannia LTD.]
A2: Balance Sheet
A3: (in INR Crores)
A5: =Assumptions!A5 -> Particular | B5: =Assumptions!B5 -> FY2019 A | C5: =Assumptions!C5 -> FY2020 A | D5: =Assumptions!D5 -> FY2021 A | E5: =Assumptions!E5 -> FY2022 E | F5: =Assumptions!F5 -> FY2023 E | G5: =Assumptions!G5 -> FY2024 E | H5: =Assumptions!H5 -> FY2025 E | ... L5: =Assumptions!L5 -> FY2029 E
A6: Assets
A8: Cash And Cash Equivalents | B8: 60.32 | C8: 81.23 | D8: 142.74 | E8: =CFS!E71 -> 1480.3768 | F8: =CFS!F71 -> 2931.1837 | G8: =CFS!G71 -> 4469.8027 | H8: =CFS!H71 -> 6149.6658 | I8: =CFS!I71 -> 7972.567 | J8: =CFS!J71 -> 9942.2825 | K8: =CFS!K71 -> 12082.604 | L8: =CFS!L71 -> 14405.129
A9: Bank Balance | B9: 49.5 | C9: 41.62 | D9: 68.6 | E9: 68.6 | F9: =E9 -> 68.6 | G9: =F9 -> 68.6 | H9: =G9 -> 68.6 | I9: =H9 -> 68.6 | J9: =I9 -> 68.6 | K9: =J9 -> 68.6 | L9: =K9 -> 68.6
A10: Current Investment | B10: 749.88 | C10: 1008.77 | D10: 1393.25 | E10: =D10 -> 1393.25 | F10: =E10 -> 1393.25 | G10: =F10 -> 1393.25 | H10: =G10 -> 1393.25 | I10: =H10 -> 1393.25 | J10: =I10 -> 1393.25 | K10: =J10 -> 1393.25 | L10: =K10 -> 1393.25
A11: Accounts Receivables | B11: 394.24 | C11: 320.36 | D11: 257.27 | E11: ='Income Statement'!E8/Assumptions!E18 -> 372.5342 | F11: ='Income Statement'!F8/Assumptions!F18 -> 372.47915 | G11: ='Income Statement'!G8/Assumptions!G18 -> 388.40843 | H11: ='Income Statement'!H8/Assumptions!H18 -> 448.13023 | I11: ='Income Statement'!I8/Assumptions!I18 -> 477.14997 | J11: ='Income Statement'!J8/Assumptions!J18 -> 518.22366 | K11: ='Income Statement'!K8/Assumptions!K18 -> 570.62047 | L11: ='Income Statement'!L8/Assumptions!L18 -> 618.52274
A12: Inventories | B12: 781.38 | C12: 740.96 | D12: 1091.49 | E12: ='Income Statement'!E13/Assumptions!E19 * -1 -> 1025.454 | F12: ='Income Statement'!F13/Assumptions!F19 * -1 -> 1122.7093 | G12: ='Income Statement'!G13/Assumptions!G19 * -1 -> 1278.4475 | H12: ='Income Statement'!H13/Assumptions!H19 * -1 -> 1351.0844 | I12: ='Income Statement'!I13/Assumptions!I19 * -1 -> 1481.2982 | J12: ='Income Statement'!J13/Assumptions!J19 * -1 -> 1624.83 | K12: ='Income Statement'!K13/Assumptions!K19 * -1 -> 1760.181 | L12: ='Income Statement'!L13/Assumptions!L19 * -1 -> 1922.4423
A13: Short-Term Loans And Advances | B13: 1203.92 | C13: 1110.11 | D13: 946.56 | E13: =D13 -> 946.56 | F13: =E13 -> 946.56 | G13: =F13 -> 946.56 | H13: =G13 -> 946.56 | I13: =H13 -> 946.56 | J13: =I13 -> 946.56 | K13: =J13 -> 946.56 | L13: =K13 -> 946.56
A14: Other Current Assets | B14: 160.81 | C14: 142.17 | D14: 397.76 | E14: =D14 -> 397.76 | F14: =E14 -> 397.76 | G14: =F14 -> 397.76 | H14: =G14 -> 397.76 | I14: =H14 -> 397.76 | J14: =I14 -> 397.76 | K14: =J14 -> 397.76 | L14: =K14 -> 397.76
A15: Other Financial Assets | B15: 126.29 | C15: 229.75 | D15: 122.01 | E15: =D15 -> 122.01 | F15: =E15 -> 122.01 | G15: =F15 -> 122.01 | H15: =G15 -> 122.01 | I15: =H15 -> 122.01 | J15: =I15 -> 122.01 | K15: =J15 -> 122.01 | L15: =K15 -> 122.01
A16: Other Items 2 | B16: 0 | C16: 0 | D16: 0 | E16: 0 | F16: 0 | G16: 0 | H16: 0 | I16: 0 | J16: 0 | K16: 0 | L16: 0
A17: Other Current Assets 3 | B17: 0 | C17: 0 | D17: 0 | E17: 0 | F17: 0 | G17: 0 | H17: 0 | I17: 0 | J17: 0 | K17: 0 | L17: 0
A18: Total Current Assets | B18: =SUM(B8:B17) -> 3526.34 | C18: =SUM(C8:C17) -> 3674.97 | D18: =SUM(D8:D17) -> 4419.68 | E18: =SUM(E8:E17) -> 5806.545 | F18: =SUM(F8:F17) -> 7354.5522 | G18: =SUM(G8:G17) -> 9064.8385 | H18: =SUM(H8:H17) -> 10877.06 | I18: =SUM(I8:I17) -> 12859.195 | ... L18: =SUM(L8:L17) -> 19874.274
A20: PPE, Net | B20: 1535.58 | C20: 1716.37 | D20: 1634.3 | E20: =Assumptions!E47 -> 1606.6744 | F20: =Assumptions!F47 -> 1598.0741 | G20: =Assumptions!G47 -> 1591.6288 | H20: =Assumptions!H47 -> 1578.5751 | I20: =Assumptions!I47 -> 1572.3439 | J20: =Assumptions!J47 -> 1566.9132 | K20: =Assumptions!K47 -> 1561.6522 | L20: =Assumptions!L47 -> 1559.715
A21: Other Intangible Assets | B21: 7.62 | C21: 8.37 | D21: 8.54 | E21: =Assumptions!E62 -> 155.43749 | F21: =Assumptions!F62 -> 168.59862 | G21: =Assumptions!G62 -> 182.61829 | H21: =Assumptions!H62 -> 197.65332 | I21: =Assumptions!I62 -> 214.33366 | J21: =Assumptions!J62 -> 232.38406 | K21: =Assumptions!K62 -> 252.02197 | L21: =Assumptions!L62 -> 273.48993
A22: Capital Work-In-Progress | B22: 101.24 | C22: 39.55 | D22: 116.52 | E22: =D22 -> 116.52 | F22: =E22 -> 116.52 | G22: =F22 -> 116.52 | H22: =G22 -> 116.52 | I22: =H22 -> 116.52 | J22: =I22 -> 116.52 | K22: =J22 -> 116.52 | L22: =K22 -> 116.52
A23: Investment Property | B23: 14.73 | C23: 14.47 | D23: 14.21 | E23: =D23 -> 14.21 | F23: =E23 -> 14.21 | G23: =F23 -> 14.21 | H23: =G23 -> 14.21 | I23: =H23 -> 14.21 | J23: =I23 -> 14.21 | K23: =J23 -> 14.21 | L23: =K23 -> 14.21
A24: Goodwill on Consolidation | B24: 130.37 | C24: 138.97 | D24: 135.9 | E24: 0 | F24: 0 | G24: 0 | H24: 0 | I24: 0 | J24: 0 | K24: 0 | L24: 0
A25: Long-Term Investments | B25: 725.36 | C25: 1882.98 | D25: 1385.15 | E25: =D25 -> 1385.15 | F25: =E25 -> 1385.15 | G25: =F25 -> 1385.15 | H25: =G25 -> 1385.15 | I25: =H25 -> 1385.15 | J25: =I25 -> 1385.15 | K25: =J25 -> 1385.15 | L25: =K25 -> 1385.15
A26: Deferred Tax Assets (Net) | B26: 13.75 | C26: 19.56 | D26: =9.66+71.84 -> 81.5 | E26: =D26 -> 81.5 | F26: =E26 -> 81.5 | G26: =F26 -> 81.5 | H26: =G26 -> 81.5 | I26: =H26 -> 81.5 | J26: =I26 -> 81.5 | K26: =J26 -> 81.5 | L26: =K26 -> 81.5
A27: Long-Term Loans And Advances | B27: 19.02 | C27: 202.95 | D27: 74.58 | E27: =D27 -> 74.58 | F27: =E27 -> 74.58 | G27: =F27 -> 74.58 | H27: =G27 -> 74.58 | I27: =H27 -> 74.58 | J27: =I27 -> 74.58 | K27: =J27 -> 74.58 | L27: =K27 -> 74.58
A28: Investment In Associates | B28: 1.04 | C28: 1.48 | D28: 2.29 | E28: =D28 -> 2.29 | F28: =E28 -> 2.29 | G28: =F28 -> 2.29 | H28: =G28 -> 2.29 | I28: =H28 -> 2.29 | J28: =I28 -> 2.29 | K28: =J28 -> 2.29 | L28: =K28 -> 2.29
A29: Other Financial Assets | B29: 28.67 | C29: 31.33 | D29: 30.13 | E29: =D29 -> 30.13 | F29: =E29 -> 30.13 | G29: =F29 -> 30.13 | H29: =G29 -> 30.13 | I29: =H29 -> 30.13 | J29: =I29 -> 30.13 | K29: =J29 -> 30.13 | L29: =K29 -> 30.13
A30: Other Non Current Assets | B30: =37.02+101.08 -> 138.1 | C30: =68.77+42.46 -> 111.23 | D30: 105.98 | E30: =D30 -> 105.98 | F30: =E30 -> 105.98 | G30: =F30 -> 105.98 | H30: =G30 -> 105.98 | I30: =H30 -> 105.98 | J30: =I30 -> 105.98 | K30: =J30 -> 105.98 | L30: =K30 -> 105.98
A31: Other items 3 | B31: 0 | C31: 0 | D31: 0
A32: Total Non-Current Assets | B32: =SUM(B20:B31) -> 2715.48 | C32: =SUM(C20:C31) -> 4167.26 | D32: =SUM(D20:D31) -> 3589.1 | E32: =SUM(E20:E31) -> 3572.4719 | F32: =SUM(F20:F31) -> 3577.0327 | G32: =SUM(G20:G31) -> 3584.6071 | H32: =SUM(H20:H31) -> 3586.5884 | I32: =SUM(I20:I31) -> 3597.0375 | ... L32: =SUM(L20:L31) -> 3643.5649
A33: Total Assets | B33: =B18+B32 -> 6241.82 | C33: =C18+C32 -> 7842.23 | D33: =D18+D32 -> 8008.78 | E33: =E18+E32 -> 9379.0169 | F33: =F18+F32 -> 10931.585 | G33: =G18+G32 -> 12649.446 | H33: =H18+H32 -> 14463.649 | I33: =I18+I32 -> 16456.233 | ... L33: =L18+L32 -> 23517.839
A35: LIABILITIES & EQUITY
A37: Accounts Payable | B37: =1.78+1138.73 -> 1140.51 | C37: =8.53+1107.75 -> 1116.28 | D37: =28.44+1286.31 -> 1314.75 | E37: ='Income Statement'!E13/Assumptions!E20 * -1 -> 1428.1487 | F37: ='Income Statement'!F13/Assumptions!F20 * -1 -> 1539.4883 | G37: ='Income Statement'!G13/Assumptions!G20 * -1 -> 1692.3745 | H37: ='Income Statement'!H13/Assumptions!H20 * -1 -> 1841.0408 | I37: ='Income Statement'!I13/Assumptions!I20 * -1 -> 2003.6711 | J37: ='Income Statement'!J13/Assumptions!J20 * -1 -> 2187.6639 | K37: ='Income Statement'!K13/Assumptions!K20 * -1 -> 2383.1042 | L37: ='Income Statement'!L13/Assumptions!L20 * -1 -> 2597.1848
A38: Short-Term Borrowings | B38: 76.1 | C38: 747.99 | D38: 1339.42 | E38: =D38 -> 1339.42 | F38: =E38 -> 1339.42 | G38: =F38 -> 1339.42 | H38: =G38 -> 1339.42 | I38: =H38 -> 1339.42 | J38: =I38 -> 1339.42 | K38: =J38 -> 1339.42 | L38: =K38 -> 1339.42
A39: Other Current Liabilities | B39: =269.2+95.22 -> 364.42 | C39: =311.91+150.08 -> 461.99 | D39: =356.01+140.54 -> 496.55 | E39: ='Income Statement'!E13/Assumptions!E27 *-1 -> 524.4835 | F39: ='Income Statement'!F13/Assumptions!F27 *-1 -> 593.83606 | G39: ='Income Statement'!G13/Assumptions!G27 *-1 -> 637.61108 | H39: ='Income Statement'!H13/Assumptions!H27 *-1 -> 693.07093 | I39: ='Income Statement'!I13/Assumptions!I27 *-1 -> 760.63546 | J39: ='Income Statement'!J13/Assumptions!J27 *-1 -> 826.07803 | K39: ='Income Statement'!K13/Assumptions!K27 *-1 -> 900.5531 | L39: ='Income Statement'!L13/Assumptions!L27 *-1 -> 982.70114
A40: Short-Term Provisions | B40: 196.51 | C40: 191.26 | D40: 387.47 | E40: =D40 -> 387.47 | F40: =E40 -> 387.47 | G40: =F40 -> 387.47 | H40: =G40 -> 387.47 | I40: =H40 -> 387.47 | J40: =I40 -> 387.47 | K40: =J40 -> 387.47 | L40: =K40 -> 387.47
A41: Current tax Liabilities | B41: 73.16 | C41: 47.78 | D41: 76.08 | E41: =D41 -> 76.08 | F41: =E41 -> 76.08 | G41: =F41 -> 76.08 | H41: =G41 -> 76.08 | I41: =H41 -> 76.08 | J41: =I41 -> 76.08 | K41: =J41 -> 76.08 | L41: =K41 -> 76.08
A42: Governmnet Grant | B42: 0.71 | C42: 0 | D42: 0 | E42: =D42 -> 0 | F42: =E42 -> 0 | G42: =F42 -> 0 | H42: =G42 -> 0 | I42: =H42 -> 0 | J42: =I42 -> 0 | K42: =J42 -> 0 | L42: =K42 -> 0
A43: Total Current Liabilities | B43: =SUM(B37:B42) -> 1851.41 | C43: =SUM(C37:C42) -> 2565.3 | D43: =SUM(D37:D42) -> 3614.27 | E43: =SUM(E37:E42) -> 3755.6022 | F43: =SUM(F37:F42) -> 3936.2943 | G43: =SUM(G37:G42) -> 4132.9556 | H43: =SUM(H37:H42) -> 4337.0818 | I43: =SUM(I37:I42) -> 4567.2766 | ... L43: =SUM(L37:L42) -> 5382.8559
A45: Long-Term Debt | B45: 61.92 | C45: 766.06 | D45: 747.75 | E45: =D45 -> 747.75 | F45: =E45 -> 747.75 | G45: =F45 -> 747.75 | H45: =G45 -> 747.75 | I45: =H45 -> 747.75 | J45: =I45 -> 747.75 | K45: =J45 -> 747.75 | L45: =K45 -> 747.75
A46: Deferred Tax Liabilities (Net) | B46: 3.87 | C46: 12.69 | D46: 8.69 | E46: =D46 -> 8.69 | F46: =E46 -> 8.69 | G46: =F46 -> 8.69 | H46: =G46 -> 8.69 | I46: =H46 -> 8.69 | J46: =I46 -> 8.69 | K46: =J46 -> 8.69 | L46: =K46 -> 8.69
A47: Other Long-Term Liabilities | B47: 27.24 | C47: 46.54 | D47: 54.07 | E47: =D47 -> 54.07 | F47: =E47 -> 54.07 | G47: =F47 -> 54.07 | H47: =G47 -> 54.07 | I47: =H47 -> 54.07 | J47: =I47 -> 54.07 | K47: =J47 -> 54.07 | L47: =K47 -> 54.07
A48: Long-Term Provisions | B48: 11.45 | C48: 13.16 | D48: 0 | E48: =D48 -> 0 | F48: =E48 -> 0 | G48: =F48 -> 0 | H48: =G48 -> 0 | I48: =H48 -> 0 | J48: =I48 -> 0 | K48: =J48 -> 0 | L48: =K48 -> 0
A49: Other items | B49: 0 | C49: 0 | D49: 0 | E49: 0 | F49: 0 | G49: 0 | H49: 0 | I49: 0 | J49: 0 | K49: 0 | L49: 0
A50: Other Items | B50: 0 | C50: 0 | D50: 0 | E50: 0 | F50: 0 | G50: 0 | H50: 0 | I50: 0 | J50: 0 | K50: 0 | L50: 0
A51: Total Non-Current Liabilities | B51: =SUM(B45:B50) -> 104.48 | C51: =SUM(C45:C50) -> 838.45 | D51: =SUM(D45:D50) -> 810.51 | E51: =SUM(E45:E50) -> 810.51 | F51: =SUM(F45:F50) -> 810.51 | G51: =SUM(G45:G50) -> 810.51 | H51: =SUM(H45:H50) -> 810.51 | I51: =SUM(I45:I50) -> 810.51 | ... L51: =SUM(L45:L50) -> 810.51
A52: Total Liabilities | B52: =B43+B51 -> 1955.89 | C52: =C43+C51 -> 3403.75 | D52: =D43+D51 -> 4424.78 | E52: =E43+E51 -> 4566.1122 | F52: =F43+F51 -> 4746.8043 | G52: =G43+G51 -> 4943.4656 | H52: =H43+H51 -> 5147.5918 | I52: =I43+I51 -> 5377.7866 | ... L52: =L43+L51 -> 6193.3659
A54: Shareholder'S Equity:
A55: Share Capital | B55: 24.03 | C55: 24.05 | D55: 24.09 | E55: =D55 -> 24.09 | F55: =E55 -> 24.09 | G55: =F55 -> 24.09 | H55: =G55 -> 24.09 | I55: =H55 -> 24.09 | J55: =I55 -> 24.09 | K55: =J55 -> 24.09 | L55: =K55 -> 24.09
A56: Reserves And Surplus | B56: 4229.22 | C56: 4378.78 | D56: 3523.57 | E56: =D56+'Income Statement'!E41+'Income Statement'!E51 -> 4753.7548 | F56: =E56+'Income Statement'!F41+'Income Statement'!F51 -> 6125.6305 | G56: =F56+'Income Statement'!G41+'Income Statement'!G51 -> 7646.8301 | H56: =G56+'Income Statement'!H41+'Income Statement'!H51 -> 9256.9071 | I56: =H56+'Income Statement'!I41+'Income Statement'!I51 -> 11019.296 | J56: =I56+'Income Statement'!J41+'Income Statement'!J51 -> 12936.802 | K56: =J56+'Income Statement'!K41+'Income Statement'!K51 -> 15009.332 | L56: =K56+'Income Statement'!L41+'Income Statement'!L51 -> 17265.323
A57: Total Shareholder'S Equity | B57: =SUM(B55:B56) -> 4253.25 | C57: =SUM(C55:C56) -> 4402.83 | D57: =SUM(D55:D56) -> 3547.66 | E57: =SUM(E55:E56) -> 4777.8448 | F57: =SUM(F55:F56) -> 6149.7205 | G57: =SUM(G55:G56) -> 7670.9201 | H57: =SUM(H55:H56) -> 9280.9971 | I57: =SUM(I55:I56) -> 11043.386 | ... L57: =SUM(L55:L56) -> 17289.413
A58: Minority Interest | B58: 32.68 | C58: 35.65 | D58: 36.34 | E58: =D58 -> 36.34 | F58: =E58 -> 36.34 | G58: =F58 -> 36.34 | H58: =G58 -> 36.34 | I58: =H58 -> 36.34 | J58: =I58 -> 36.34 | K58: =J58 -> 36.34 | L58: =K58 -> 36.34
A59: Total Equity | B59: =B57+B58 -> 4285.93 | C59: =C57+C58 -> 4438.48 | D59: =D57+D58 -> 3584 | E59: =E57+E58 -> 4814.1848 | F59: =F57+F58 -> 6186.0605 | G59: =G57+G58 -> 7707.2601 | H59: =H57+H58 -> 9317.3371 | I59: =I57+I58 -> 11079.726 | ... L59: =L57+L58 -> 17325.753
A60: Total Liabilities And Equity | B60: =B52+B59 -> 6241.82 | C60: =C52+C59 -> 7842.23 | D60: =D52+D59 -> 8008.78 | E60: =E52+E59 -> 9380.2969 | F60: =F52+F59 -> 10932.865 | G60: =G52+G59 -> 12650.726 | H60: =H52+H59 -> 14464.929 | I60: =I52+I59 -> 16457.513 | ... L60: =L52+L59 -> 23519.119
A63: COMMON SIZE BALANCE SHEET
A66: PARTICULARS | B66: =B5 -> FY2019 A | C66: =C5 -> FY2020 A | D66: =D5 -> FY2021 A | E66: =E5 -> FY2022 E | F66: =F5 -> FY2023 E | G66: =G5 -> FY2024 E | H66: =H5 -> FY2025 E | I66: =I5 -> FY2026 E | ... L66: =L5 -> FY2029 E
A67: ASSETS
A68: =A6 -> Assets
A70: =A8 -> Cash And Cash Equivalents | B70: =B8/B$33 -> 0.009663848 | C70: =C8/C$33 -> 0.010358023 | D70: =D8/D$33 -> 0.017822939 | E70: =E8/E$33 -> 0.15783923 | F70: =F8/F$33 -> 0.26813895 | G70: =G8/G$33 -> 0.35335957 | H70: =H8/H$33 -> 0.4251808 | I70: =I8/I$33 -> 0.48447097 | ... L70: =L8/L$33 -> 0.61251925
A71: =A9 -> Bank Balance | B71: =B9/B$33 -> 0.0079303793 | C71: =C9/C$33 -> 0.0053071639 | D71: =D9/D$33 -> 0.0085655993 | E71: =E9/E$33 -> 0.0073141994 | F71: =F9/F$33 -> 0.0062753938 | G71: =G9/G$33 -> 0.0054231626 | H71: =H9/H$33 -> 0.0047429249 | I71: =I9/I$33 -> 0.0041686333 | ... L71: =L9/L$33 -> 0.0029169347
A72: =A10 -> Current Investment | B72: =B10/B$33 -> 0.12013804 | C72: =C10/C$33 -> 0.12863305 | D72: =D10/D$33 -> 0.17396532 | E72: =E10/E$33 -> 0.14854968 | F72: =F10/F$33 -> 0.12745178 | G72: =G10/G$33 -> 0.11014317 | H72: =H10/H$33 -> 0.096327698 | I72: =I10/I$33 -> 0.084663971 | ... L72: =L10/L$33 -> 0.059242263
A73: =A11 -> Accounts Receivables | B73: =B11/B$33 -> 0.063161065 | C73: =C11/C$33 -> 0.040850625 | D73: =D11/D$33 -> 0.032123494 | E73: =E11/E$33 -> 0.039719962 | F73: =F11/F$33 -> 0.034073664 | G73: =G11/G$33 -> 0.030705569 | H73: =H11/H$33 -> 0.030983207 | I73: =I11/I$33 -> 0.028995091 | ... L73: =L11/L$33 -> 0.026300152
A74: =A12 -> Inventories | B74: =B12/B$33 -> 0.12518464 | C74: =C12/C$33 -> 0.094483329 | D74: =D12/D$33 -> 0.13628668 | E74: =E12/E$33 -> 0.10933491 | F74: =F12/F$33 -> 0.10270325 | G74: =G12/G$33 -> 0.10106747 | H74: =H12/H$33 -> 0.093412419 | I74: =I12/I$33 -> 0.090014417 | ... L74: =L12/L$33 -> 0.081744005
A75: =A13 -> Short-Term Loans And Advances | B75: =B13/B$33 -> 0.19287964 | C75: =C13/C$33 -> 0.1415554 | D75: =D13/D$33 -> 0.11819029 | E75: =E13/E$33 -> 0.10092316 | F75: =F13/F$33 -> 0.086589457 | G75: =G13/G$33 -> 0.074830157 | H75: =H13/H$33 -> 0.065444067 | I75: =I13/I$33 -> 0.057519848 | ... L75: =L13/L$33 -> 0.040248596
A76: =A14 -> Other Current Assets | B76: =B14/B$33 -> 0.025763319 | C76: =C14/C$33 -> 0.018128772 | D76: =D14/D$33 -> 0.049665492 | E76: =E14/E$33 -> 0.042409562 | F76: =F14/F$33 -> 0.036386307 | G76: =G14/G$33 -> 0.031444856 | H76: =H14/H$33 -> 0.027500668 | I76: =I14/I$33 -> 0.024170781 | ... L76: =L14/L$33 -> 0.016913119
A77: =A15 -> Other Financial Assets | B77: =B15/B$33 -> 0.020232881 | C77: =C15/C$33 -> 0.029296514 | D77: =D15/D$33 -> 0.01523453 | E77: =E15/E$33 -> 0.013008826 | F77: =F15/F$33 -> 0.011161236 | G77: =G15/G$33 -> 0.009645482 | H77: =H15/H$33 -> 0.0084356307 | I77: =I15/I$33 -> 0.0074142121 | ... L77: =L15/L$33 -> 0.0051879767
A78: =A16 -> Other Items 2 | B78: =B16/B$33 -> 0 | C78: =C16/C$33 -> 0 | D78: =D16/D$33 -> 0 | E78: =E16/E$33 -> 0 | F78: =F16/F$33 -> 0 | G78: =G16/G$33 -> 0 | H78: =H16/H$33 -> 0 | I78: =I16/I$33 -> 0 | ... L78: =L16/L$33 -> 0
A79: =A17 -> Other Current Assets 3 | B79: =B17/B$33 -> 0 | C79: =C17/C$33 -> 0 | D79: =D17/D$33 -> 0 | E79: =E17/E$33 -> 0 | F79: =F17/F$33 -> 0 | G79: =G17/G$33 -> 0 | H79: =H17/H$33 -> 0 | I79: =I17/I$33 -> 0 | ... L79: =L17/L$33 -> 0
A80: =A18 -> Total Current Assets | B80: =B18/B$33 -> 0.56495381 | C80: =C18/C$33 -> 0.46861288 | D80: =D18/D$33 -> 0.55185434 | E80: =E18/E$33 -> 0.61909953 | F80: =F18/F$33 -> 0.67278005 | G80: =G18/G$33 -> 0.71661943 | H80: =H18/H$33 -> 0.75202741 | I80: =I18/I$33 -> 0.78141792 | ... L80: =L18/L$33 -> 0.84507229
A82: =A20 -> PPE, Net | B82: =B20/B$33 -> 0.24601478 | C82: =C20/C$33 -> 0.21886249 | D82: =D20/D$33 -> 0.20406354 | E82: =E20/E$33 -> 0.17130521 | F82: =F20/F$33 -> 0.14618869 | G82: =G20/G$33 -> 0.12582597 | H82: =H20/H$33 -> 0.10914086 | I82: =I20/I$33 -> 0.095547011 | ... L82: =L20/L$33 -> 0.066320505
... A95: =A33 -> Total Assets | B95: =B33/B$33 -> 1 | C95: =C33/C$33 -> 1 | D95: =D33/D$33 -> 1 | E95: =E33/E$33 -> 1 | F95: =F33/F$33 -> 1 | G95: =G33/G$33 -> 1 | H95: =H33/H$33 -> 1 | I95: =I33/I$33 -> 1 | ... L95: =L33/L$33 -> 1
A97: =A35 -> LIABILITIES & EQUITY
A99: =A37 -> Accounts Payable | B99: =B37/B$60 -> 0.18272074 | C99: =C37/C$60 -> 0.14234217 | D99: =D37/D$60 -> 0.16416358 | E99: =E37/E$60 -> 0.15224983 | F99: =F37/F$60 -> 0.14081289 | G99: =G37/G$60 -> 0.13377687 | H99: =H37/H$60 -> 0.12727618 | I99: =I37/I$60 -> 0.12174811 | ... L99: =L37/L$60 -> 0.11042866
A100: =A38 -> Short-Term Borrowings | B100: =B38/B$60 -> 0.012191957 | C100: =C38/C$60 -> 0.095379758 | D100: =D38/D$60 -> 0.16724395 | E100: =E38/E$60 -> 0.14279079 | F100: =F38/F$60 -> 0.12251318 | G100: =G38/G$60 -> 0.10587693 | H100: =H38/H$60 -> 0.092597759 | I100: =I38/I$60 -> 0.081386539 | ... L100: =L38/L$60 -> 0.056950262
A101: =A39 -> Other Current Liabilities | B101: =B39/B$60 -> 0.058383612 | C101: =C39/C$60 -> 0.058910539 | D101: =D39/D$60 -> 0.062000704 | E101: =E39/E$60 -> 0.055913316 | F101: =F39/F$60 -> 0.054316601 | G101: =G39/G$60 -> 0.050401147 | H101: =H39/H$60 -> 0.047913885 | I101: =I39/I$60 -> 0.04621813 | ... L101: =L39/L$60 -> 0.041783076
A102: =A40 -> Short-Term Provisions | B102: =B40/B$60 -> 0.031482805 | C102: =C40/C$60 -> 0.024388471 | D102: =D40/D$60 -> 0.048380652 | E102: =E40/E$60 -> 0.041306795 | F102: =F40/F$60 -> 0.035440848 | G102: =G40/G$60 -> 0.030628283 | H102: =H40/H$60 -> 0.026786858 | I102: =I40/I$60 -> 0.023543655 | ... L102: =L40/L$60 -> 0.016474682
A103: =A41 -> Current tax Liabilities | B103: =B41/B$60 -> 0.01172094 | C103: =C41/C$60 -> 0.0060926548 | D103: =D41/D$60 -> 0.0094995742 | E103: =E41/E$60 -> 0.0081106175 | F103: =F41/F$60 -> 0.0069588348 | G103: =G41/G$60 -> 0.0060138843 | H103: =H41/H$60 -> 0.005259618 | I103: =I41/I$60 -> 0.0046228128 | ... L103: =L41/L$60 -> 0.003234815
A104: =A42 -> Governmnet Grant | B104: =B42/B$60 -> 0.00011374887 | C104: =C42/C$60 -> 0 | D104: =D42/D$60 -> 0 | E104: =E42/E$60 -> 0 | F104: =F42/F$60 -> 0 | G104: =G42/G$60 -> 0 | H104: =H42/H$60 -> 0 | I104: =I42/I$60 -> 0 | ... L104: =L42/L$60 -> 0
A105: =A43 -> Total Current Liabilities | B105: =B43/B$60 -> 0.29661381 | C105: =C43/C$60 -> 0.32711359 | D105: =D43/D$60 -> 0.45128846 | E105: =E43/E$60 -> 0.40037135 | F105: =F43/F$60 -> 0.36004235 | G105: =G43/G$60 -> 0.32669711 | H105: =H43/H$60 -> 0.2998343 | I105: =I43/I$60 -> 0.27751925 | ... L105: =L43/L$60 -> 0.2288715
A107: =A45 -> Long-Term Debt | B107: =B45/B$60 -> 0.0099201835 | C107: =C45/C$60 -> 0.09768395 | D107: =D45/D$60 -> 0.093366281 | E107: =E45/E$60 -> 0.079714961 | F107: =F45/F$60 -> 0.068394699 | G107: =G45/G$60 -> 0.059107281 | H107: =H45/H$60 -> 0.051693998 | I107: =I45/I$60 -> 0.045435177 | ... L107: =L45/L$60 -> 0.031793283
A108: =A46 -> Deferred Tax Liabilities (Net) | B108: =B46/B$60 -> 0.00062001147 | C108: =C46/C$60 -> 0.0016181622 | D108: =D46/D$60 -> 0.0010850591 | E108: =E46/E$60 -> 0.00092640991 | F108: =F46/F$60 -> 0.00079485113 | G108: =G46/G$60 -> 0.00068691712 | H108: =H46/H$60 -> 0.00060076341 | I108: =I46/I$60 -> 0.00052802633 | ... L108: =L46/L$60 -> 0.00036948663
A109: =A47 -> Other Long-Term Liabilities | B109: =B47/B$60 -> 0.0043641117 | C109: =C47/C$60 -> 0.0059345365 | D109: =D47/D$60 -> 0.0067513404 | E109: =E47/E$60 -> 0.0057642099 | F109: =F47/F$60 -> 0.0049456387 | G109: =G47/G$60 -> 0.0042740631 | H109: =H47/H$60 -> 0.0037380066 | I109: =I47/I$60 -> 0.0032854296 | ... L109: =L47/L$60 -> 0.0022989807
A110: =A48 -> Long-Term Provisions | B110: =B48/B$60 -> 0.0018344009 | C110: =C48/C$60 -> 0.0016780941 | D110: =D48/D$60 -> 0 | E110: =E48/E$60 -> 0 | F110: =F48/F$60 -> 0 | G110: =G48/G$60 -> 0 | H110: =H48/H$60 -> 0 | I110: =I48/I$60 -> 0 | ... L110: =L48/L$60 -> 0
A111: =A49 -> Other items | B111: =B49/B$60 -> 0 | C111: =C49/C$60 -> 0 | D111: =D49/D$60 -> 0 | E111: =E49/E$60 -> 0 | F111: =F49/F$60 -> 0 | G111: =G49/G$60 -> 0 | H111: =H49/H$60 -> 0 | I111: =I49/I$60 -> 0 | ... L111: =L49/L$60 -> 0
... A114: =A52 -> Total Liabilities | B114: =B52/B$60 -> 0.31335252 | C114: =C52/C$60 -> 0.43402833 | D114: =D52/D$60 -> 0.55249114 | E114: =E52/E$60 -> 0.48677693 | F114: =F52/F$60 -> 0.43417754 | G114: =G52/G$60 -> 0.39076538 | H114: =H52/H$60 -> 0.35586706 | I114: =I52/I$60 -> 0.32676788 | ... L114: =L52/L$60 -> 0.26333325
A116: =A54 -> Shareholder'S Equity:
A117: =A55 -> Share Capital | B117: =B55/B$60 -> 0.0038498387 | C117: =C55/C$60 -> 0.0030667297 | D117: =D55/D$60 -> 0.0030079488 | E117: =E55/E$60 -> 0.002568149 | F117: =F55/F$60 -> 0.0022034481 | G117: =G55/G$60 -> 0.0019042386 | H117: =H55/H$60 -> 0.0016654074 | I117: =I55/I$60 -> 0.0014637692 | ... L117: =L55/L$60 -> 0.0010242731
A118: =A56 -> Reserves And Surplus | B118: =B56/B$60 -> 0.67756199 | C118: =C56/C$60 -> 0.55835904 | D118: =D56/D$60 -> 0.43996339 | E118: =E56/E$60 -> 0.50678084 | F118: =F56/F$60 -> 0.56029509 | G118: =G56/G$60 -> 0.60445782 | H118: =H56/H$60 -> 0.63995525 | I118: =I56/I$60 -> 0.66956024 | ... L118: =L56/L$60 -> 0.73409736
A119: =A57 -> Total Shareholder'S Equity | B119: =B57/B$60 -> 0.68141183 | C119: =C57/C$60 -> 0.56142577 | D119: =D57/D$60 -> 0.44297134 | E119: =E57/E$60 -> 0.50934899 | F119: =F57/F$60 -> 0.56249854 | G119: =G57/G$60 -> 0.60636206 | H119: =H57/H$60 -> 0.64162065 | I119: =I57/I$60 -> 0.67102401 | ... L119: =L57/L$60 -> 0.73512163
A120: =A58 -> Minority Interest | B120: =B58/B$60 -> 0.0052356524 | C120: =C58/C$60 -> 0.0045459008 | D120: =D58/D$60 -> 0.0045375201 | E120: =E58/E$60 -> 0.0038740778 | F120: =F58/F$60 -> 0.0033239229 | G120: =G58/G$60 -> 0.0028725625 | H120: =H58/H$60 -> 0.0025122834 | I120: =I58/I$60 -> 0.0022081101 | ... L120: =L58/L$60 -> 0.0015451259
A121: =A59 -> Total Equity | B121: =B59/B$60 -> 0.68664748 | C121: =C59/C$60 -> 0.56597167 | D121: =D59/D$60 -> 0.44750886 | E121: =E59/E$60 -> 0.51322307 | F121: =F59/F$60 -> 0.56582246 | G121: =G59/G$60 -> 0.60923462 | H121: =H59/H$60 -> 0.64413294 | I121: =I59/I$60 -> 0.67323212 | ... L121: =L59/L$60 -> 0.73666675
A122: =A60 -> Total Liabilities And Equity | B122: =B60/B$60 -> 1 | C122: =C60/C$60 -> 1 | D122: =D60/D$60 -> 1 | E122: =E60/E$60 -> 1 | F122: =F60/F$60 -> 1 | G122: =G60/G$60 -> 1 | H122: =H60/H$60 -> 1 | I122: =I60/I$60 -> 1 | ... L122: =L60/L$60 -> 1

Sheet CFS
A1: =Dashboard!A1 -> [Britannia LTD.]
A2: Cash Flow Statement
A3: (in INR Crores, unless otherwise stated)
A5: =Assumptions!A5 -> Particular | B5: =Assumptions!B5 -> FY2019 A | C5: =Assumptions!C5 -> FY2020 A | D5: =Assumptions!D5 -> FY2021 A | E5: =Assumptions!E5 -> FY2022 E | F5: =Assumptions!F5 -> FY2023 E | G5: =Assumptions!G5 -> FY2024 E | H5: =Assumptions!H5 -> FY2025 E | ... L5: =Assumptions!L5 -> FY2029 E
A6: Cash Flows From Operating Activities:
A7: Profit For The Year | B7: 1768.9 | C7: 1843.86 | D7: 2512.8 | E7: ='Income Statement'!E31 -> 2390.1465 | F7: ='Income Statement'!F31 -> 2665.4404 | G7: ='Income Statement'!G31 -> 2968.3133 | H7: ='Income Statement'!H31 -> 3132.7307 | I7: ='Income Statement'!I31 -> 3430.7242 | J7: ='Income Statement'!J31 -> 3735.06 | K7: ='Income Statement'!K31 -> 4034.6708 | L7: ='Income Statement'!L31 -> 4392.5966
A8: Adjustments To Reconcile Net Income To Cash Provided By Operating Activities | B8: 0 | C8: 0 | D8: 0
A9: Depreciation & Amortization | B9: 161.88 | C9: 184.81 | D9: 197.85 | E9: ='Income Statement'!E24*-1 -> 224.97421 | F9: ='Income Statement'!F24*-1 -> 236.31509 | G9: ='Income Statement'!G24*-1 -> 254.52266 | H9: ='Income Statement'!H24*-1 -> 278.34895 | I9: ='Income Statement'!I24*-1 -> 299.15394 | J9: ='Income Statement'!J24*-1 -> 324.0067 | K9: ='Income Statement'!K24*-1 -> 351.54263 | L9: ='Income Statement'!L24*-1 -> 380.3817
A10: Profit On Sale Of Assets (Including Assets Scrapped / Written Off) | B10: -0.97 | C10: -0.11 | D10: -0.33 | E10: 0 | F10: 0 | G10: 0 | H10: 0 | I10: 0 | J10: 0 | K10: 0 | L10: 0
A11: Profit On Sale Of Investments (Net) | B11: 0 | C11: 0 | D11: 0 | E11: 0 | F11: 0 | G11: 0 | H11: 0 | I11: 0 | J11: 0 | K11: 0 | L11: 0
A12: Provision For Doubtful Trade Receivables And Advances | B12: 0 | C12: 0 | D12: 0 | E12: 0 | F12: 0 | G12: 0 | H12: 0 | I12: 0 | J12: 0 | K12: 0 | L12: 0
A13: Share Of (Profit) / Loss Of Associate Companies (Net) | B13: 0 | C13: 0 | D13: 0 | E13: 0 | F13: 0 | G13: 0 | H13: 0 | I13: 0 | J13: 0 | K13: 0 | L13: 0
A14: Share Of Minority Interest | B14: 0 | C14: 0 | D14: 0 | E14: 0 | F14: 0 | G14: 0 | H14: 0 | I14: 0 | J14: 0 | K14: 0 | L14: 0
A15: Interest / Dividend (Net) | B15: -136.77 | C15: -176.77 | D15: -234.66 | E15: =-'Income Statement'!E27 -> -313 | F15: =-'Income Statement'!F27 -> -313 | G15: =-'Income Statement'!G27 -> -313 | H15: =-'Income Statement'!H27 -> -313 | I15: =-'Income Statement'!I27 -> -313 | J15: =-'Income Statement'!J27 -> -313 | K15: =-'Income Statement'!K27 -> -313 | L15: =-'Income Statement'!L27 -> -313
A16: Esop expense | B16: 0 | C16: 0 | D16: 0 | E16: 0 | F16: 0 | G16: 0 | H16: 0 | I16: 0 | J16: 0 | K16: 0 | L16: 0
A17: Net gain on financial asset measured | B17: -63.85 | C17: -89.88 | D17: -65.47 | E17: 0 | F17: 0 | G17: 0 | H17: 0 | I17: 0 | J17: 0 | K17: 0 | L17: 0
A18: Interest Income | B18: 0 | C18: 0 | D18: 0 | E18: 0 | F18: 0 | G18: 0 | H18: 0 | I18: 0 | J18: 0 | K18: 0 | L18: 0
A19: Finance cost | B19: 9.09 | C19: 76.9 | D19: 110.9 | E19: ='Income Statement'!E26*-1 -> 118.12345 | F19: ='Income Statement'!F26*-1 -> 111.67758 | G19: ='Income Statement'!G26*-1 -> 113.56701 | H19: ='Income Statement'!H26*-1 -> 114.45601 | I19: ='Income Statement'!I26*-1 -> 113.23354 | J19: ='Income Statement'!J26*-1 -> 113.75219 | K19: ='Income Statement'!K26*-1 -> 113.81391 | L19: ='Income Statement'!L26*-1 -> 113.59988
A20: Share Based Payment | B20: 16.12 | C20: 21.58 | D20: 18.94 | E20: 0 | F20: 0 | G20: 0 | H20: 0 | I20: 0 | J20: 0 | K20: 0 | L20: 0
A21: Other Adjustments 6 | B21: 0 | C21: 0 | D21: 0 | E21: 0 | F21: 0 | G21: 0 | H21: 0 | I21: 0 | J21: 0 | K21: 0 | L21: 0
A22: Adjustment for working capital | B22: 0 | C22: 0 | D22: 0
A23: Increase In Inventories | B23: -127.21 | C23: 42.99 | D23: -351.44 | E23: ='Balance Sheet'!D12-'Balance Sheet'!E12 -> 66.035983 | F23: ='Balance Sheet'!E12-'Balance Sheet'!F12 -> -97.255322 | G23: ='Balance Sheet'!F12-'Balance Sheet'!G12 -> -155.73812 | H23: ='Balance Sheet'!G12-'Balance Sheet'!H12 -> -72.636971 | I23: ='Balance Sheet'!H12-'Balance Sheet'!I12 -> -130.21376 | J23: ='Balance Sheet'!I12-'Balance Sheet'!J12 -> -143.53183 | K23: ='Balance Sheet'!J12-'Balance Sheet'!K12 -> -135.35102 | L23: ='Balance Sheet'!K12-'Balance Sheet'!L12 -> -162.26131
A24: (Increase) Decrease In Accounts Receivable | B24: -86.67 | C24: 78.85 | D24: 61.4 | E24: ='Balance Sheet'!D11-'Balance Sheet'!E11 -> -115.2642 | F24: ='Balance Sheet'!E11-'Balance Sheet'!F11 -> 0.055043801 | G24: ='Balance Sheet'!F11-'Balance Sheet'!G11 -> -15.929276 | H24: ='Balance Sheet'!G11-'Balance Sheet'!H11 -> -59.7218 | I24: ='Balance Sheet'!H11-'Balance Sheet'!I11 -> -29.019741 | J24: ='Balance Sheet'!I11-'Balance Sheet'!J11 -> -41.073693 | K24: ='Balance Sheet'!J11-'Balance Sheet'!K11 -> -52.396809 | L24: ='Balance Sheet'!K11-'Balance Sheet'!L11 -> -47.902265
A25: (Increase) Decrease In Finance Receivable | B25: 0 | C25: 0 | D25: 0 | E25: 0 | F25: 0 | G25: 0 | H25: 0 | I25: 0 | J25: 0 | K25: 0 | L25: 0
A26: Other Current And Non-Current Assets | B26: 10.9 | C26: -23.66 | D26: -170.82 | E26: ='Balance Sheet'!D14-'Balance Sheet'!E14 -> 0 | F26: ='Balance Sheet'!E14-'Balance Sheet'!F14 -> 0 | G26: ='Balance Sheet'!F14-'Balance Sheet'!G14 -> 0 | H26: ='Balance Sheet'!G14-'Balance Sheet'!H14 -> 0 | I26: ='Balance Sheet'!H14-'Balance Sheet'!I14 -> 0 | J26: ='Balance Sheet'!I14-'Balance Sheet'!J14 -> 0 | K26: ='Balance Sheet'!J14-'Balance Sheet'!K14 -> 0 | L26: ='Balance Sheet'!K14-'Balance Sheet'!L14 -> 0
A27: Trade Payables | B27: 0 | C27: 0 | D27: 0 | E27: ='Balance Sheet'!E37-'Balance Sheet'!D37 -> 113.39865 | F27: ='Balance Sheet'!F37-'Balance Sheet'!E37 -> 111.33961 | G27: ='Balance Sheet'!G37-'Balance Sheet'!F37 -> 152.88621 | H27: ='Balance Sheet'!H37-'Balance Sheet'!G37 -> 148.66635 | I27: ='Balance Sheet'!I37-'Balance Sheet'!H37 -> 162.6303 | J27: ='Balance Sheet'!J37-'Balance Sheet'!I37 -> 183.99277 | K27: ='Balance Sheet'!K37-'Balance Sheet'!J37 -> 195.4403 | L27: ='Balance Sheet'!L37-'Balance Sheet'!K37 -> 214.0806
A28: Other Current And Non-Current Liabilities | B28: 200.49 | C28: 29.21 | D28: 404.71 | E28: ='Balance Sheet'!E39-'Balance Sheet'!D39 -> 27.933503 | F28: ='Balance Sheet'!F39-'Balance Sheet'!E39 -> 69.352553 | G28: ='Balance Sheet'!G39-'Balance Sheet'!F39 -> 43.775022 | H28: ='Balance Sheet'!H39-'Balance Sheet'!G39 -> 55.459854 | I28: ='Balance Sheet'!I39-'Balance Sheet'!H39 -> 67.564533 | J28: ='Balance Sheet'!J39-'Balance Sheet'!I39 -> 65.442565 | K28: ='Balance Sheet'!K39-'Balance Sheet'!J39 -> 74.475069 | L28: ='Balance Sheet'!L39-'Balance Sheet'!K39 -> 82.148045
A29: Provisions | B29: 0 | C29: 0 | D29: 0 | E29: 0 | F29: 0 | G29: 0 | H29: 0 | I29: 0 | J29: 0 | K29: 0 | L29: 0
A30: Cash Provided By Operating Activities | B30: =SUM(B7:B29) -> 1751.91 | C30: =SUM(C7:C29) -> 1987.78 | D30: =SUM(D7:D29) -> 2483.88 | E30: =SUM(E7:E29) -> 2512.3481 | F30: =SUM(F7:F29) -> 2783.9249 | G30: =SUM(G7:G29) -> 3048.3968 | H30: =SUM(H7:H29) -> 3284.3031 | I30: =SUM(I7:I29) -> 3601.073 | ... L30: =SUM(L7:L29) -> 4659.6432
A31: Income Taxes Paid (Net) | B31: -596.13 | C31: -503.25 | D31: -632.81 | E31: ='Income Statement'!E32 -> -607.27005 | F31: ='Income Statement'!F32 -> -677.2146 | G31: ='Income Statement'!G32 -> -763.67629 | H31: ='Income Statement'!H32 -> -799.28575 | I31: ='Income Statement'!I32 -> -876.53716 | J31: ='Income Statement'!J32 -> -956.06666 | K31: ='Income Statement'!K32 -> -1031.0028 | L31: ='Income Statement'!L32 -> -1123.0448
A32: Net Cash Flow From Operating Activities | B32: =B30+B31 -> 1155.78 | C32: =C30+C31 -> 1484.53 | D32: =D30+D31 -> 1851.07 | E32: =E30+E31 -> 1905.0781 | F32: =F30+F31 -> 2106.7103 | G32: =G30+G31 -> 2284.7205 | H32: =H30+H31 -> 2485.0173 | I32: =I30+I31 -> 2724.5358 | ... L32: =L30+L31 -> 3536.5984
B33: 0 | C33: 0 | D33: 0
A34: Cash Flows From Investing Activities: | B34: 0 | C34: 0 | D34: 0
A35: Payments For Fixed Assets | B35: -401.21 | C35: -244.17 | D35: -242.07 | E35: =(Assumptions!E33+Assumptions!E51)*-1 -> -208.34613 | F35: =(Assumptions!F33+Assumptions!F51)*-1 -> -240.87585 | G35: =(Assumptions!G33+Assumptions!G51)*-1 -> -262.09707 | H35: =(Assumptions!H33+Assumptions!H51)*-1 -> -280.33028 | I35: =(Assumptions!I33+Assumptions!I51)*-1 -> -309.60303 | J35: =(Assumptions!J33+Assumptions!J51)*-1 -> -336.62647 | K35: =(Assumptions!K33+Assumptions!K51)*-1 -> -365.91955 | L35: =(Assumptions!L33+Assumptions!L51)*-1 -> -399.91239
A36: Proceeds From Sale Of Fixed Assets | B36: 1.82 | C36: 0.73 | D36: 2.17 | E36: 0 | F36: 0 | G36: 0 | H36: 0 | I36: 0 | J36: 0 | K36: 0 | L36: 0
A37: Purchase/sale of investment | B37: -334.12 | C37: -1326.63 | D37: 178.82 | E37: 0 | F37: 0 | G37: 0 | H37: 0 | I37: 0 | J37: 0 | K37: 0 | L37: 0
A38: Inter corporate deposit | B38: -874.3 | C38: -1293.41 | D38: -1202.5 | E38: 0 | F38: 0 | G38: 0 | H38: 0 | I38: 0 | J38: 0 | K38: 0 | L38: 0
A39: Redeem of inter corporate deposit | B39: 635.4 | C39: 1204.24 | D39: 1491.41 | E39: 0 | F39: 0 | G39: 0 | H39: 0 | I39: 0 | J39: 0 | K39: 0 | L39: 0
A40: Interest received | B40: 116.88 | C40: 127.62 | D40: 233.43 | E40: ='Income Statement'!E27 -> 313 | F40: ='Income Statement'!F27 -> 313 | G40: ='Income Statement'!G27 -> 313 | H40: ='Income Statement'!H27 -> 313 | I40: ='Income Statement'!I27 -> 313 | J40: ='Income Statement'!J27 -> 313 | K40: ='Income Statement'!K27 -> 313 | L40: ='Income Statement'!L27 -> 313
A41: Other Investing Activity 5 | B41: 0 | C41: 0 | D41: 0 | E41: 0 | F41: 0 | G41: 0 | H41: 0 | I41: 0 | J41: 0 | K41: 0 | L41: 0
A42: Other Investing Activity 6 | B42: 0 | C42: 0 | D42: 0 | E42: 0 | F42: 0 | G42: 0 | H42: 0 | I42: 0 | J42: 0 | K42: 0 | L42: 0
A43: Other Investing Activity 7 | B43: 0 | C43: 0 | D43: 0 | E43: 0 | F43: 0 | G43: 0 | H43: 0 | I43: 0 | J43: 0 | K43: 0 | L43: 0
A44: Other Investing Activity 8 | B44: 0 | C44: 0 | D44: 0 | E44: 0 | F44: 0 | G44: 0 | H44: 0 | I44: 0 | J44: 0 | K44: 0 | L44: 0
A45: Other Investing Activity 9 | B45: 0 | C45: 0 | D45: 0 | E45: 0 | F45: 0 | G45: 0 | H45: 0 | I45: 0 | J45: 0 | K45: 0 | L45: 0
A46: Other Investing Activity 10 | B46: 0 | C46: 0 | D46: 0 | E46: 0 | F46: 0 | G46: 0 | H46: 0 | I46: 0 | J46: 0 | K46: 0 | L46: 0
A47: Net Cash Flow From Investing Activities | B47: =SUM(B35:B46) -> -855.53 | C47: =SUM(C35:C46) -> -1531.62 | D47: =SUM(D35:D46) -> 461.26 | E47: =SUM(E35:E46) -> 104.65387 | F47: =SUM(F35:F46) -> 72.124148 | G47: =SUM(G35:G46) -> 50.902932 | H47: =SUM(H35:H46) -> 32.669716 | I47: =SUM(I35:I46) -> 3.3969657 | ... L47: =SUM(L35:L46) -> -86.912385
A49: Cash Flows From Financing Activities:
A50: Proceeds From Share Allotment | B50: 29.79 | C50: 23.97 | D50: 103.15 | E50: =0 -> 0 | F50: =0 -> 0 | G50: =0 -> 0 | H50: =0 -> 0 | I50: =0 -> 0 | J50: =0 -> 0 | K50: =0 -> 0 | L50: =0 -> 0
A51: Repayment Of Long Term Borrowings | B51: -41.91 | C51: 640.72 | D51: 567.8 | E51: 0 | F51: 0 | G51: 0 | H51: 0 | I51: 0 | J51: 0 | K51: 0 | L51: 0
A52: Proceeds From Short Term Borrowings | B52: 0 | C52: 0 | D52: 0 | E52: 0 | F52: 0 | G52: 0 | H52: 0 | I52: 0 | J52: 0 | K52: 0 | L52: 0
A53: Repayment Of Short Term Borrowings | B53: 0 | C53: 0 | D53: 0
A54: Interest Paid | B54: -9.38 | C54: -35.54 | D54: -101.3 | E54: ='Income Statement'!E26 -> -118.12345 | F54: ='Income Statement'!F26 -> -111.67758 | G54: ='Income Statement'!G26 -> -113.56701 | H54: ='Income Statement'!H26 -> -114.45601 | I54: ='Income Statement'!I26 -> -113.23354 | J54: ='Income Statement'!J26 -> -113.75219 | K54: ='Income Statement'!K26 -> -113.81391 | L54: ='Income Statement'!L26 -> -113.59988
A55: Dividend Paid (Including Dividend Distribution Tax) | B55: -354.38 | C55: -432.53 | D55: -2823.75 | E55: ='Income Statement'!E51 -> -552.69171 | F55: ='Income Statement'!F51 -> -616.34999 | G55: ='Income Statement'!G51 -> -683.43746 | H55: ='Income Statement'!H51 -> -723.36794 | I55: ='Income Statement'!I51 -> -791.79797 | J55: ='Income Statement'!J51 -> -861.48793 | K55: ='Income Statement'!K51 -> -931.13706 | L55: ='Income Statement'!L51 -> -1013.561
A56: Dividend Paid To Minority Shareholders | B56: 23.2 | C56: 12 | D56: 14 | E56: 0 | F56: 0 | G56: 0 | H56: 0 | I56: 0 | J56: 0 | K56: 0 | L56: 0
A57: Payment of bonus debenture | B57: 0 | C57: 0 | D57: 0 | E57: 0 | F57: 0 | G57: 0 | H57: 0 | I57: 0 | J57: 0 | K57: 0 | L57: 0
A58: payment of debenture and interest | B58: 0 | C58: -869.15 | D58: 0 | E58: 0 | F58: 0 | G58: 0 | H58: 0 | I58: 0 | J58: 0 | K58: 0 | L58: 0
A59: Principle payment of lease liabilities | B59: 0 | C59: -2.03 | D59: -2.55 | E59: 0 | F59: 0 | G59: 0 | H59: 0 | I59: 0 | J59: 0 | K59: 0 | L59: 0
A60: Interest Paid on lease liabilities | C60: -0.45 | D60: -1.04 | E60: 0 | F60: 0 | G60: 0 | H60: 0 | I60: 0 | J60: 0 | K60: 0 | L60: 0
A61: Issue Of bonus debenture | B61: 0 | C61: 720.95 | D61: 0 | E61: 0 | F61: 0 | G61: 0 | H61: 0 | I61: 0 | J61: 0 | K61: 0 | L61: 0
A62: Other Financing Activity 6 | B62: 0 | C62: 0 | D62: 0 | E62: 0 | F62: 0 | G62: 0 | H62: 0 | I62: 0 | J62: 0 | K62: 0 | L62: 0
A63: Other Financing Activity 7 | B63: 0 | C63: 0 | D63: 0 | E63: 0 | F63: 0 | G63: 0 | H63: 0 | I63: 0 | J63: 0 | K63: 0 | L63: 0
A64: Other Financing Activity 8 | B64: 0 | C64: 0 | D64: 0 | E64: 0 | F64: 0 | G64: 0 | H64: 0 | I64: 0 | J64: 0 | K64: 0 | L64: 0
A65: Net Cash Used In Financing Activities | B65: =SUM(B50:B64) -> -352.68 | C65: =SUM(C50:C64) -> 57.94 | D65: =SUM(D50:D64) -> -2243.69 | E65: =SUM(E50:E64) -> -670.81516 | F65: =SUM(F50:F64) -> -728.02757 | G65: =SUM(G50:G64) -> -797.00447 | H65: =SUM(H50:H64) -> -837.82395 | I65: =SUM(I50:I64) -> -905.0315 | ... L65: =SUM(L50:L64) -> -1127.1609
A67: Increase (Decrease) In Cash And Cash Equivalents | E67: =E32+E47+E65 -> 1338.9168 | F67: =F32+F47+F65 -> 1450.8069 | G67: =G32+G47+G65 -> 1538.6189 | H67: =H32+H47+H65 -> 1679.8631 | I67: =I32+I47+I65 -> 1822.9013 | J67: =J32+J47+J65 -> 1969.7154 | K67: =K32+K47+K65 -> 2140.3215 | L67: =L32+L47+L65 -> 2322.5251
A68: Cash And Cash Equivalents At Beginning Of Period | B68: =B47+B65+B32 -> -52.43 | C68: =C47+C65+C32 -> 10.85 | D68: =D47+D65+D32 -> 68.64 | E68: =D71 -> 141.46 | F68: =E71 -> 1480.3768 | G68: =F71 -> 2931.1837 | H68: =G71 -> 4469.8027 | I68: =H71 -> 6149.6658 | J68: =I71 -> 7972.567 | K68: =J71 -> 9942.2825 | L68: =K71 -> 12082.604
A69: Cash And Cash Equivalent On Acquisition Of Subsidiary | B69: 107.84 | C69: =B71 -> 58.72 | D69: =C71 -> 75.26 | E69: 0 | F69: 0 | G69: 0 | H69: 0 | I69: 0 | J69: 0 | K69: 0 | L69: 0
A70: Effect Of Exchange Rate Change On Cash | B70: 3.31 | C70: 5.69 | D70: -2.44 | E70: 0
A71: Cash And Cash Equivalent At The end of period | B71: =SUM(B68:B70) -> 58.72 | C71: =SUM(C68:C70) -> 75.26 | D71: =SUM(D68:D70) -> 141.46 | E71: =SUM(E67:E70) -> 1480.3768 | F71: =SUM(F67:F70) -> 2931.1837 | G71: =SUM(G67:G70) -> 4469.8027 | H71: =SUM(H67:H70) -> 6149.6658 | I71: =SUM(I67:I70) -> 7972.567 | J71: =SUM(J67:J70) -> 9942.2825 | K71: =SUM(K67:K70) -> 12082.604 | L71: =SUM(L67:L70) -> 14405.129

Sheet Valuation 1
A1: =[3]Assumptions!A1 -> Britannia Ltd.
A2: Assumptions
A5: Long Term Growth Rate | B5: 0.038
A7: Cost of Equity (Ke) | B7: =E7+(B8*E9) -> 0.11767 | D7: Risk Free rate | E7: 0.0742
A8: Stock Beta | B8: 0.69 | D8: market Return | E8: 0.1372
A9: Long Term Cost of Debt | B9: ='Income Statement'!D26*-1/('Balance Sheet'!D38 + 'Balance Sheet'!D45) -> 0.053134148 | D9: Market Premium | E9: =E8-E7 -> 0.063
A10: Tax Rate (@) | B10: ='Income Statement'!B32*-1/'Income Statement'!B31 -> 0.33895259 | D10: Weight of Equity | E10: =E12/(E12+E13) -> 0.63196836
A11: WACC | B11: =(E10*B7) +(E11*B9) -> 0.093918765 | D11: Weight of Debt | E11: =E13/(E12+E13) -> 0.36803164
D12: Equity | E12: ='Balance Sheet'!D59 -> 3584
A13: Number of Shares Outstanding | B13: ='Income Statement'!D45 -> 24.07 | D13: Total Debt | E13: ='Balance Sheet'!D45+'Balance Sheet'!D38 -> 2087.17
A14: Current market Price | B14: 3815
A15: Market Capitalisation | B15: =B13*B14 -> 91827.05
A16: Debt | B16: =E13 -> 2087.17
A17: Cash | B17: ='Balance Sheet'!D8+'Balance Sheet'!D9+'Balance Sheet'!D10 -> 1604.59
A18: Minority Interest | B18: ='Balance Sheet'!D58 -> 36.34
A19: Enterprise Value | B19: =B15+B16-B17+B18 -> 92345.97
G21: Shares # | H21: CMP | J21: Equity Value
E22: Ordinary shares
A24: CALCULATION OF FREE CASH FLOW
A26: Particulars | B26: =Assumptions!B5 -> FY2019 A | C26: =Assumptions!C5 -> FY2020 A | D26: =Assumptions!D5 -> FY2021 A | E26: =Assumptions!E5 -> FY2022 E | F26: =Assumptions!F5 -> FY2023 E | G26: =Assumptions!G5 -> FY2024 E | H26: =Assumptions!H5 -> FY2025 E | I26: =Assumptions!I5 -> FY2026 E | ... L26: =Assumptions!L5 -> FY2029 E | M26: Terminal Value
A27: Revenues | B27: ='Income Statement'!B7 -> 11054 | C27: ='Income Statement'!C7 -> 11599 | D27: ='Income Statement'!D7 -> 13136 | E27: ='Income Statement'!E7 -> 14318.24 | F27: ='Income Statement'!F7 -> 15606.882 | G27: ='Income Statement'!G7 -> 17011.501 | H27: ='Income Statement'!H7 -> 18542.536 | I27: ='Income Statement'!I7 -> 20211.364 | ... L27: ='Income Statement'!L7 -> 26174.303
A28: % Growth Revenue | C28: =(C27/B27)-1 -> 0.04930342 | D28: =(D27/C27)-1 -> 0.13251142 | E28: =(E27/D27)-1 -> 0.09 | F28: =(F27/E27)-1 -> 0.09 | G28: =(G27/F27)-1 -> 0.09 | H28: =(H27/G27)-1 -> 0.09 | I28: =(I27/H27)-1 -> 0.09 | J28: =(J27/I27)-1 -> 0.09 | ... L28: =(L27/K27)-1 -> 0.09
A29: EBITDA | B29: ='Income Statement'!B23 -> 1735 | C29: ='Income Statement'!C23 -> 1842.53 | D29: ='Income Statement'!D23 -> 2510 | E29: ='Income Statement'!E23 -> 2419.2442 | F29: ='Income Statement'!F23 -> 2699.433 | G29: ='Income Statement'!G23 -> 3022.4029 | H29: ='Income Statement'!H23 -> 3211.5357 | I29: ='Income Statement'!I23 -> 3529.1116 | ... L29: ='Income Statement'!L23 -> 4572.5781
A30: EBIT | B30: ='Income Statement'!B25 -> 1573.12 | C30: ='Income Statement'!C25 -> 1657.72 | D30: ='Income Statement'!D25 -> 2312.15 | E30: ='Income Statement'!E25 -> 2194.27 | F30: ='Income Statement'!F25 -> 2463.118 | G30: ='Income Statement'!G25 -> 2767.8803 | H30: ='Income Statement'!H25 -> 2933.1867 | I30: ='Income Statement'!I25 -> 3229.9577 | ... L30: ='Income Statement'!L25 -> 4192.1964
A31: Tax Rate | B31: =ABS(SUM('Income Statement'!B32:B34))/'Income Statement'!B31 -> 0.34612407 | C31: =ABS(SUM('Income Statement'!C32:C34))/'Income Statement'!C31 -> 0.24446072 | D31: =ABS(SUM('Income Statement'!D32:D34))/'Income Statement'!D31 -> 0.26368391 | E31: =ABS(SUM('Income Statement'!E32:E34))/'Income Statement'!E31 -> 0.25407231 | F31: =ABS(SUM('Income Statement'!F32:F34))/'Income Statement'!F31 -> 0.25407231 | G31: =ABS(SUM('Income Statement'!G32:G34))/'Income Statement'!G31 -> 0.25727618 | H31: =ABS(SUM('Income Statement'!H32:H34))/'Income Statement'!H31 -> 0.25514027 | I31: =ABS(SUM('Income Statement'!I32:I34))/'Income Statement'!I31 -> 0.25549625 | ... L31: =ABS(SUM('Income Statement'!L32:L34))/'Income Statement'!L31 -> 0.25566765
A32: Net Operating Profit After Taxes | B32: ='Income Statement'!B41 -> 1160.88 | C32: ='Income Statement'!C41 -> 1398.07 | D32: ='Income Statement'!D41 -> 1849.93 | E32: ='Income Statement'!E41 -> 1782.8765 | F32: ='Income Statement'!F41 -> 1988.2258 | G32: ='Income Statement'!G41 -> 2204.637 | H32: ='Income Statement'!H41 -> 2333.445 | I32: ='Income Statement'!I41 -> 2554.187 | ... L32: ='Income Statement'!L41 -> 3269.5517
A33: Operating Cash Flow | B33: =CFS!B32 -> 1155.78 | C33: =CFS!C32 -> 1484.53 | D33: =CFS!D32 -> 1851.07 | E33: =CFS!E32 -> 1905.0781 | F33: =CFS!F32 -> 2106.7103 | G33: =CFS!G32 -> 2284.7205 | H33: =CFS!H32 -> 2485.0173 | I33: =CFS!I32 -> 2724.5358 | ... L33: =CFS!L32 -> 3536.5984
A34: Capex | B34: =SUM(CFS!B35:B46) -> -855.53 | C34: =SUM(CFS!C35:C46) -> -1531.62 | D34: =SUM(CFS!D35:D46) -> 461.26 | E34: =CFS!E35 -> -208.34613 | F34: =CFS!F35 -> -240.87585 | G34: =CFS!G35 -> -262.09707 | H34: =CFS!H35 -> -280.33028 | I34: =CFS!I35 -> -309.60303 | J34: =CFS!J35 -> -336.62647 | K34: =CFS!K35 -> -365.91955 | L34: =CFS!L35 -> -399.91239
A35: FCF | B35: =B33+B34 -> 300.25 | C35: =C33+C34 -> -47.09 | D35: =D33+D34 -> 2312.33 | E35: =E33+E34 -> 1696.732 | F35: =F33+F34 -> 1865.8345 | G35: =G33+G34 -> 2022.6234 | H35: =H33+H34 -> 2204.6871 | I35: =I33+I34 -> 2414.9328 | ... L35: =L33+L34 -> 3136.686 | M35: =B42 -> 58225.178
A36: Years to Discount | E36: 1 | F36: 2 | G36: 3 | H36: 4 | I36: 5 | J36: 6 | K36: 7 | L36: 8 | M36: 8
A37: Discount Factor | E37: =1*((1+$B$11)^E36) -> 1.0939188 | F37: =1*((1+$B$11)^F36) -> 1.1966583 | G37: =1*((1+$B$11)^G36) -> 1.3090469 | H37: =1*((1+$B$11)^H36) -> 1.431991 | I37: =1*((1+$B$11)^I36) -> 1.5664818 | J37: =1*((1+$B$11)^J36) -> 1.7136039 | K37: =1*((1+$B$11)^K36) -> 1.8745434 | L37: =1*((1+$B$11)^L36) -> 2.0505982
A38: PV | E38: =E35/E37 -> 1551.0585 | F38: =F35/F37 -> 1559.2041 | G38: =G35/G37 -> 1545.1115 | H38: =H35/H37 -> 1539.5956 | I38: =I35/I37 -> 1541.6283 | J38: =J35/J37 -> 1535.9183 | K38: =K35/K37 -> 1532.2518 | L38: =L35/L37 -> 1529.6443
A40: Sum of PV | B40: =SUM(E38:L38) -> 12334.412
A41: Terminal Value | B41: FCF8 (1 + long term growth rate) / (WACC - long term rate)
B42: =(L35*(1+B5))/(B11-B5) -> 58225.178
A43: Present Value of Terminal Value | B43: =M35/L37 -> 28394.24
A44: Company's EV | B44: =B40+B43 -> 40728.653

Sheet Comps
A1: Company | B1: Sh. Price | C1: TSO | D1: Mkt. Cap | E1: Debt | F1: Minority Interest | G1: Cash & Investments | H1: Enterprise Value | I1: Revenue (mlln) | L1: EBITDA (mlln) | O1: PAT (mlln) | R1: Price / Revenue | U1: Price/Earnings | X1: EV/Sales | AA1: EV/EBITDA
B2: (INR) | C2: (MLLN) | D2: (INR MLLN) | I2: LTM Dec 21 | J2: FY 2022 | K2: FY 2023 | L2: LTM Dec21 | M2: FY 2022 | N2: FY2023 | O2: LTM Dec21 | P2: =J2 -> FY 2022 | Q2: =K2 -> FY 2023 | R2: LTM Dec21 | S2: =M2 -> FY 2022 | T2: =N2 -> FY2023 | U2: LTM Dec 21 | V2: =S2 -> FY 2022 | W2: =T2 -> FY2023 | X2: LTM Dec21 | Y2: =V2 -> FY 2022 | Z2: =W2 -> FY2023 | AA2: LTM Dec21 | AB2: =Y2 -> FY 2022 | AC2: =Z2 -> FY2023
A3: Parag Milk Foods Ltd | B3: 113.6 | C3: 8.39 | D3: =IF(ISERROR(B3*C3),"- ",(B3*C3)) -> 953.104 | E3: 75.438 | F3: 0 | G3: 1.865 | H3: =D3+E3+F3-G3 -> 1026.677 | I3: =(14074.17+(24379.24-19026.91))/10 -> 1942.65 | J3: ='Comps - Consensus'!C10 -> 2265.45 | K3: ='Comps - Consensus'!D10 -> 2704 | L3: =(1130.41+(2187.01-1777.53))/10 -> 153.989 | M3: ='Comps - Consensus'!C18 -> 208.15 | N3: ='Comps - Consensus'!D18 -> 232.9 | O3: =(411+(174.54-186.46)+0.32)/10 -> 39.94 | P3: ='Comps - Consensus'!C26 -> 93 | Q3: ='Comps - Consensus'!D26 -> 127.1 | R3: =IF(ISERROR($D3/I3),"- ",($D3/I3)) -> 0.49062054 | S3: =IF(ISERROR($D3/J3),"- ",($D3/J3)) -> 0.42071288 | T3: =IF(ISERROR($D3/K3),"- ",($D3/K3)) -> 0.35247929 | U3: =IF(ISERROR($D3/O3),"- ",($D3/O3)) -> 23.863395 | V3: =IF(ISERROR($D3/P3),"- ",($D3/P3)) -> 10.24843 | W3: =IF(ISERROR($D3/Q3),"- ",($D3/Q3)) -> 7.4988513 | X3: =IFERROR($H3/I3, "NA") -> 0.52849304 | Y3: =IFERROR($H3/J3, "NA") -> 0.45318899 | Z3: =IFERROR($H3/K3, "NA") -> 0.37968824 | AA3: =IF(ISERROR($H3/L3),"- ",($H3/L3)) -> 6.66721 | AB3: =IF(ISERROR($H3/M3),"- ",($H3/M3)) -> 4.9323901 | AC3: =IF(ISERROR($H3/N3),"- ",($H3/N3)) -> 4.408231
A4: Dodla Dairy Limited | B4: 518.15 | C4: 5.83 | D4: =IF(ISERROR(B4*C4),"- ",(B4*C4)) -> 3020.8145 | E4: 31.427 | F4: 0 | G4: 22.444 | H4: =D4+E4+F4-G4 -> 3029.7975 | I4: =(5305+5121+5664+5752)/10 -> 2184.2 | J4: ='Comps - Consensus'!G10 -> 2241.3 | K4: ='Comps - Consensus'!H10 -> 2534.9 | L4: 200.8 | M4: ='Comps - Consensus'!G18 -> 227.5 | N4: ='Comps - Consensus'!H18 -> 262.4 | O4: =(96+361+294+269)/10 -> 102 | P4: ='Comps - Consensus'!G26 -> 138.9 | Q4: ='Comps - Consensus'!H26 -> 174.2 | R4: =IF(ISERROR($D4/I4),"- ",($D4/I4)) -> 1.3830302 | S4: =IF(ISERROR($D4/J4),"- ",($D4/J4)) -> 1.3477957 | T4: =IF(ISERROR($D4/K4),"- ",($D4/K4)) -> 1.1916898 | U4: =IF(ISERROR($D4/O4),"- ",($D4/O4)) -> 29.615828 | V4: =IF(ISERROR($D4/P4),"- ",($D4/P4)) -> 21.748125 | W4: =IF(ISERROR($D4/Q4),"- ",($D4/Q4)) -> 17.341071 | X4: =IFERROR($H4/I4, "NA") -> 1.3871429 | Y4: =IFERROR($H4/J4, "NA") -> 1.3518036 | Z4: =IFERROR($H4/K4, "NA") -> 1.1952335 | AA4: =IF(ISERROR($H4/L4),"- ",($H4/L4)) -> 15.088633 | AB4: =IF(ISERROR($H4/M4),"- ",($H4/M4)) -> 13.317791 | AC4: =IF(ISERROR($H4/N4),"- ",($H4/N4)) -> 11.546484
A5: Heritage Foods LTD | B5: 371.5 | C5: 4.63 | D5: =IF(ISERROR(B5*C5),"- ",(B5*C5)) -> 1720.045 | E5: 28.219 | F5: 0.0488 | G5: 2.355 | H5: =D5+E5+F5-G5 -> 1745.9578 | I5: =(19853.85+(24731.13-18537.51))/10 -> 2604.747 | J5: ='Comps - Consensus'!K10 -> NA | K5: ='Comps - Consensus'!L10 -> NA | L5: =(1680.8+(2665.4-2211.53))/10 -> 213.467 | M5: ='Comps - Consensus'!K18 -> NA | N5: ='Comps - Consensus'!L18 -> NA | O5: =(838.81+(1490.5-1248.22))/10 -> 108.109 | P5: ='Comps - Consensus'!K26 -> NA | Q5: ='Comps - Consensus'!L26 -> NA | R5: =IF(ISERROR($D5/I5),"- ",($D5/I5)) -> 0.66035012 | S5: =IF(ISERROR($D5/J5),"- ",($D5/J5)) -> - | T5: =IF(ISERROR($D5/K5),"- ",($D5/K5)) -> - | U5: =IF(ISERROR($D5/O5),"- ",($D5/O5)) -> 15.910285 | V5: =IF(ISERROR($D5/P5),"- ",($D5/P5)) -> - | W5: =IF(ISERROR($D5/Q5),"- ",($D5/Q5)) -> - | X5: =IFERROR($H5/I5, "NA") -> 0.67029842 | Y5: =IFERROR($H5/J5, "NA") -> NA | Z5: =IFERROR($H5/K5, "NA") -> NA | AA5: =IF(ISERROR($H5/L5),"- ",($H5/L5)) -> 8.1790525 | AB5: =IF(ISERROR($H5/M5),"- ",($H5/M5)) -> - | AC5: =IF(ISERROR($H5/N5),"- ",($H5/N5)) -> -
A6: MilkFood LTD | B6: 368.15 | C6: 0.4 | D6: =IF(ISERROR(B6*C6),"- ",(B6*C6)) -> 147.26 | E6: 19.046 | F6: 0 | G6: 0.09 | H6: =D6+E6+F6-G6 -> 166.216 | I6: =((13563+(36830-15693))/10)/10 -> 347 | J6: ='Comps - Consensus'!O10 -> NA | K6: ='Comps - Consensus'!P10 -> NA | L6: =((786+(2022-1070))/10)/10 -> 17.38 | M6: ='Comps - Consensus'!O18 -> NA | N6: ='Comps - Consensus'!P18 -> NA | O6: =((87+(244-136))/10)/10 -> 1.95 | P6: ='Comps - Consensus'!O26 -> NA | Q6: ='Comps - Consensus'!P26 -> NA | R6: =IF(ISERROR($D6/I6),"- ",($D6/I6)) -> 0.4243804 | S6: =IF(ISERROR($D6/J6),"- ",($D6/J6)) -> - | T6: =IF(ISERROR($D6/K6),"- ",($D6/K6)) -> - | U6: =IF(ISERROR($D6/O6),"- ",($D6/O6)) -> 75.517949 | V6: =IF(ISERROR($D6/P6),"- ",($D6/P6)) -> - | W6: =IF(ISERROR($D6/Q6),"- ",($D6/Q6)) -> - | X6: =IFERROR($H6/I6, "NA") -> 0.47900865 | Y6: =IFERROR($H6/J6, "NA") -> NA | Z6: =IFERROR($H6/K6, "NA") -> NA | AA6: =IF(ISERROR($H6/L6),"- ",($H6/L6)) -> 9.5636364 | AB6: =IF(ISERROR($H6/M6),"- ",($H6/M6)) -> - | AC6: =IF(ISERROR($H6/N6),"- ",($H6/N6)) -> -
A7: Umang Dairies LTD | B7: 75.75 | C7: 2.2 | D7: =IF(ISERROR(B7*C7),"- ",(B7*C7)) -> 166.65 | E7: 10.553 | F7: 0 | G7: 0.047 | H7: =D7+E7+F7-G7 -> 177.156 | I7: =((8980.54+(24895.14-11728.82))/10)/10 -> 221.4686 | J7: ='Comps - Consensus'!S10 -> NA | K7: ='Comps - Consensus'!T10 -> NA | L7: =((-688.26+(1462.11-878.42))/10)/10 -> -1.0457 | M7: ='Comps - Consensus'!S18 -> NA | N7: ='Comps - Consensus'!T18 -> NA | O7: =((-863+(410.01-321.61))/10)/10 -> -7.746 | P7: ='Comps - Consensus'!S26 -> NA | Q7: ='Comps - Consensus'!T26 -> NA | R7: =IF(ISERROR($D7/I7),"- ",($D7/I7)) -> 0.75247687 | S7: =IF(ISERROR($D7/J7),"- ",($D7/J7)) -> - | T7: =IF(ISERROR($D7/K7),"- ",($D7/K7)) -> - | U7: =IF(ISERROR($D7/O7),"- ",($D7/O7)) -> -21.51433 | V7: =IF(ISERROR($D7/P7),"- ",($D7/P7)) -> - | W7: =IF(ISERROR($D7/Q7),"- ",($D7/Q7)) -> - | X7: =IFERROR($H7/I7, "NA") -> 0.79991475 | Y7: =IFERROR($H7/J7, "NA") -> NA | Z7: =IFERROR($H7/K7, "NA") -> NA | AA7: =IF(ISERROR($H7/L7),"- ",($H7/L7)) -> -169.41379 | AB7: =IF(ISERROR($H7/M7),"- ",($H7/M7)) -> - | AC7: =IF(ISERROR($H7/N7),"- ",($H7/N7)) -> -
A8: Hatsun Agro Products LTD | B8: 1059.55 | C8: 21.5 | D8: =IF(ISERROR(B8*C8),"- ",(B8*C8)) -> 22780.325 | E8: 209.552 | F8: 0 | G8: 3.924 | H8: =D8+E8+F8-G8 -> 22985.953 | I8: =(47651.28+(55697.43-40008.7))/10 -> 6334.001 | J8: ='Comps - Consensus'!W10 -> 6705.7 | K8: ='Comps - Consensus'!X10 -> 7777.9 | L8: =(5551.48+(7844.91-5938.02))/10 -> 745.837 | M8: ='Comps - Consensus'!W18 -> 810.7 | N8: ='Comps - Consensus'!X18 -> 944.1 | O8: =((18826.89+(24635.06-18921.48))/10)/10 -> 245.4047 | P8: ='Comps - Consensus'!W26 -> 275 | Q8: ='Comps - Consensus'!X26 -> 356.4 | R8: =IF(ISERROR($D8/I8),"- ",($D8/I8)) -> 3.5965143 | S8: =IF(ISERROR($D8/J8),"- ",($D8/J8)) -> 3.3971584 | T8: =IF(ISERROR($D8/K8),"- ",($D8/K8)) -> 2.9288529 | U8: =IF(ISERROR($D8/O8),"- ",($D8/O8)) -> 92.827582 | V8: =IF(ISERROR($D8/P8),"- ",($D8/P8)) -> 82.837545 | W8: =IF(ISERROR($D8/Q8),"- ",($D8/Q8)) -> 63.917859 | X8: =IFERROR($H8/I8, "NA") -> 3.6289784 | Y8: =IFERROR($H8/J8, "NA") -> 3.427823 | Z8: =IFERROR($H8/K8, "NA") -> 2.9552904 | AA8: =IF(ISERROR($H8/L8),"- ",($H8/L8)) -> 30.819003 | AB8: =IF(ISERROR($H8/M8),"- ",($H8/M8)) -> 28.353217 | AC8: =IF(ISERROR($H8/N8),"- ",($H8/N8)) -> 24.346947
A9: Britannia Industries Ltd. | B9: 3530 | C9: 24.08 | D9: =IF(ISERROR(B9*C9),"- ",(B9*C9)) -> 85002.4 | E9: 4424.78 | F9: 3.634 | G9: 211.34 | H9: =D9+E9+F9-G9 -> 89219.474 | I9: =((10035.17+(12378.83-9426.19))*10)/10 -> 12987.81 | J9: ='Comps - Consensus'!AA10 -> 13975.5 | K9: ='Comps - Consensus'!AB10 -> 15406 | L9: =((1823.51+(2644.02-2099.68))*10)/10 -> 2367.85 | M9: ='Comps - Consensus'!AA18 -> 2305.2 | N9: ='Comps - Consensus'!AB18 -> 2756.6 | O9: =((1189.76+(1760.03-1406.57))*10)/10 -> 1543.22 | P9: ='Comps - Consensus'!AA26 -> 1648.65 | Q9: ='Comps - Consensus'!AB26 -> 1978.45 | R9: =IF(ISERROR($D9/I9),"- ",($D9/I9)) -> 6.5447831 | S9: =IF(ISERROR($D9/J9),"- ",($D9/J9)) -> 6.0822439 | T9: =IF(ISERROR($D9/K9),"- ",($D9/K9)) -> 5.5174867 | U9: =IF(ISERROR($D9/O9),"- ",($D9/O9)) -> 55.081194 | V9: =IF(ISERROR($D9/P9),"- ",($D9/P9)) -> 51.558791 | W9: =IF(ISERROR($D9/Q9),"- ",($D9/Q9)) -> 42.964139 | X9: =IFERROR($H9/I9, "NA") -> 6.8694779 | Y9: =IFERROR($H9/J9, "NA") -> 6.3839916 | Z9: =IFERROR($H9/K9, "NA") -> 5.791216 | AA9: =IF(ISERROR($H9/L9),"- ",($H9/L9)) -> 37.67953 | AB9: =IF(ISERROR($H9/M9),"- ",($H9/M9)) -> 38.703572 | AC9: =IF(ISERROR($H9/N9),"- ",($H9/N9)) -> 32.365767
A10: DFM Foods | B10: 284.35 | C10: 5 | D10: =IF(ISERROR(B10*C10),"- ",(B10*C10)) -> 1421.75 | E10: 226.25 | F10: 0 | G10: 88.81 | H10: =D10+E10+F10-G10 -> 1559.19 | I10: =(2575.7+(5240.6-2562))/10 -> 525.43 | J10: ='Comps - Consensus'!AE10 -> 697.74 | K10: ='Comps - Consensus'!AF10 -> 772.9 | L10: =(61.1+(625.6-364.3))/10 -> 32.24 | M10: ='Comps - Consensus'!AE18 -> 91.72 | N10: ='Comps - Consensus'!AF18 -> 90 | O10: =(-486+(2870-1832))/10 -> 55.2 | P10: ='Comps - Consensus'!AE26 -> 55.45 | Q10: ='Comps - Consensus'!AF26 -> 58.4 | R10: =IF(ISERROR($D10/I10),"- ",($D10/I10)) -> 2.705879 | S10: =IF(ISERROR($D10/J10),"- ",($D10/J10)) -> 2.0376501 | T10: =IF(ISERROR($D10/K10),"- ",($D10/K10)) -> 1.8395006 | U10: =IF(ISERROR($D10/O10),"- ",($D10/O10)) -> 25.756341 | V10: =IF(ISERROR($D10/P10),"- ",($D10/P10)) -> 25.640216 | W10: =IF(ISERROR($D10/Q10),"- ",($D10/Q10)) -> 24.345034 | X10: =IFERROR($H10/I10, "NA") -> 2.9674552 | Y10: =IFERROR($H10/J10, "NA") -> 2.2346289 | Z10: =IFERROR($H10/K10, "NA") -> 2.0173244 | AA10: =IF(ISERROR($H10/L10),"- ",($H10/L10)) -> 48.361973 | AB10: =IF(ISERROR($H10/M10),"- ",($H10/M10)) -> 16.999455 | AC10: =IF(ISERROR($H10/N10),"- ",($H10/N10)) -> 17.324333
A11: Company 9 | B11: 0 | C11: 0 | D11: =IF(ISERROR(B11*C11),"- ",(B11*C11)) -> 0 | E11: 0 | F11: 0 | G11: 0 | H11: =D11+E11+F11-G11 -> 0 | I11: 0 | J11: ='Comps - Consensus'!AI10 -> NA | K11: ='Comps - Consensus'!AJ10 -> NA | L11: 0 | M11: ='Comps - Consensus'!AI18 -> NA | N11: ='Comps - Consensus'!AJ18 -> NA | P11: ='Comps - Consensus'!AI26 -> NA | Q11: ='Comps - Consensus'!AJ26 -> NA | R11: =IF(ISERROR($D11/I11),"- ",($D11/I11)) -> - | S11: =IF(ISERROR($D11/J11),"- ",($D11/J11)) -> - | T11: =IF(ISERROR($D11/K11),"- ",($D11/K11)) -> - | U11: =IF(ISERROR($D11/O11),"- ",($D11/O11)) -> - | V11: =IF(ISERROR($D11/P11),"- ",($D11/P11)) -> - | W11: =IF(ISERROR($D11/Q11),"- ",($D11/Q11)) -> - | X11: =IFERROR($H11/I11, "NA") -> NA | Y11: =IFERROR($H11/J11, "NA") -> NA | Z11: =IFERROR($H11/K11, "NA") -> NA | AA11: =IF(ISERROR($H11/L11),"- ",($H11/L11)) -> - | AB11: =IF(ISERROR($H11/M11),"- ",($H11/M11)) -> - | AC11: =IF(ISERROR($H11/N11),"- ",($H11/N11)) -> -
A12: Company 10 | B12: 0 | C12: 0 | D12: =IF(ISERROR(B12*C12),"- ",(B12*C12)) -> 0 | E12: 0 | F12: 0 | G12: 0 | H12: =D12+E12+F12-G12 -> 0 | I12: 0 | J12: ='Comps - Consensus'!AM10 -> NA | K12: ='Comps - Consensus'!AN10 -> NA | L12: 0 | M12: ='Comps - Consensus'!AM18 -> NA | N12: ='Comps - Consensus'!AN18 -> NA | P12: ='Comps - Consensus'!AM26 -> NA | Q12: ='Comps - Consensus'!AN26 -> NA | R12: =IF(ISERROR($D12/I12),"- ",($D12/I12)) -> - | S12: =IF(ISERROR($D12/J12),"- ",($D12/J12)) -> - | T12: =IF(ISERROR($D12/K12),"- ",($D12/K12)) -> - | U12: =IF(ISERROR($D12/O12),"- ",($D12/O12)) -> - | V12: =IF(ISERROR($D12/P12),"- ",($D12/P12)) -> - | W12: =IF(ISERROR($D12/Q12),"- ",($D12/Q12)) -> - | X12: =IFERROR($H12/I12, "NA") -> NA | Y12: =IFERROR($H12/J12, "NA") -> NA | Z12: =IFERROR($H12/K12, "NA") -> NA | AA12: =IF(ISERROR($H12/L12),"- ",($H12/L12)) -> - | AB12: =IF(ISERROR($H12/M12),"- ",($H12/M12)) -> - | AC12: =IF(ISERROR($H12/N12),"- ",($H12/N12)) -> -
A13: Mean | R13: =IFERROR(AVERAGE(R3:R12),"NA") -> 2.0697543 | S13: =IFERROR(AVERAGE(S3:S12),"NA") -> 2.6571122 | T13: =IFERROR(AVERAGE(T3:T12),"NA") -> 2.3660019 | U13: =IFERROR(AVERAGE(U3:U12),"NA") -> 37.132281 | V13: =IFERROR(AVERAGE(V3:V12),"NA") -> 38.406621 | W13: =IFERROR(AVERAGE(W3:W12),"NA") -> 31.213391 | X13: =IFERROR(AVERAGE(X3:X12),"NA") -> 2.1663462 | Y13: =IFERROR(AVERAGE(Y3:Y12),"NA") -> 2.7702872 | ... AC13: =IFERROR(AVERAGE(AC3:AC12),"NA") -> 17.998353
A14: Median | R14: =IFERROR(MEDIAN(R3:R12), "NA") -> 1.0677535 | S14: =IFERROR(MEDIAN(S3:S12), "NA") -> 2.0376501 | T14: =IFERROR(MEDIAN(T3:T12), "NA") -> 1.8395006 | U14: =IFERROR(MEDIAN(U3:U12), "NA") -> 27.686085 | V14: =IFERROR(MEDIAN(V3:V12), "NA") -> 25.640216 | W14: =IFERROR(MEDIAN(W3:W12), "NA") -> 24.345034 | X14: =IFERROR(MEDIAN(X3:X12), "NA") -> 1.0935288 | Y14: =IFERROR(MEDIAN(Y3:Y12), "NA") -> 2.2346289 | ... AC14: =IFERROR(MEDIAN(AC3:AC12), "NA") -> 17.324333
I16: 44256
I17: Add Q1, Q2 and Q3 of 2021-22
I18: Subtracted Q1, Q2 and Q3 of 2020-21

Sheet Comps - Consensus
B2: Parag Milk Foods | F2: Dodla Dairy | J2: Heritage Foods | N2: MilkFood Ltd | R2: Umang Dairies Ltd | V2: Hatsun Agro Products Ltd | Z2: Britannia Industries Ltd. | AD2: DFM Foods | AH2: Company 9 | AL2: Company 10
B4: Sales | C4: FY 2022 | D4: FY 2023 | F4: Sales | G4: FY 2022 | H4: FY 2023 | J4: Sales | K4: FY 2022 | L4: FY 2023 | N4: Sales | O4: FY 2022 | P4: FY 2023 | R4: Sales | S4: FY 2022 | T4: FY 2023 | V4: Sales | W4: FY 2022 | X4: FY 2023 | Z4: Sales | AA4: FY 2022 | AB4: FY 2023 | AD4: Sales | AE4: FY 2022 | AF4: FY 2023 | AH4: Sales | AI4: FY 2022 | AJ4: FY 2023 | AL4: Sales | AM4: FY 2022 | AN4: FY 2023
B5: ICICI SECURITIES | C5: 2137.8 | D5: 2704 | F5: ICICI SECURITIES | G5: 2241.3 | H5: 2534.9 | V5: ICICI SECURITIES | W5: 6705.7 | X5: 7777.9 | Z5: hdfc securities | AA5: 14244.5 | AB5: 15563 | AD5: Rudra Share | AE5: 723.18 | AH5: Report Name 1 (Date) | AL5: Report Name 1 (Date)
B6: Edelweiss Research | C6: 2393.1 | Z6: Motilal Oswal | AA6: 13970 | AB6: 15900 | AD6: Hdfc Securities | AE6: 672.3 | AF6: 772.9 | AH6: Report Name 2 (Date) | AL6: Report Name 2 (Date)
Z7: Idbi Capital | AA7: 13848.2 | AB7: 15248.8 | AH7: Report Name 3 (Date) | AL7: Report Name 3 (Date)
Z8: Axis Securities | AA8: 13981 | AB8: 15249 | AH8: Report Name 4 (Date) | AL8: Report Name 4 (Date)
AH9: Report Name 4 (Date) | AL9: Report Name 4 (Date)
B10: Median | C10: =IFERROR(MEDIAN(C5:C9), "NA") -> 2265.45 | D10: =IFERROR(MEDIAN(D5:D9), "NA") -> 2704 | F10: Median | G10: =IFERROR(MEDIAN(G5:G9), "NA") -> 2241.3 | H10: =IFERROR(MEDIAN(H5:H9), "NA") -> 2534.9 | J10: Median | K10: =IFERROR(MEDIAN(K5:K9), "NA") -> NA | L10: =IFERROR(MEDIAN(L5:L9), "NA") -> NA | N10: Median | O10: =IFERROR(MEDIAN(O5:O9), "NA") -> NA | P10: =IFERROR(MEDIAN(P5:P9), "NA") -> NA | R10: Median | S10: =IFERROR(MEDIAN(S5:S9), "NA") -> NA | T10: =IFERROR(MEDIAN(T5:T9), "NA") -> NA | V10: Median | W10: =IFERROR(MEDIAN(W5:W9), "NA") -> 6705.7 | X10: =IFERROR(MEDIAN(X5:X9), "NA") -> 7777.9 | Z10: Median | AA10: =IFERROR(MEDIAN(AA5:AA9), "NA") -> 13975.5 | AB10: =IFERROR(MEDIAN(AB5:AB9), "NA") -> 15406 | AD10: Median | AE10: =IFERROR(MEDIAN(AE5:AE9), "NA") -> 697.74 | AF10: =IFERROR(MEDIAN(AF5:AF9), "NA") -> 772.9 | AH10: Median | AI10: =IFERROR(MEDIAN(AI5:AI9), "NA") -> NA | AJ10: =IFERROR(MEDIAN(AJ5:AJ9), "NA") -> NA | AL10: Median | AM10: =IFERROR(MEDIAN(AM5:AM9), "NA") -> NA | AN10: =IFERROR(MEDIAN(AN5:AN9), "NA") -> NA
B12: EBITDA | C12: =$C$4 -> FY 2022 | D12: =$D$4 -> FY 2023 | F12: EBITDA | G12: =$C$4 -> FY 2022 | H12: =$D$4 -> FY 2023 | J12: EBITDA | K12: =$C$4 -> FY 2022 | L12: =$D$4 -> FY 2023 | N12: EBITDA | O12: =$C$4 -> FY 2022 | P12: =$D$4 -> FY 2023 | R12: EBITDA | S12: =$C$4 -> FY 2022 | T12: =$D$4 -> FY 2023 | V12: EBITDA | W12: =$C$4 -> FY 2022 | X12: =$D$4 -> FY 2023 | Z12: EBITDA | AA12: =$C$4 -> FY 2022 | AB12: =$D$4 -> FY 2023 | AD12: EBITDA | AE12: =$C$4 -> FY 2022 | AF12: =$D$4 -> FY 2023 | AH12: EBITDA | AI12: =$C$4 -> FY 2022 | AJ12: =$D$4 -> FY 2023 | AL12: EBITDA | AM12: =$C$4 -> FY 2022 | AN12: =$D$4 -> FY 2023
B13: ICICI SECURITIES | C13: 203.8 | D13: 232.9 | F13: ICICI SECURITIES | G13: 227.5 | H13: 262.4 | V13: ICICI SECURITIES | W13: 810.7 | X13: 944.1 | Z13: hdfc securities | AA13: 2607.5 | AB13: 2846.8 | AD13: Rudra Share | AE13: 100.74 | AH13: Report Name 1 (Date) | AL13: Report Name 1 (Date)
B14: Edelweiss Research | C14: 212.5 | Z14: Motilal Oswal | AA14: 2270 | AB14: 2760 | AD14: Hdfc Securities | AE14: 82.7 | AF14: 90 | AH14: Report Name 2 (Date) | AL14: Report Name 2 (Date)
Z15: Idbi Capital | AA15: 2317.4 | AB15: 2753.2 | AH15: Report Name 3 (Date) | AL15: Report Name 3 (Date)
Z16: Axis Securities | AA16: 2293 | AB16: 2577 | AH16: Report Name 4 (Date) | AL16: Report Name 4 (Date)
AH17: Report Name 4 (Date) | AL17: Report Name 4 (Date)
B18: Median | C18: =IFERROR(MEDIAN(C13:C17), "NA") -> 208.15 | D18: =IFERROR(MEDIAN(D13:D17), "NA") -> 232.9 | F18: Median | G18: =IFERROR(MEDIAN(G13:G17), "NA") -> 227.5 | H18: =IFERROR(MEDIAN(H13:H17), "NA") -> 262.4 | J18: Median | K18: =IFERROR(MEDIAN(K13:K17), "NA") -> NA | L18: =IFERROR(MEDIAN(L13:L17), "NA") -> NA | N18: Median | O18: =IFERROR(MEDIAN(O13:O17), "NA") -> NA | P18: =IFERROR(MEDIAN(P13:P17), "NA") -> NA | R18: Median | S18: =IFERROR(MEDIAN(S13:S17), "NA") -> NA | T18: =IFERROR(MEDIAN(T13:T17), "NA") -> NA | V18: Median | W18: =IFERROR(MEDIAN(W13:W17), "NA") -> 810.7 | X18: =IFERROR(MEDIAN(X13:X17), "NA") -> 944.1 | Z18: Median | AA18: =IFERROR(MEDIAN(AA13:AA17), "NA") -> 2305.2 | AB18: =IFERROR(MEDIAN(AB13:AB17), "NA") -> 2756.6 | AD18: Median | AE18: =IFERROR(MEDIAN(AE13:AE17), "NA") -> 91.72 | AF18: =IFERROR(MEDIAN(AF13:AF17), "NA") -> 90 | AH18: Median | AI18: =IFERROR(MEDIAN(AI13:AI17), "NA") -> NA | AJ18: =IFERROR(MEDIAN(AJ13:AJ17), "NA") -> NA | AL18: Median | AM18: =IFERROR(MEDIAN(AM13:AM17), "NA") -> NA | AN18: =IFERROR(MEDIAN(AN13:AN17), "NA") -> NA
B20: PAT | C20: =$C$4 -> FY 2022 | D20: =$D$4 -> FY 2023 | F20: PAT | G20: =$C$4 -> FY 2022 | H20: =$D$4 -> FY 2023 | J20: PAT | K20: =$C$4 -> FY 2022 | L20: =$D$4 -> FY 2023 | N20: PAT | O20: =$C$4 -> FY 2022 | P20: =$D$4 -> FY 2023 | R20: PAT | S20: =$C$4 -> FY 2022 | T20: =$D$4 -> FY 2023 | V20: PAT | W20: =$C$4 -> FY 2022 | X20: =$D$4 -> FY 2023 | Z20: PAT | AA20: =$C$4 -> FY 2022 | AB20: =$D$4 -> FY 2023 | AD20: PAT | AE20: =$C$4 -> FY 2022 | AF20: =$D$4 -> FY 2023 | AH20: PAT | AI20: =$C$4 -> FY 2022 | AJ20: =$D$4 -> FY 2023 | AL20: PAT | AM20: =$C$4 -> FY 2022 | AN20: =$D$4 -> FY 2023
B21: ICICI SECURITIES | C21: 96.5 | D21: 127.1 | F21: ICICI SECURITIES | G21: 138.9 | H21: 174.2 | V21: ICICI SECURITIES | W21: 275 | X21: 356.4 | Z21: hdfc securities | AA21: 1974.2 | AB21: 2160.6 | AD21: Rudra Share | AE21: 60.5 | AH21: Report Name 1 (Date) | AL21: Report Name 1 (Date)
B22: Edelweiss Research | C22: 89.5 | Z22: Motilal Oswal | AA22: 1600 | AB22: 2000 | AD22: Hdfc Securities | AE22: 50.4 | AF22: 58.4 | AH22: Report Name 2 (Date) | AL22: Report Name 2 (Date)
Z23: Idbi Capital | AA23: 1615.3 | AB23: 1956.9 | AH23: Report Name 3 (Date) | AL23: Report Name 3 (Date)
Z24: Axis Securities | AA24: 1682 | AB24: 1913 | AH24: Report Name 4 (Date) | AL24: Report Name 4 (Date)
AH25: Report Name 4 (Date) | AL25: Report Name 4 (Date)
B26: Median | C26: =IFERROR(MEDIAN(C21:C25), "NA") -> 93 | D26: =IFERROR(MEDIAN(D21:D25), "NA") -> 127.1 | F26: Median | G26: =IFERROR(MEDIAN(G21:G25), "NA") -> 138.9 | H26: =IFERROR(MEDIAN(H21:H25), "NA") -> 174.2 | J26: Median | K26: =IFERROR(MEDIAN(K21:K25), "NA") -> NA | L26: =IFERROR(MEDIAN(L21:L25), "NA") -> NA | N26: Median | O26: =IFERROR(MEDIAN(O21:O25), "NA") -> NA | P26: =IFERROR(MEDIAN(P21:P25), "NA") -> NA | R26: Median | S26: =IFERROR(MEDIAN(S21:S25), "NA") -> NA | T26: =IFERROR(MEDIAN(T21:T25), "NA") -> NA | V26: Median | W26: =IFERROR(MEDIAN(W21:W25), "NA") -> 275 | X26: =IFERROR(MEDIAN(X21:X25), "NA") -> 356.4 | Z26: Median | AA26: =IFERROR(MEDIAN(AA21:AA25), "NA") -> 1648.65 | AB26: =IFERROR(MEDIAN(AB21:AB25), "NA") -> 1978.45 | AD26: Median | AE26: =IFERROR(MEDIAN(AE21:AE25), "NA") -> 55.45 | AF26: =IFERROR(MEDIAN(AF21:AF25), "NA") -> 58.4 | AH26: Median | AI26: =IFERROR(MEDIAN(AI21:AI25), "NA") -> NA | AJ26: =IFERROR(MEDIAN(AJ21:AJ25), "NA") -> NA | AL26: Median | AM26: =IFERROR(MEDIAN(AM21:AM25), "NA") -> NA | AN26: =IFERROR(MEDIAN(AN21:AN25), "NA") -> NA
