Workbook

Sheet Summary
A1: INFOSYS LIMITED - DCF VALUATION MODEL
A2: Integrated consolidated 3-statement forecast FY26E-FY30E | Valuation date 31-Mar-2025 | Rs crore unless stated
A3: ="Active scenario: "&Inputs!C7&" | Model status: "&Checks!C19
A5: VALUATION OUTPUT
A6: Blended intrinsic value per share (Rs) | B6: =DCF!C55
A7: Market price at 31-Mar-2025 (Rs) | B7: =DCF!C56
A8: Upside / (downside) | B8: =DCF!C57
A9: Value per share - Gordon growth (Rs) | B9: =DCF!C53
A10: Value per share - exit multiple (Rs) | B10: =DCF!D53
A11: Enterprise value - Gordon growth (Rs crore) | B11: =DCF!C40
A12: Equity value - Gordon growth (Rs crore) | B12: =DCF!C51
A13: WACC | B13: =WACC!C19
A14: Terminal growth | B14: =Inputs!C67
A15: PV of terminal value as % of EV (Gordon) | B15: =DCF!C41
A16: Implied EV / FY25 EBITDA (Gordon) | B16: =DCF!C61
A17: Market EV / FY25 EBITDA at market price | B17: =DCF!C66
A19: FINANCIAL SUMMARY | B19: FY23A | C19: FY24A | D19: FY25A | E19: FY26E | F19: FY27E | G19: FY28E | H19: FY29E | I19: FY30E
A20: Revenue | B20: =IS!C7 | C20: =IS!D7 | D20: =IS!E7 | E20: =IS!F7 | F20: =IS!G7 | G20: =IS!H7 | H20: =IS!I7 | I20: =IS!J7
A21: growth (INR) | B21: =IS!C40 | C21: =IS!D40 | D21: =IS!E40 | E21: =IS!F40 | F21: =IS!G40 | G21: =IS!H40 | H21: =IS!I40 | I21: =IS!J40
A22: EBITDA (excl. other income) | B22: =IS!C38 | C22: =IS!D38 | D22: =IS!E38 | E22: =IS!F38 | F22: =IS!G38 | G22: =IS!H38 | H22: =IS!I38 | I22: =IS!J38
A23: EBITDA margin | B23: =IS!C39 | C23: =IS!D39 | D23: =IS!E39 | E23: =IS!F39 | F23: =IS!G39 | G23: =IS!H39 | H23: =IS!I39 | I23: =IS!J39
A24: Operating profit | B24: =IS!C36 | C24: =IS!D36 | D24: =IS!E36 | E24: =IS!F36 | F24: =IS!G36 | G24: =IS!H36 | H24: =IS!I36 | I24: =IS!J36
A25: operating margin | B25: =IS!C37 | C25: =IS!D37 | D25: =IS!E37 | E25: =IS!F37 | F25: =IS!G37 | G25: =IS!H37 | H25: =IS!I37 | I25: =IS!J37
A26: Profit for the year | B26: =IS!C24 | C26: =IS!D24 | D26: =IS!E24 | E26: =IS!F24 | F26: =IS!G24 | G26: =IS!H24 | H26: =IS!I24 | I26: =IS!J24
A27: EPS (Rs) | B27: =IS!C32 | C27: =IS!D32 | D27: =IS!E32 | E27: =IS!F32 | F27: =IS!G32 | G27: =IS!H32 | H27: =IS!I32 | I27: =IS!J32
A28: Cash from operations | B28: =CF!C26 | C28: =CF!D26 | D28: =CF!E26 | E28: =CF!F26 | F28: =CF!G26 | G28: =CF!H26 | H28: =CF!I26 | I28: =CF!J26
A29: Free cash flow | B29: =CF!C52 | C29: =CF!D52 | D29: =CF!E52 | E29: =CF!F52 | F29: =CF!G52 | G29: =CF!H52 | H29: =CF!I52 | I29: =CF!J52
A30: Cash + investments | B30: =BS!C56 | C30: =BS!D56 | D30: =BS!E56 | E30: =BS!F56 | F30: =BS!G56 | G30: =BS!H56 | H30: =BS!I56 | I30: =BS!J56
A31: Return on equity | B31: =BS!C59 | C31: =BS!D59 | D31: =BS!E59 | E31: =BS!F59 | F31: =BS!G59 | G31: =BS!H59 | H31: =BS!I59 | I31: =BS!J59
A33: FCFF (Rs crore) | E33: =DCF!F19 | F33: =DCF!G19 | G33: =DCF!H19 | H33: =DCF!I19 | I33: =DCF!J19
A35: Sheet guide: Inputs -> Segments -> IS / BS / CF -> Sched -> WACC -> DCF -> Sens -> Scenarios -> Checks -> Notes

Sheet Inputs
A1: Infosys Limited - Inputs & Assumptions
A2: Rs crore unless stated | Consolidated Ind AS financials | FY ends 31 March | Blue = hard-coded input / reported data, Black = formula, Green = cross-sheet link
A4: Assumption | B4: Unit | C4: FY23A / value | D4: FY24A | E4: FY25A | F4: FY26E | G4: FY27E | H4: FY28E | I4: FY29E | J4: FY30E | L4: Notes / source
A6: Scenario selector (1 = Base, 2 = Bull, 3 = Bear) | B6: # | C6: 1 | L6: Change this cell to flip every scenario-driven assumption below. All three statements and the DCF update live.
A7: Active scenario | C7: =CHOOSE(C6,"Base","Bull","Bear")
A9: A. SCENARIO-DRIVEN ASSUMPTIONS (live row = CHOOSE of the three cases)
A10: Constant-currency USD growth adjustment (all verticals): Base | B10: pp | F10: 0 | G10: 0 | H10: 0 | I10: 0 | J10: 0 | L10: Added to every vertical growth rate in section B. Base = 0.
A11: Constant-currency USD growth adjustment: Bull | B11: pp | F11: 0.015 | G11: 0.02 | H11: 0.02 | I11: 0.02 | J11: 0.02 | L11: Faster GenAI-led deal ramp-up, discretionary spend recovery, large-deal conversion.
A12: Constant-currency USD growth adjustment: Bear | B12: pp | F12: -0.02 | G12: -0.025 | H12: -0.025 | I12: -0.025 | J12: -0.02 | L12: Discretionary spend stays weak, AI-driven deflation of effort-based pricing, US/Europe slowdown.
A13: Constant-currency USD growth adjustment: LIVE | B13: pp | F13: =CHOOSE($C$6,F10,F11,F12) | G13: =CHOOSE($C$6,G10,G11,G12) | H13: =CHOOSE($C$6,H10,H11,H12) | I13: =CHOOSE($C$6,I10,I11,I12) | J13: =CHOOSE($C$6,J10,J11,J12)
A15: Employee cost per head growth (INR): Base | B15: % | F15: 0.04 | G15: 0.045 | H15: 0.045 | I15: 0.045 | J15: 0.045 | L15: FY25A: ~Rs26.8 lakh per average employee. Wage inflation + FX translation on overseas staff, partly offset by pyramid / utilisation gains.
A16: Employee cost per head growth (INR): Bull | B16: % | F16: 0.036 | G16: 0.041 | H16: 0.041 | I16: 0.041 | J16: 0.041 | L16: Base less 0.4pp: stronger pyramid, automation and utilisation.
A17: Employee cost per head growth (INR): Bear | B17: % | F17: 0.045 | G17: 0.05 | H17: 0.05 | I17: 0.05 | J17: 0.05 | L17: Base plus 0.5pp: wage pressure, AI-skill premiums, weaker pricing power.
A18: Employee cost per head growth (INR): LIVE | B18: % | F18: =CHOOSE($C$6,F15,F16,F17) | G18: =CHOOSE($C$6,G15,G16,G17) | H18: =CHOOSE($C$6,H15,H16,H17) | I18: =CHOOSE($C$6,I15,I16,I17) | J18: =CHOOSE($C$6,J15,J16,J17)
A20: B. REVENUE: CONSTANT-CURRENCY USD GROWTH BY INDUSTRY VERTICAL (Base) AND INR/USD
A21: Financial Services (incl. Insurance) - USD growth (Base) | B21: % | D21: =Segments!D58/Segments!C58-1 | E21: =Segments!E58/Segments!D58-1 | F21: 0.025 | G21: 0.055 | H21: 0.065 | I21: 0.07 | J21: 0.065 | L21: FY25A USD growth is derived from INR segment revenue at the average INR/USD rate (cross-currency effects included). FY26E anchored to management FY26 constant-currency guidance of 0-3% issued with Q4 FY25 results (public release, not in the Annual Report) - verify.
A22: Retail (incl. CPG, Logistics) - USD growth (Base) | B22: % | D22: =Segments!D59/Segments!C59-1 | E22: =Segments!E59/Segments!D59-1 | F22: 0.005 | G22: 0.035 | H22: 0.05 | I22: 0.055 | J22: 0.055
A23: Communication (incl. Telecom OEM, Media) - USD growth (Base) | B23: % | D23: =Segments!D60/Segments!C60-1 | E23: =Segments!E60/Segments!D60-1 | F23: 0.01 | G23: 0.04 | H23: 0.055 | I23: 0.06 | J23: 0.06
A24: Energy, Utilities, Resources & Services - USD growth (Base) | B24: % | D24: =Segments!D61/Segments!C61-1 | E24: =Segments!E61/Segments!D61-1 | F24: 0.035 | G24: 0.06 | H24: 0.07 | I24: 0.07 | J24: 0.065
A25: Manufacturing - USD growth (Base) | B25: % | D25: =Segments!D62/Segments!C62-1 | E25: =Segments!E62/Segments!D62-1 | F25: 0.04 | G25: 0.07 | H25: 0.08 | I25: 0.08 | J25: 0.075
A26: Hi-Tech - USD growth (Base) | B26: % | D26: =Segments!D63/Segments!C63-1 | E26: =Segments!E63/Segments!D63-1 | F26: -0.01 | G26: 0.03 | H26: 0.05 | I26: 0.055 | J26: 0.055
A27: Life Sciences (incl. Healthcare) - USD growth (Base) | B27: % | D27: =Segments!D64/Segments!C64-1 | E27: =Segments!E64/Segments!D64-1 | F27: 0.025 | G27: 0.05 | H27: 0.06 | I27: 0.065 | J27: 0.06
A28: All other segments (India, Japan, China, Public Services) - USD growth (Base) | B28: % | D28: =Segments!D65/Segments!C65-1 | E28: =Segments!E65/Segments!D65-1 | F28: 0.03 | G28: 0.05 | H28: 0.06 | I28: 0.06 | J28: 0.06
A29: INR depreciation vs USD (average rate, YoY) | B29: % | D29: =Segments!D48/Segments!C48-1 | E29: =Segments!E48/Segments!D48-1 | F29: 0.02 | G29: 0.015 | H29: 0.015 | I29: 0.015 | J29: 0.015 | L29: FY25A average Rs84.55/US$ (FY24A 82.79). Assumes steady ~1.5% p.a. depreciation consistent with inflation differentials; a major earnings sensitivity.
A31: C. HEADCOUNT, COSTS AND MARGIN DRIVERS
A32: Year-end headcount growth (Base, before scenario link) | B32: % | E32: =Segments!E49/Segments!D49-1 | F32: 0.01 | G32: 0.025 | H32: 0.035 | I32: 0.04 | J32: 0.035 | L32: FY25A +2.0% (317,240 -> 323,578). Headcount grows at roughly half of revenue growth as productivity (automation, GenAI) rises.
A33: Headcount sensitivity to scenario growth adjustment (elasticity) | B33: x | C33: 0.8 | L33: Bull/Bear revenue change flows 80% into headcount; the rest is productivity / pricing.
A34: Cost of technical sub-contractors, % of revenue | B34: % | C34: =IS!C11/IS!C7 | D34: =IS!D11/IS!D7 | E34: =IS!E11/IS!E7 | F34: 0.079 | G34: 0.079 | H34: 0.079 | I34: 0.079 | J34: 0.079
A35: Travel expenses, % of revenue | B35: % | C35: =IS!C12/IS!C7 | D35: =IS!D12/IS!D7 | E35: =IS!E12/IS!E7 | F35: 0.0116 | G35: 0.0116 | H35: 0.0116 | I35: 0.0116 | J35: 0.0116
A36: Cost of software packages and others, % of revenue | B36: % | C36: =IS!C13/IS!C7 | D36: =IS!D13/IS!D7 | E36: =IS!E13/IS!E7 | F36: 0.0975 | G36: 0.0975 | H36: 0.0975 | I36: 0.0975 | J36: 0.0975 | L36: Third-party software / hardware bought for client deals (pass-through, low margin). Rose from 7.4% (FY23) to 9.8% (FY25) with large-deal mix; held at FY25 level.
A37: Communication expenses, % of revenue | B37: % | C37: =IS!C14/IS!C7 | D37: =IS!D14/IS!D7 | E37: =IS!E14/IS!E7 | F37: 0.0038 | G37: 0.0038 | H37: 0.0038 | I37: 0.0038 | J37: 0.0038
A38: Consultancy and professional charges, % of revenue | B38: % | C38: =IS!C15/IS!C7 | D38: =IS!D15/IS!D7 | E38: =IS!E15/IS!E7 | F38: 0.0102 | G38: 0.0102 | H38: 0.0102 | I38: 0.0102 | J38: 0.0102
A39: Other expenses, % of revenue | B39: % | C39: =IS!C18/IS!C7 | D39: =IS!D18/IS!D7 | E39: =IS!E18/IS!E7 | F39: 0.0294 | G39: 0.0294 | H39: 0.0294 | I39: 0.0294 | J39: 0.0294
A40: Stock-based compensation (non-cash, inside employee cost), % of revenue | B40: % | C40: =CF!C15/IS!C7 | D40: =CF!D15/IS!D7 | E40: =CF!E15/IS!E7 | F40: 0.005 | G40: 0.005 | H40: 0.005 | I40: 0.005 | J40: 0.005 | L40: Added back in the cash flow statement and credited to equity; NOT added back in FCFF (treated as a real cost).
A42: D. OTHER P&L, CAPEX, LEASES AND BALANCE SHEET
A43: Other income: yield on opening cash + investments | B43: % | D43: =IS!D8/(BS!C23+BS!C21+BS!C13) | E43: =IS!E8/(BS!D23+BS!D21+BS!D13) | F43: 0.065 | G43: 0.065 | H43: 0.065 | I43: 0.065 | J43: 0.065 | L43: FY25A: 9.1% total, of which interest & dividend ~6.5%; the rest is FX / investment gains and Rs327 crore of interest on tax refunds (not repeated).
A44: Tax rate (on PBT; and on EBIT in the DCF) | B44: % | C44: =IS!C23/IS!C20 | D44: =IS!D23/IS!D20 | E44: =IS!E23/IS!E20 | F44: 0.275 | G44: 0.275 | H44: 0.275 | I44: 0.275 | J44: 0.275 | L44: Effective rate FY23A 27.7%, FY24A 27.1%, FY25A 28.9% (statutory 25.17% plus overseas taxes and non-deductible items).
A45: Non-controlling interest, % of PAT | B45: % | C45: =IS!C25/IS!C24 | D45: =IS!D25/IS!D24 | E45: =IS!E25/IS!E24 | F45: 0.0014 | G45: 0.0014 | H45: 0.0014 | I45: 0.0014 | J45: 0.0014
A46: Dividend per share paid in year (Rs) | B46: Rs | F46: 45 | G46: 48 | H46: 52 | I46: 56 | J46: 60 | L46: FY26E = FY25 final Rs22 + FY26 interim ~Rs23. Policy: ~85% of free cash flow returned over five years via dividends / buybacks. FY25A paid Rs49 incl. Rs8 special.
A47: Dividends to NCI, % of NCI profit | B47: % | F47: 0.5 | G47: 0.5 | H47: 0.5 | I47: 0.5 | J47: 0.5
A48: Shares outstanding (crore) = equity share capital Rs2,073 crore / Rs5 | B48: crore | D48: 413.857 | E48: 414.161 | F48: 414.6 | G48: 414.6 | H48: 414.6 | I48: 414.6 | J48: 414.6 | L48: Hist = weighted average basic shares (EPS note). 1 crore = 10 million.
A49: Capex (PPE + intangibles), % of revenue | B49: % | C49: =-(CF!C28)/IS!C7 | D49: =-(CF!D28)/IS!D7 | E49: =-(CF!E28)/IS!E7 | F49: 0.016 | G49: 0.016 | H49: 0.016 | I49: 0.016 | J49: 0.016 | L49: FY25A 1.4% / FY24A 1.4% / FY23A 1.8%. Asset-light; campus build-out largely complete. Held at 1.6% for sustaining + AI infrastructure.
A50: PPE share of capex | B50: % | F50: 0.95 | G50: 0.95 | H50: 0.95 | I50: 0.95 | J50: 0.95
A51: New lease additions (ROU), % of revenue | B51: % | D51: 0.01425 | E51: 0.01323 | F51: 0.0135 | G51: 0.0135 | H51: 0.0135 | I51: 0.0135 | J51: 0.0135 | L51: FY25A Rs2,156 crore; FY24A Rs2,190 crore (Note 2.21).
A52: D&A rate on opening net block (PPE + ROU + intangibles) | B52: % | D52: =IS!D16/(BS!C8+BS!C9+BS!C12) | E52: =IS!E16/(BS!D8+BS!D9+BS!D12) | F52: 0.235 | G52: 0.235 | H52: 0.235 | I52: 0.235 | J52: 0.235 | L52: Uniform rate. FY25A 23.7%, FY24A 21.3%. Intangibles rose in FY25 after the in-tech acquisition.
A53: Finance cost: rate on opening lease liabilities | B53: % | D53: =IS!D17/(BS!C44+BS!C38) | E53: =IS!E17/(BS!D44+BS!D38) | F53: 0.05 | G53: 0.05 | H53: 0.05 | I53: 0.05 | J53: 0.05 | L53: Infosys has NO borrowings: finance cost is almost entirely lease interest (FY25A Rs341 crore of Rs416 crore).
A54: Lease payments (principal + interest), % of opening lease liability | B54: % | D54: =-CF!D36/(BS!C44+BS!C38) | E54: =-CF!E36/(BS!D44+BS!D38) | F54: 0.28 | G54: 0.28 | H54: 0.28 | I54: 0.28 | J54: 0.28 | L54: FY25A Rs2,355 crore / opening Rs8,359 crore = 28.2% (Infosys presents total lease payments in financing).
A55: Current portion of lease liabilities, % of total | B55: % | C55: =BS!C44/(BS!C44+BS!C38) | D55: =BS!D44/(BS!D44+BS!D38) | E55: =BS!E44/(BS!E44+BS!E38) | F55: =BS!$E$44/(BS!$E$44+BS!$E$38) | G55: =BS!$E$44/(BS!$E$44+BS!$E$38) | H55: =BS!$E$44/(BS!$E$44+BS!$E$38) | I55: =BS!$E$44/(BS!$E$44+BS!$E$38) | J55: =BS!$E$44/(BS!$E$44+BS!$E$38)
A57: E. WORKING CAPITAL, % OF REVENUE (forecast default = FY25 balance / FY25 revenue)
A58: Trade receivables | B58: % | C58: =BS!C22/IS!C7 | D58: =BS!D22/IS!D7 | E58: =BS!E22/IS!E7 | F58: =BS!$E$22/IS!$E$7 | G58: =BS!$E$22/IS!$E$7 | H58: =BS!$E$22/IS!$E$7 | I58: =BS!$E$22/IS!$E$7 | J58: =BS!$E$22/IS!$E$7
A59: Other financial assets (current; incl. unbilled revenue) | B59: % | C59: =BS!C25/IS!C7 | D59: =BS!D25/IS!D7 | E59: =BS!E25/IS!E7 | F59: =BS!$E$25/IS!$E$7 | G59: =BS!$E$25/IS!$E$7 | H59: =BS!$E$25/IS!$E$7 | I59: =BS!$E$25/IS!$E$7 | J59: =BS!$E$25/IS!$E$7
A60: Other current assets | B60: % | C60: =BS!C27/IS!C7 | D60: =BS!D27/IS!D7 | E60: =BS!E27/IS!E7 | F60: =BS!$E$27/IS!$E$7 | G60: =BS!$E$27/IS!$E$7 | H60: =BS!$E$27/IS!$E$7 | I60: =BS!$E$27/IS!$E$7 | J60: =BS!$E$27/IS!$E$7
A61: Trade payables | B61: % | C61: =BS!C45/IS!C7 | D61: =BS!D45/IS!D7 | E61: =BS!E45/IS!E7 | F61: =BS!$E$45/IS!$E$7 | G61: =BS!$E$45/IS!$E$7 | H61: =BS!$E$45/IS!$E$7 | I61: =BS!$E$45/IS!$E$7 | J61: =BS!$E$45/IS!$E$7
A62: Other financial liabilities (current; incl. accrued compensation) | B62: % | C62: =BS!C46/IS!C7 | D62: =BS!D46/IS!D7 | E62: =BS!E46/IS!E7 | F62: =BS!$E$46/IS!$E$7 | G62: =BS!$E$46/IS!$E$7 | H62: =BS!$E$46/IS!$E$7 | I62: =BS!$E$46/IS!$E$7 | J62: =BS!$E$46/IS!$E$7
A63: Other current liabilities (incl. unearned revenue) | B63: % | C63: =BS!C47/IS!C7 | D63: =BS!D47/IS!D7 | E63: =BS!E47/IS!E7 | F63: =BS!$E$47/IS!$E$7 | G63: =BS!$E$47/IS!$E$7 | H63: =BS!$E$47/IS!$E$7 | I63: =BS!$E$47/IS!$E$7 | J63: =BS!$E$47/IS!$E$7
A64: Provisions | B64: % | C64: =BS!C48/IS!C7 | D64: =BS!D48/IS!D7 | E64: =BS!E48/IS!E7 | F64: =BS!$E$48/IS!$E$7 | G64: =BS!$E$48/IS!$E$7 | H64: =BS!$E$48/IS!$E$7 | I64: =BS!$E$48/IS!$E$7 | J64: =BS!$E$48/IS!$E$7
A66: F. VALUATION INPUTS
A67: Terminal growth rate (Gordon growth, INR) | B67: % | C67: 0.055 | L67: ~4% USD growth + ~1.5% INR depreciation. Below nominal GDP (9-10%) and in line with long-run IT-services demand growth; sensitised 4.5-6.5%.
A68: Exit EV/EBITDA multiple (FY30E) | B68: x | C68: 14 | L68: Cross-check method. Infosys trades ~15x EV/EBITDA on FY25 (market cap Rs6.5 lakh crore less ~Rs0.5 lakh crore net cash / Rs0.39 lakh crore EBITDA).
A69: Weight on Gordon-growth value in blended price | B69: % | C69: 0.5
A70: Mid-year discounting (1 = on, 0 = year-end) | B70: # | C70: 1
A71: Lease treatment (1 = leases as debt, 2 = pre-Ind AS 116 / leases as opex) | B71: # | C71: 1 | L71: 1: lease liabilities in net debt and new ROU additions deducted from FCFF. 2: lease cash cost deducted from FCFF and lease liabilities excluded from net debt.
A72: Include working-capital inflow in terminal FCFF (1 = yes, 0 = no) | B72: # | C72: 0 | L72: Default OFF to avoid capitalising a growth-funded working-capital release in perpetuity.
A73: NCI valuation: multiple of book value | B73: x | C73: 1 | L73: Book NCI is only Rs385 crore (0.06% of market cap); immaterial.
A74: Other debt-like items (Rs crore) | B74: Rs cr | C74: 0 | L74: None: no borrowings. Contingent tax / legal exposures are disclosed in the notes but not provided for in the valuation.
A75: Company-reported market capitalisation, 31-Mar-2025 (Rs crore) | B75: Rs cr | C75: 652332 | L75: Annual Report FY25, financial highlights (US$75,797 mn); price-to-earnings 24.4x.
A76: Implied market price at valuation date (Rs/share) | B76: Rs | C76: =C75/F48 | L76: Market capitalisation / 414.6 crore shares. Cross-check: 24.4x P/E x FY25 EPS Rs64.50 = Rs1,574.

Sheet Segments
A1: Infosys Limited - Segment Build (Revenue & EBITDA)
A2: Rs crore unless stated | Consolidated Ind AS financials | FY ends 31 March | Blue = hard-coded input / reported data, Black = formula, Green = cross-sheet link
A4: Rs crore | B4: Unit | C4: FY23A | D4: FY24A | E4: FY25A | F4: FY26E | G4: FY27E | H4: FY28E | I4: FY29E | J4: FY30E | L4: Notes / source
A6: A. REPORTED DATA - Rs crore (Note 2.26 Segment reporting; FY23 from the FY24 Annual Report)
A7: Revenue by industry vertical (external customers)
A8: Financial Services (incl. Insurance) | B8: Rs cr | C8: 43763 | D8: 42158 | E8: 45175
A9: Retail (incl. CPG, Logistics) | B9: Rs cr | C9: 21204 | D9: 22504 | E9: 22059
A10: Communication (incl. Telecom OEM, Media) | B10: Rs cr | C10: 18086 | D10: 17991 | E10: 19108
A11: Energy, Utilities, Resources & Services | B11: Rs cr | C11: 18539 | D11: 20035 | E11: 21710
A12: Manufacturing | B12: Rs cr | C12: 19035 | D12: 22298 | E12: 25207
A13: Hi-Tech | B13: Rs cr | C13: 11867 | D13: 12411 | E13: 13090
A14: Life Sciences (incl. Healthcare) | B14: Rs cr | C14: 10085 | D14: 11515 | E14: 11831
A15: All other segments (India, Japan, China, Public Services) | B15: Rs cr | C15: 4188 | D15: 4758 | E15: 4810
A16: Revenue from operations | B16: Rs cr | C16: =SUM(C8:C15) | D16: =SUM(D8:D15) | E16: =SUM(E8:E15)
A17: Segment operating income (before unallocable D&A)
A18: Financial Services (incl. Insurance) | B18: Rs cr | C18: 10843 | D18: 9324 | E18: 11099
A19: Retail (incl. CPG, Logistics) | B19: Rs cr | C19: 6396 | D19: 6882 | E19: 7133
A20: Communication (incl. Telecom OEM, Media) | B20: Rs cr | C20: 3759 | D20: 3688 | E20: 3341
A21: Energy, Utilities, Resources & Services | B21: Rs cr | C21: 5155 | D21: 5523 | E21: 6097
A22: Manufacturing | B22: Rs cr | C22: 3113 | D22: 4197 | E22: 4856
A23: Hi-Tech | B23: Rs cr | C23: 2959 | D23: 3153 | E23: 3220
A24: Life Sciences (incl. Healthcare) | B24: Rs cr | C24: 2566 | D24: 2898 | E24: 2663
A25: All other segments (India, Japan, China, Public Services) | B25: Rs cr | C25: 339 | D25: 760 | E25: 827
A26: Total segment operating income (= EBITDA) | B26: Rs cr | C26: =SUM(C18:C25) | D26: =SUM(D18:D25) | E26: =SUM(E18:E25)
A27: Less: unallocable expenses (= depreciation & amortisation) | B27: Rs cr | C27: 4225 | D27: 4678 | E27: 4812
A28: Operating profit (company definition, before other income) | B28: Rs cr | C28: =C26-C27 | D28: =D26-D27 | E28: =E26-E27
A29: Segment operating margin
A30: Financial Services (incl. Insurance) | B30: % | C30: =C18/C8 | D30: =D18/D8 | E30: =E18/E8
A31: Retail (incl. CPG, Logistics) | B31: % | C31: =C19/C9 | D31: =D19/D9 | E31: =E19/E9
A32: Communication (incl. Telecom OEM, Media) | B32: % | C32: =C20/C10 | D32: =D20/D10 | E32: =E20/E10
A33: Energy, Utilities, Resources & Services | B33: % | C33: =C21/C11 | D33: =D21/D11 | E33: =E21/E11
A34: Manufacturing | B34: % | C34: =C22/C12 | D34: =D22/D12 | E34: =E22/E12
A35: Hi-Tech | B35: % | C35: =C23/C13 | D35: =D23/D13 | E35: =E23/E13
A36: Life Sciences (incl. Healthcare) | B36: % | C36: =C24/C14 | D36: =D24/D14 | E36: =E24/E14
A37: All other segments (India, Japan, China, Public Services) | B37: % | C37: =C25/C15 | D37: =D25/D15 | E37: =E25/E15
A38: Total segment margin (EBITDA margin) | B38: % | C38: =C26/C16 | D38: =D26/D16 | E38: =E26/E16
A39: Revenue by geography
A40: North America | B40: Rs cr | C40: 90724 | D40: 92411 | E40: 94397
A41: Europe | B41: Rs cr | C41: 37675 | D41: 42267 | E41: 48595
A42: India | B42: Rs cr | C42: 3861 | D42: 3881 | E42: 5014
A43: Rest of the World | B43: Rs cr | C43: 14507 | D43: 15111 | E43: 14984
A44: Total | B44: Rs cr | C44: =SUM(C40:C43) | D44: =SUM(D40:D43) | E44: =SUM(E40:E43)
A45: North America % of revenue | B45: % | C45: =C40/C44 | D45: =D40/D44 | E45: =E40/E44
A46: Currency and workforce KPIs
A47: Revenue in US$ million (company-reported) | B47: US$ mn | C47: 18212 | D47: 18562 | E47: 19277 | L47: Annual Report five-year summary.
A48: Implied average INR/USD rate (revenue Rs crore x 10 / US$ mn) | B48: Rs | C48: =C16*10/C47 | D48: =D16*10/D47 | E48: =E16*10/E47
A49: Headcount - end of year (employees) | B49: # | D49: 317240 | E49: 323578 | L49: Annual Reports FY24 / FY25 (permanent employees).
A50: Average headcount | B50: # | E50: =AVERAGE(D49,E49)
A51: Employee cost per average head (Rs lakh) | B51: Rs lakh | E51: =IS!E10/E50*100
A52: Revenue per average head (Rs lakh) | B52: Rs lakh | E52: =IS!E7/E50*100
A54: B. REVENUE BUILD: USD revenue by vertical x INR/USD
A55: Hist columns: USD revenue derived = INR revenue / average rate. Forecast: USD revenue = prior year x (1 + vertical growth + scenario adjustment); INR = USD x rate.
A56: Average INR/USD rate | B56: Rs | C56: =C48 | D56: =D48 | E56: =E48 | F56: =E56*(1+Inputs!F29) | G56: =F56*(1+Inputs!G29) | H56: =G56*(1+Inputs!H29) | I56: =H56*(1+Inputs!I29) | J56: =I56*(1+Inputs!J29)
A57: Revenue by vertical in US$ million
A58: Financial Services (incl. Insurance) | B58: US$ mn | C58: =C8*10/C56 | D58: =D8*10/D56 | E58: =E8*10/E56 | F58: =E58*(1+Inputs!F21+Inputs!F13) | G58: =F58*(1+Inputs!G21+Inputs!G13) | H58: =G58*(1+Inputs!H21+Inputs!H13) | I58: =H58*(1+Inputs!I21+Inputs!I13) | J58: =I58*(1+Inputs!J21+Inputs!J13)
A59: Retail (incl. CPG, Logistics) | B59: US$ mn | C59: =C9*10/C56 | D59: =D9*10/D56 | E59: =E9*10/E56 | F59: =E59*(1+Inputs!F22+Inputs!F13) | G59: =F59*(1+Inputs!G22+Inputs!G13) | H59: =G59*(1+Inputs!H22+Inputs!H13) | I59: =H59*(1+Inputs!I22+Inputs!I13) | J59: =I59*(1+Inputs!J22+Inputs!J13)
A60: Communication (incl. Telecom OEM, Media) | B60: US$ mn | C60: =C10*10/C56 | D60: =D10*10/D56 | E60: =E10*10/E56 | F60: =E60*(1+Inputs!F23+Inputs!F13) | G60: =F60*(1+Inputs!G23+Inputs!G13) | H60: =G60*(1+Inputs!H23+Inputs!H13) | I60: =H60*(1+Inputs!I23+Inputs!I13) | J60: =I60*(1+Inputs!J23+Inputs!J13)
A61: Energy, Utilities, Resources & Services | B61: US$ mn | C61: =C11*10/C56 | D61: =D11*10/D56 | E61: =E11*10/E56 | F61: =E61*(1+Inputs!F24+Inputs!F13) | G61: =F61*(1+Inputs!G24+Inputs!G13) | H61: =G61*(1+Inputs!H24+Inputs!H13) | I61: =H61*(1+Inputs!I24+Inputs!I13) | J61: =I61*(1+Inputs!J24+Inputs!J13)
A62: Manufacturing | B62: US$ mn | C62: =C12*10/C56 | D62: =D12*10/D56 | E62: =E12*10/E56 | F62: =E62*(1+Inputs!F25+Inputs!F13) | G62: =F62*(1+Inputs!G25+Inputs!G13) | H62: =G62*(1+Inputs!H25+Inputs!H13) | I62: =H62*(1+Inputs!I25+Inputs!I13) | J62: =I62*(1+Inputs!J25+Inputs!J13)
A63: Hi-Tech | B63: US$ mn | C63: =C13*10/C56 | D63: =D13*10/D56 | E63: =E13*10/E56 | F63: =E63*(1+Inputs!F26+Inputs!F13) | G63: =F63*(1+Inputs!G26+Inputs!G13) | H63: =G63*(1+Inputs!H26+Inputs!H13) | I63: =H63*(1+Inputs!I26+Inputs!I13) | J63: =I63*(1+Inputs!J26+Inputs!J13)
A64: Life Sciences (incl. Healthcare) | B64: US$ mn | C64: =C14*10/C56 | D64: =D14*10/D56 | E64: =E14*10/E56 | F64: =E64*(1+Inputs!F27+Inputs!F13) | G64: =F64*(1+Inputs!G27+Inputs!G13) | H64: =G64*(1+Inputs!H27+Inputs!H13) | I64: =H64*(1+Inputs!I27+Inputs!I13) | J64: =I64*(1+Inputs!J27+Inputs!J13)
A65: All other segments (India, Japan, China, Public Services) | B65: US$ mn | C65: =C15*10/C56 | D65: =D15*10/D56 | E65: =E15*10/E56 | F65: =E65*(1+Inputs!F28+Inputs!F13) | G65: =F65*(1+Inputs!G28+Inputs!G13) | H65: =G65*(1+Inputs!H28+Inputs!H13) | I65: =H65*(1+Inputs!I28+Inputs!I13) | J65: =I65*(1+Inputs!J28+Inputs!J13)
A66: Total revenue (US$ mn) | B66: US$ mn | C66: =SUM(C58:C65) | D66: =SUM(D58:D65) | E66: =SUM(E58:E65) | F66: =SUM(F58:F65) | G66: =SUM(G58:G65) | H66: =SUM(H58:H65) | I66: =SUM(I58:I65) | J66: =SUM(J58:J65)
A67: growth (USD, ~constant-currency proxy) | B67: % | D67: =D66/C66-1 | E67: =E66/D66-1 | F67: =F66/E66-1 | G67: =G66/F66-1 | H67: =H66/G66-1 | I67: =I66/H66-1 | J67: =J66/I66-1
A68: Revenue by vertical in Rs crore
A69: Financial Services (incl. Insurance) | B69: Rs cr | C69: =C8 | D69: =D8 | E69: =E8 | F69: =F58*F56/10 | G69: =G58*G56/10 | H69: =H58*H56/10 | I69: =I58*I56/10 | J69: =J58*J56/10
A70: Retail (incl. CPG, Logistics) | B70: Rs cr | C70: =C9 | D70: =D9 | E70: =E9 | F70: =F59*F56/10 | G70: =G59*G56/10 | H70: =H59*H56/10 | I70: =I59*I56/10 | J70: =J59*J56/10
A71: Communication (incl. Telecom OEM, Media) | B71: Rs cr | C71: =C10 | D71: =D10 | E71: =E10 | F71: =F60*F56/10 | G71: =G60*G56/10 | H71: =H60*H56/10 | I71: =I60*I56/10 | J71: =J60*J56/10
A72: Energy, Utilities, Resources & Services | B72: Rs cr | C72: =C11 | D72: =D11 | E72: =E11 | F72: =F61*F56/10 | G72: =G61*G56/10 | H72: =H61*H56/10 | I72: =I61*I56/10 | J72: =J61*J56/10
A73: Manufacturing | B73: Rs cr | C73: =C12 | D73: =D12 | E73: =E12 | F73: =F62*F56/10 | G73: =G62*G56/10 | H73: =H62*H56/10 | I73: =I62*I56/10 | J73: =J62*J56/10
A74: Hi-Tech | B74: Rs cr | C74: =C13 | D74: =D13 | E74: =E13 | F74: =F63*F56/10 | G74: =G63*G56/10 | H74: =H63*H56/10 | I74: =I63*I56/10 | J74: =J63*J56/10
A75: Life Sciences (incl. Healthcare) | B75: Rs cr | C75: =C14 | D75: =D14 | E75: =E14 | F75: =F64*F56/10 | G75: =G64*G56/10 | H75: =H64*H56/10 | I75: =I64*I56/10 | J75: =J64*J56/10
A76: All other segments (India, Japan, China, Public Services) | B76: Rs cr | C76: =C15 | D76: =D15 | E76: =E15 | F76: =F65*F56/10 | G76: =G65*G56/10 | H76: =H65*H56/10 | I76: =I65*I56/10 | J76: =J65*J56/10
A77: CONSOLIDATED REVENUE FROM OPERATIONS | B77: Rs cr | C77: =SUM(C69:C76) | D77: =SUM(D69:D76) | E77: =SUM(E69:E76) | F77: =SUM(F69:F76) | G77: =SUM(G69:G76) | H77: =SUM(H69:H76) | I77: =SUM(I69:I76) | J77: =SUM(J69:J76)
A78: growth (INR) | B78: % | D78: =D77/C77-1 | E78: =E77/D77-1 | F78: =F77/E77-1 | G78: =G77/F77-1 | H78: =H77/G77-1 | I78: =I77/H77-1 | J78: =J77/I77-1
A79: Financial Services share of revenue | B79: % | C79: =C69/C77 | D79: =D69/D77 | E79: =E69/E77 | F79: =F69/F77 | G79: =G69/G77 | H79: =H69/H77 | I79: =I69/I77 | J79: =J69/J77
A81: Headcount and employee cost build
A82: Headcount - end of year | B82: # | D82: =D49 | E82: =E49 | F82: =E82*(1+Inputs!F32+Inputs!$C$33*Inputs!F13) | G82: =F82*(1+Inputs!G32+Inputs!$C$33*Inputs!G13) | H82: =G82*(1+Inputs!H32+Inputs!$C$33*Inputs!H13) | I82: =H82*(1+Inputs!I32+Inputs!$C$33*Inputs!I13) | J82: =I82*(1+Inputs!J32+Inputs!$C$33*Inputs!J13)
A83: Average headcount | B83: # | E83: =E50 | F83: =AVERAGE(E82,F82) | G83: =AVERAGE(F82,G82) | H83: =AVERAGE(G82,H82) | I83: =AVERAGE(H82,I82) | J83: =AVERAGE(I82,J82)
A84: Employee cost per average head (Rs lakh) | B84: Rs lakh | E84: =E51 | F84: =E84*(1+Inputs!F18) | G84: =F84*(1+Inputs!G18) | H84: =G84*(1+Inputs!H18) | I84: =H84*(1+Inputs!I18) | J84: =I84*(1+Inputs!J18)
A85: Employee benefit expense (Rs crore) | B85: Rs cr | C85: =IS!C10 | D85: =IS!D10 | E85: =IS!E10 | F85: =F83*F84/100 | G85: =G83*G84/100 | H85: =H83*H84/100 | I85: =I83*I84/100 | J85: =J83*J84/100
A86: employee cost % of revenue | B86: % | C86: =C85/C77 | D86: =D85/D77 | E86: =E85/E77 | F86: =F85/F77 | G86: =G85/G77 | H86: =H85/H77 | I86: =I85/I77 | J86: =J85/J77
A87: Revenue per average head (Rs lakh) | B87: Rs lakh | E87: =E52 | F87: =F77/F83*100 | G87: =G77/G83*100 | H87: =H77/H83*100 | I87: =I77/I83*100 | J87: =J77/J83*100
A88: growth in revenue per head | B88: % | F88: =F87/E87-1 | G88: =G87/F87-1 | H88: =H87/G87-1 | I88: =I87/H87-1 | J88: =J87/I87-1
A89: US$ revenue per average head (US$ thousand) | B89: US$ k | E89: =E66/E83*1000 | F89: =F66/F83*1000 | G89: =G66/G83*1000 | H89: =H66/H83*1000 | I89: =I66/I83*1000 | J89: =J66/J83*1000

Sheet IS
A1: Infosys Limited - Consolidated Income Statement
A2: Rs crore unless stated | Consolidated Ind AS financials | FY ends 31 March | Blue = hard-coded input / reported data, Black = formula, Green = cross-sheet link
A4: Rs crore | B4: Unit | C4: FY23A | D4: FY24A | E4: FY25A | F4: FY26E | G4: FY27E | H4: FY28E | I4: FY29E | J4: FY30E | L4: Notes / source
A6: CONSOLIDATED STATEMENT OF PROFIT AND LOSS (Rs crore, Ind AS)
A7: Revenue from operations | B7: Rs cr | C7: 146767 | D7: 153670 | E7: 162990 | F7: =Segments!F77 | G7: =Segments!G77 | H7: =Segments!H77 | I7: =Segments!I77 | J7: =Segments!J77
A8: Other income, net | B8: Rs cr | C8: 2701 | D8: 4711 | E8: 3600 | F8: =Inputs!F43*(BS!E23+BS!E21+BS!E13) | G8: =Inputs!G43*(BS!F23+BS!F21+BS!F13) | H8: =Inputs!H43*(BS!G23+BS!G21+BS!G13) | I8: =Inputs!I43*(BS!H23+BS!H21+BS!H13) | J8: =Inputs!J43*(BS!I23+BS!I21+BS!I13)
A9: Total income | B9: Rs cr | C9: =C7+C8 | D9: =D7+D8 | E9: =E7+E8 | F9: =F7+F8 | G9: =G7+G8 | H9: =H7+H8 | I9: =I7+I8 | J9: =J7+J8
A10: Employee benefit expenses | B10: Rs cr | C10: 78359 | D10: 82620 | E10: 85950 | F10: =Segments!F85 | G10: =Segments!G85 | H10: =Segments!H85 | I10: =Segments!I85 | J10: =Segments!J85
A11: Cost of technical sub-contractors | B11: Rs cr | C11: 14062 | D11: 12232 | E11: 12937 | F11: =Inputs!F34*F7 | G11: =Inputs!G34*G7 | H11: =Inputs!H34*H7 | I11: =Inputs!I34*I7 | J11: =Inputs!J34*J7
A12: Travel expenses | B12: Rs cr | C12: 1525 | D12: 1759 | E12: 1894 | F12: =Inputs!F35*F7 | G12: =Inputs!G35*G7 | H12: =Inputs!H35*H7 | I12: =Inputs!I35*I7 | J12: =Inputs!J35*J7
A13: Cost of software packages and others | B13: Rs cr | C13: 10902 | D13: 13515 | E13: 15911 | F13: =Inputs!F36*F7 | G13: =Inputs!G36*G7 | H13: =Inputs!H36*H7 | I13: =Inputs!I36*I7 | J13: =Inputs!J36*J7
A14: Communication expenses | B14: Rs cr | C14: 713 | D14: 677 | E14: 620 | F14: =Inputs!F37*F7 | G14: =Inputs!G37*G7 | H14: =Inputs!H37*H7 | I14: =Inputs!I37*I7 | J14: =Inputs!J37*J7
A15: Consultancy and professional charges | B15: Rs cr | C15: 1684 | D15: 1726 | E15: 1655 | F15: =Inputs!F38*F7 | G15: =Inputs!G38*G7 | H15: =Inputs!H38*H7 | I15: =Inputs!I38*I7 | J15: =Inputs!J38*J7
A16: Depreciation and amortization expenses | B16: Rs cr | C16: 4225 | D16: 4678 | E16: 4812 | F16: =Sched!F28 | G16: =Sched!G28 | H16: =Sched!H28 | I16: =Sched!I28 | J16: =Sched!J28
A17: Finance cost | B17: Rs cr | C17: 284 | D17: 470 | E17: 416 | F17: =Sched!F34 | G17: =Sched!G34 | H17: =Sched!H34 | I17: =Sched!I34 | J17: =Sched!J34
A18: Other expenses | B18: Rs cr | C18: 4392 | D18: 4716 | E18: 4787 | F18: =Inputs!F39*F7 | G18: =Inputs!G39*G7 | H18: =Inputs!H39*H7 | I18: =Inputs!I39*I7 | J18: =Inputs!J39*J7
A19: Total expenses | B19: Rs cr | C19: =SUM(C10:C18) | D19: =SUM(D10:D18) | E19: =SUM(E10:E18) | F19: =SUM(F10:F18) | G19: =SUM(G10:G18) | H19: =SUM(H10:H18) | I19: =SUM(I10:I18) | J19: =SUM(J10:J18)
A20: Profit before tax | B20: Rs cr | C20: =C9-C19 | D20: =D9-D19 | E20: =E9-E19 | F20: =F9-F19 | G20: =G9-G19 | H20: =H9-H19 | I20: =I9-I19 | J20: =J9-J19
A21: Current tax | B21: Rs cr | C21: 9287 | D21: 8390 | E21: 12130 | F21: =Inputs!F44*F20 | G21: =Inputs!G44*G20 | H21: =Inputs!H44*H20 | I21: =Inputs!I44*I20 | J21: =Inputs!J44*J20
A22: Deferred tax | B22: Rs cr | C22: -73 | D22: 1350 | E22: -1272 | F22: 0 | G22: 0 | H22: 0 | I22: 0 | J22: 0
A23: Total tax expense | B23: Rs cr | C23: =C21+C22 | D23: =D21+D22 | E23: =E21+E22 | F23: =F21+F22 | G23: =G21+G22 | H23: =H21+H22 | I23: =I21+I22 | J23: =J21+J22
A24: Profit for the year | B24: Rs cr | C24: =C20-C23 | D24: =D20-D23 | E24: =E20-E23 | F24: =F20-F23 | G24: =G20-G23 | H24: =H20-H23 | I24: =I20-I23 | J24: =J20-J23
A25: attributable to non-controlling interests | B25: Rs cr | C25: 13 | D25: 15 | E25: 37 | F25: =F24*Inputs!F45 | G25: =G24*Inputs!G45 | H25: =H24*Inputs!H45 | I25: =I24*Inputs!I45 | J25: =J24*Inputs!J45
A26: attributable to owners of the Company | B26: Rs cr | C26: 24095 | D26: 26233 | E26: 26713 | F26: =F24-F25 | G26: =G24-G25 | H26: =H24-H25 | I26: =I24-I25 | J26: =J24-J25
A27: Other comprehensive income, net of tax | B27: Rs cr | C27: 514 | D27: 520 | E27: 459 | F27: 0 | G27: 0 | H27: 0 | I27: 0 | J27: 0 | L27: FX translation and fair-value reserves not forecast.
A28: Total comprehensive income | B28: Rs cr | C28: =C24+C27 | D28: =D24+D27 | E28: =E24+E27 | F28: =F24+F27 | G28: =G24+G27 | H28: =H24+H27 | I28: =I24+I27 | J28: =J24+J27
A30: Per-share data
A31: Weighted average shares - basic (crore) | B31: crore | C31: 418.09 | D31: 413.857 | E31: 414.161 | F31: =Inputs!F48 | G31: =Inputs!G48 | H31: =Inputs!H48 | I31: =Inputs!I48 | J31: =Inputs!J48
A32: Basic EPS (Rs) | B32: Rs | C32: =C26/C31 | D32: =D26/D31 | E32: =E26/E31 | F32: =F26/F31 | G32: =G26/G31 | H32: =H26/H31 | I32: =I26/I31 | J32: =J26/J31
A33: Dividend per share paid (Rs) | B33: Rs | F33: =Inputs!F46 | G33: =Inputs!G46 | H33: =Inputs!H46 | I33: =Inputs!I46 | J33: =Inputs!J46
A35: Operating metrics (company definitions)
A36: Operating profit (revenue - all expenses excl. finance cost) | B36: Rs cr | C36: =C7-(C19-C17) | D36: =D7-(D19-D17) | E36: =E7-(E19-E17) | F36: =F7-(F19-F17) | G36: =G7-(G19-G17) | H36: =H7-(H19-H17) | I36: =I7-(I19-I17) | J36: =J7-(J19-J17)
A37: Operating margin | B37: % | C37: =C36/C7 | D37: =D36/D7 | E37: =E36/E7 | F37: =F36/F7 | G37: =G36/G7 | H37: =H36/H7 | I37: =I36/I7 | J37: =J36/J7
A38: EBITDA (operating profit + D&A; excl. other income) | B38: Rs cr | C38: =C36+C16 | D38: =D36+D16 | E38: =E36+E16 | F38: =F36+F16 | G38: =G36+G16 | H38: =H36+H16 | I38: =I36+I16 | J38: =J36+J16
A39: EBITDA margin | B39: % | C39: =C38/C7 | D39: =D38/D7 | E39: =E38/E7 | F39: =F38/F7 | G39: =G38/G7 | H39: =H38/H7 | I39: =I38/I7 | J39: =J38/J7
A40: Revenue growth (INR) | B40: % | D40: =D7/C7-1 | E40: =E7/D7-1 | F40: =F7/E7-1 | G40: =G7/F7-1 | H40: =H7/G7-1 | I40: =I7/H7-1 | J40: =J7/I7-1
A41: Net profit growth | B41: % | D41: =D24/C24-1 | E41: =E24/D24-1 | F41: =F24/E24-1 | G41: =G24/F24-1 | H41: =H24/G24-1 | I41: =I24/H24-1 | J41: =J24/I24-1
A42: Net profit margin | B42: % | C42: =C24/C7 | D42: =D24/D7 | E42: =E24/E7 | F42: =F24/F7 | G42: =G24/G7 | H42: =H24/H7 | I42: =I24/I7 | J42: =J24/J7
A43: Dividend payout, % of owners profit | B43: % | F43: =Sched!F41/F26 | G43: =Sched!G41/G26 | H43: =Sched!H41/H26 | I43: =Sched!I41/I26 | J43: =Sched!J41/J26
A44: Revenue per average head (Rs lakh) | B44: Rs lakh | E44: =Segments!E52 | F44: =Segments!F87 | G44: =Segments!G87 | H44: =Segments!H87 | I44: =Segments!I87 | J44: =Segments!J87

Sheet BS
A1: Infosys Limited - Consolidated Balance Sheet
A2: Rs crore unless stated | Consolidated Ind AS financials | FY ends 31 March | Blue = hard-coded input / reported data, Black = formula, Green = cross-sheet link
A4: Rs crore | B4: Unit | C4: FY23A | D4: FY24A | E4: FY25A | F4: FY26E | G4: FY27E | H4: FY28E | I4: FY29E | J4: FY30E | L4: Notes / source
A6: CONSOLIDATED BALANCE SHEET (Rs crore, Ind AS)
A7: Non-current assets
A8: Property, plant and equipment | B8: Rs cr | C8: 13346 | D8: 12370 | E8: 11778 | F8: =Sched!F17 | G8: =Sched!G17 | H8: =Sched!H17 | I8: =Sched!I17 | J8: =Sched!J17
A9: Right-of-use assets | B9: Rs cr | C9: 6882 | D9: 6552 | E9: 6311 | F9: =Sched!F22 | G9: =Sched!G22 | H9: =Sched!H22 | I9: =Sched!I22 | J9: =Sched!J22
A10: Capital work-in-progress | B10: Rs cr | C10: 288 | D10: 293 | E10: 814 | F10: =E10 | G10: =F10 | H10: =G10 | I10: =H10 | J10: =I10
A11: Goodwill | B11: Rs cr | C11: 7248 | D11: 7303 | E11: 10106 | F11: =E11 | G11: =F11 | H11: =G11 | I11: =H11 | J11: =I11
A12: Other intangible assets | B12: Rs cr | C12: 1749 | D12: 1397 | E12: 2766 | F12: =Sched!F27 | G12: =Sched!G27 | H12: =Sched!H27 | I12: =Sched!I27 | J12: =Sched!J27
A13: Investments (non-current) | B13: Rs cr | C13: 12569 | D13: 11708 | E13: 11059 | F13: =E13 | G13: =F13 | H13: =G13 | I13: =H13 | J13: =I13
A14: Loans (non-current) | B14: Rs cr | C14: 39 | D14: 34 | E14: 16 | F14: =E14 | G14: =F14 | H14: =G14 | I14: =H14 | J14: =I14
A15: Other financial assets (non-current) | B15: Rs cr | C15: 2798 | D15: 3105 | E15: 3511 | F15: =E15 | G15: =F15 | H15: =G15 | I15: =H15 | J15: =I15
A16: Deferred tax assets (net) | B16: Rs cr | C16: 1245 | D16: 454 | E16: 1108 | F16: =E16 | G16: =F16 | H16: =G16 | I16: =H16 | J16: =I16
A17: Income tax assets (net, non-current) | B17: Rs cr | C17: 6453 | D17: 3045 | E17: 1622 | F17: =E17 | G17: =F17 | H17: =G17 | I17: =H17 | J17: =I17
A18: Other non-current assets | B18: Rs cr | C18: 2318 | D18: 2121 | E18: 2713 | F18: =E18 | G18: =F18 | H18: =G18 | I18: =H18 | J18: =I18
A19: Total non-current assets | B19: Rs cr | C19: =SUM(C8:C18) | D19: =SUM(D8:D18) | E19: =SUM(E8:E18) | F19: =SUM(F8:F18) | G19: =SUM(G8:G18) | H19: =SUM(H8:H18) | I19: =SUM(I8:I18) | J19: =SUM(J8:J18)
A20: Current assets
A21: Investments (current) | B21: Rs cr | C21: 6909 | D21: 12915 | E21: 12482 | F21: =E21 | G21: =F21 | H21: =G21 | I21: =H21 | J21: =I21
A22: Trade receivables | B22: Rs cr | C22: 25424 | D22: 30193 | E22: 31158 | F22: =IS!F7*Inputs!F58 | G22: =IS!G7*Inputs!G58 | H22: =IS!H7*Inputs!H58 | I22: =IS!I7*Inputs!I58 | J22: =IS!J7*Inputs!J58
A23: Cash and cash equivalents | B23: Rs cr | C23: 12173 | D23: 14786 | E23: 24455 | F23: =E23+CF!F45+CF!F46 | G23: =F23+CF!G45+CF!G46 | H23: =G23+CF!H45+CF!H46 | I23: =H23+CF!I45+CF!I46 | J23: =I23+CF!J45+CF!J46
A24: Loans (current) | B24: Rs cr | C24: 289 | D24: 248 | E24: 249 | F24: =E24 | G24: =F24 | H24: =G24 | I24: =H24 | J24: =I24
A25: Other financial assets (current) | B25: Rs cr | C25: 11604 | D25: 12085 | E25: 13840 | F25: =IS!F7*Inputs!F59 | G25: =IS!G7*Inputs!G59 | H25: =IS!H7*Inputs!H59 | I25: =IS!I7*Inputs!I59 | J25: =IS!J7*Inputs!J59
A26: Income tax assets (net, current) | B26: Rs cr | C26: 6 | D26: 6397 | E26: 2975 | F26: =E26 | G26: =F26 | H26: =G26 | I26: =H26 | J26: =I26
A27: Other current assets | B27: Rs cr | C27: 14476 | D27: 12808 | E27: 11940 | F27: =IS!F7*Inputs!F60 | G27: =IS!G7*Inputs!G60 | H27: =IS!H7*Inputs!H60 | I27: =IS!I7*Inputs!I60 | J27: =IS!J7*Inputs!J60
A28: Total current assets | B28: Rs cr | C28: =SUM(C21:C27) | D28: =SUM(D21:D27) | E28: =SUM(E21:E27) | F28: =SUM(F21:F27) | G28: =SUM(G21:G27) | H28: =SUM(H21:H27) | I28: =SUM(I21:I27) | J28: =SUM(J21:J27)
A29: TOTAL ASSETS | B29: Rs cr | C29: =C19+C28 | D29: =D19+D28 | E29: =E19+E28 | F29: =F19+F28 | G29: =G19+G28 | H29: =H19+H28 | I29: =I19+I28 | J29: =J19+J28
A31: Equity
A32: Equity share capital | B32: Rs cr | C32: 2069 | D32: 2071 | E32: 2073 | F32: =E32 | G32: =F32 | H32: =G32 | I32: =H32 | J32: =I32
A33: Other equity | B33: Rs cr | C33: 73338 | D33: 86045 | E33: 93745 | F33: =E33+IS!F26+CF!F15-Sched!F41 | G33: =F33+IS!G26+CF!G15-Sched!G41 | H33: =G33+IS!H26+CF!H15-Sched!H41 | I33: =H33+IS!I26+CF!I15-Sched!I41 | J33: =I33+IS!J26+CF!J15-Sched!J41
A34: Equity attributable to equity holders of the Company | B34: Rs cr | C34: =C32+C33 | D34: =D32+D33 | E34: =E32+E33 | F34: =F32+F33 | G34: =G32+G33 | H34: =H32+H33 | I34: =I32+I33 | J34: =J32+J33
A35: Non-controlling interests | B35: Rs cr | C35: 388 | D35: 345 | E35: 385 | F35: =E35+IS!F25-Sched!F42 | G35: =F35+IS!G25-Sched!G42 | H35: =G35+IS!H25-Sched!H42 | I35: =H35+IS!I25-Sched!I42 | J35: =I35+IS!J25-Sched!J42
A36: Total equity | B36: Rs cr | C36: =C34+C35 | D36: =D34+D35 | E36: =E34+E35 | F36: =F34+F35 | G36: =G34+G35 | H36: =H34+H35 | I36: =I34+I35 | J36: =J34+J35
A37: Non-current liabilities
A38: Lease liabilities (non-current) | B38: Rs cr | C38: 7057 | D38: 6400 | E38: 5772 | F38: =Sched!F38 | G38: =Sched!G38 | H38: =Sched!H38 | I38: =Sched!I38 | J38: =Sched!J38
A39: Other financial liabilities (non-current) | B39: Rs cr | C39: 2058 | D39: 2130 | E39: 2141 | F39: =E39 | G39: =F39 | H39: =G39 | I39: =H39 | J39: =I39
A40: Deferred tax liabilities (net) | B40: Rs cr | C40: 1220 | D40: 1794 | E40: 1722 | F40: =E40 | G40: =F40 | H40: =G40 | I40: =H40 | J40: =I40
A41: Other non-current liabilities | B41: Rs cr | C41: 500 | D41: 235 | E41: 215 | F41: =E41 | G41: =F41 | H41: =G41 | I41: =H41 | J41: =I41
A42: Total non-current liabilities | B42: Rs cr | C42: =SUM(C38:C41) | D42: =SUM(D38:D41) | E42: =SUM(E38:E41) | F42: =SUM(F38:F41) | G42: =SUM(G38:G41) | H42: =SUM(H38:H41) | I42: =SUM(I38:I41) | J42: =SUM(J38:J41)
A43: Current liabilities
A44: Lease liabilities (current) | B44: Rs cr | C44: 1242 | D44: 1959 | E44: 2455 | F44: =Sched!F37 | G44: =Sched!G37 | H44: =Sched!H37 | I44: =Sched!I37 | J44: =Sched!J37
A45: Trade payables | B45: Rs cr | C45: 3865 | D45: 3956 | E45: 4164 | F45: =IS!F7*Inputs!F61 | G45: =IS!G7*Inputs!G61 | H45: =IS!H7*Inputs!H61 | I45: =IS!I7*Inputs!I61 | J45: =IS!J7*Inputs!J61
A46: Other financial liabilities (current) | B46: Rs cr | C46: 18558 | D46: 16959 | E46: 18138 | F46: =IS!F7*Inputs!F62 | G46: =IS!G7*Inputs!G62 | H46: =IS!H7*Inputs!H62 | I46: =IS!I7*Inputs!I62 | J46: =IS!J7*Inputs!J62
A47: Other current liabilities | B47: Rs cr | C47: 10830 | D47: 10539 | E47: 11765 | F47: =IS!F7*Inputs!F63 | G47: =IS!G7*Inputs!G63 | H47: =IS!H7*Inputs!H63 | I47: =IS!I7*Inputs!I63 | J47: =IS!J7*Inputs!J63
A48: Provisions | B48: Rs cr | C48: 1307 | D48: 1796 | E48: 1475 | F48: =IS!F7*Inputs!F64 | G48: =IS!G7*Inputs!G64 | H48: =IS!H7*Inputs!H64 | I48: =IS!I7*Inputs!I64 | J48: =IS!J7*Inputs!J64
A49: Income tax liabilities (net) | B49: Rs cr | C49: 3384 | D49: 3585 | E49: 4853 | F49: =E49 | G49: =F49 | H49: =G49 | I49: =H49 | J49: =I49
A50: Total current liabilities | B50: Rs cr | C50: =SUM(C44:C49) | D50: =SUM(D44:D49) | E50: =SUM(E44:E49) | F50: =SUM(F44:F49) | G50: =SUM(G44:G49) | H50: =SUM(H44:H49) | I50: =SUM(I44:I49) | J50: =SUM(J44:J49)
A51: Total liabilities | B51: Rs cr | C51: =C42+C50 | D51: =D42+D50 | E51: =E42+E50 | F51: =F42+F50 | G51: =G42+G50 | H51: =H42+H50 | I51: =I42+I50 | J51: =J42+J50
A52: TOTAL EQUITY AND LIABILITIES | B52: Rs cr | C52: =C36+C51 | D52: =D36+D51 | E52: =E36+E51 | F52: =F36+F51 | G52: =G36+G51 | H52: =H36+H51 | I52: =I36+I51 | J52: =J36+J51
A53: Balance check (assets - equity & liabilities) | B53: Rs cr | C53: =ROUND(C29-C52,0) | D53: =ROUND(D29-D52,0) | E53: =ROUND(E29-E52,0) | F53: =ROUND(F29-F52,0) | G53: =ROUND(G29-G52,0) | H53: =ROUND(H29-H52,0) | I53: =ROUND(I29-I52,0) | J53: =ROUND(J29-J52,0)
A55: Memo: liquidity, leverage and returns
A56: Cash + current and non-current investments | B56: Rs cr | C56: =C23+C21+C13 | D56: =D23+D21+D13 | E56: =E23+E21+E13 | F56: =F23+F21+F13 | G56: =G23+G21+G13 | H56: =H23+H21+H13 | I56: =I23+I21+I13 | J56: =J23+J21+J13 | L56: Company-defined "cash and investments" Rs47,549 crore at FY25 excludes ~Rs447 crore of equity / preference holdings.
A57: Total lease liabilities | B57: Rs cr | C57: =C38+C44 | D57: =D38+D44 | E57: =E38+E44 | F57: =F38+F44 | G57: =G38+G44 | H57: =H38+H44 | I57: =I38+I44 | J57: =J38+J44
A58: Net debt / (net cash) incl. leases | B58: Rs cr | C58: =C57-C56 | D58: =D57-D56 | E58: =E57-E56 | F58: =F57-F56 | G58: =G57-G56 | H58: =H57-H56 | I58: =I57-I56 | J58: =J57-J56 | L58: Negative = net cash. Infosys has no borrowings.
A59: Return on equity (owners profit / average owners equity) | B59: % | D59: =IS!D26/AVERAGE(C34,D34) | E59: =IS!E26/AVERAGE(D34,E34) | F59: =IS!F26/AVERAGE(E34,F34) | G59: =IS!G26/AVERAGE(F34,G34) | H59: =IS!H26/AVERAGE(G34,H34) | I59: =IS!I26/AVERAGE(H34,I34) | J59: =IS!J26/AVERAGE(I34,J34)
A60: ROCE = operating profit / (equity + leases) | B60: % | C60: =IS!C36/(C36+C57) | D60: =IS!D36/(D36+D57) | E60: =IS!E36/(E36+E57) | F60: =IS!F36/(F36+F57) | G60: =IS!G36/(G36+G57) | H60: =IS!H36/(H36+H57) | I60: =IS!I36/(I36+I57) | J60: =IS!J36/(J36+J57)
A61: Cash & investments as % of total assets | B61: % | C61: =C56/C29 | D61: =D56/D29 | E61: =E56/E29 | F61: =F56/F29 | G61: =G56/G29 | H61: =H56/H29 | I61: =I56/I29 | J61: =J56/J29
A62: Days sales outstanding (trade receivables + unbilled approx.: receivables / revenue x 365) | B62: days | C62: =C22/IS!C7*365 | D62: =D22/IS!D7*365 | E62: =E22/IS!E7*365 | F62: =F22/IS!F7*365 | G62: =G22/IS!G7*365 | H62: =H22/IS!H7*365 | I62: =I22/IS!I7*365 | J62: =J22/IS!J7*365

Sheet CF
A1: Infosys Limited - Consolidated Cash Flow Statement
A2: Rs crore unless stated | Consolidated Ind AS financials | FY ends 31 March | Blue = hard-coded input / reported data, Black = formula, Green = cross-sheet link
A4: Rs crore | B4: Unit | C4: FY23A | D4: FY24A | E4: FY25A | F4: FY26E | G4: FY27E | H4: FY28E | I4: FY29E | J4: FY30E | L4: Notes / source
A6: CONSOLIDATED STATEMENT OF CASH FLOWS (Rs crore, indirect method - Ind AS 7)
A7: Cash flow from operating activities
A8: Profit for the year | B8: Rs cr | C8: 24108 | D8: 26248 | E8: 26750 | F8: =IS!F24 | G8: =IS!G24 | H8: =IS!H24 | I8: =IS!I24 | J8: =IS!J24
A9: Income tax expense | B9: Rs cr | C9: 9214 | D9: 9740 | E9: 10858 | F9: =IS!F23 | G9: =IS!G23 | H9: =IS!H23 | I9: =IS!I23 | J9: =IS!J23
A10: Depreciation and amortization | B10: Rs cr | C10: 4225 | D10: 4678 | E10: 4812 | F10: =IS!F16 | G10: =IS!G16 | H10: =IS!H16 | I10: =IS!I16 | J10: =IS!J16
A11: Interest and dividend income | B11: Rs cr | C11: -1817 | D11: -2067 | E11: -2570 | F11: 0 | G11: 0 | H11: 0 | I11: 0 | J11: 0 | L11: Forecast keeps other income inside operating cash flow.
A12: Finance cost | B12: Rs cr | C12: 284 | D12: 470 | E12: 416 | F12: =IS!F17 | G12: =IS!G17 | H12: =IS!H17 | I12: =IS!I17 | J12: =IS!J17
A13: Impairment loss recognised under expected credit loss model | B13: Rs cr | C13: 283 | D13: 121 | E13: 48 | F13: 0 | G13: 0 | H13: 0 | I13: 0 | J13: 0
A14: Exchange differences on translation of assets and liabilities | B14: Rs cr | C14: 161 | D14: 76 | E14: 79 | F14: 0 | G14: 0 | H14: 0 | I14: 0 | J14: 0
A15: Stock compensation expense | B15: Rs cr | C15: 519 | D15: 652 | E15: 802 | F15: =Inputs!F40*IS!F7 | G15: =Inputs!G40*IS!G7 | H15: =Inputs!H40*IS!H7 | I15: =Inputs!I40*IS!I7 | J15: =Inputs!J40*IS!J7
A16: Interest receivable on income tax refund | B16: Rs cr | C16: 0 | D16: -1934 | E16: -327 | F16: 0 | G16: 0 | H16: 0 | I16: 0 | J16: 0
A17: Provision for post-sales client support | B17: Rs cr | C17: 120 | D17: 75 | E17: -110 | F17: 0 | G17: 0 | H17: 0 | I17: 0 | J17: 0
A18: Other adjustments | B18: Rs cr | C18: 508 | D18: 1464 | E18: 833 | F18: 0 | G18: 0 | H18: 0 | I18: 0 | J18: 0
A19: Trade receivables and unbilled revenue | B19: Rs cr | C19: -7076 | D19: -2667 | E19: -1769 | F19: =-(BS!F22-BS!E22) | G19: =-(BS!G22-BS!F22) | H19: =-(BS!H22-BS!G22) | I19: =-(BS!I22-BS!H22) | J19: =-(BS!J22-BS!I22)
A20: Loans, other financial assets and other assets | B20: Rs cr | C20: -3108 | D20: -1172 | E20: -1024 | F20: =-((BS!F25+BS!F27)-(BS!E25+BS!E27)) | G20: =-((BS!G25+BS!G27)-(BS!F25+BS!F27)) | H20: =-((BS!H25+BS!H27)-(BS!G25+BS!G27)) | I20: =-((BS!I25+BS!I27)-(BS!H25+BS!H27)) | J20: =-((BS!J25+BS!J27)-(BS!I25+BS!I27))
A21: Trade payables | B21: Rs cr | C21: -279 | D21: 91 | E21: 176 | F21: =BS!F45-BS!E45 | G21: =BS!G45-BS!F45 | H21: =BS!H45-BS!G45 | I21: =BS!I45-BS!H45 | J21: =BS!J45-BS!I45
A22: Other financial liabilities, other liabilities and provisions | B22: Rs cr | C22: 4119 | D22: -1334 | E22: 2322 | F22: =(BS!F46+BS!F47+BS!F48)-(BS!E46+BS!E47+BS!E48) | G22: =(BS!G46+BS!G47+BS!G48)-(BS!F46+BS!F47+BS!F48) | H22: =(BS!H46+BS!H47+BS!H48)-(BS!G46+BS!G47+BS!G48) | I22: =(BS!I46+BS!I47+BS!I48)-(BS!H46+BS!H47+BS!H48) | J22: =(BS!J46+BS!J47+BS!J48)-(BS!I46+BS!I47+BS!I48)
A23: Net change in working capital | B23: Rs cr | C23: =SUM(C19:C22) | D23: =SUM(D19:D22) | E23: =SUM(E19:E22) | F23: =SUM(F19:F22) | G23: =SUM(G19:G22) | H23: =SUM(H19:H22) | I23: =SUM(I19:I22) | J23: =SUM(J19:J22)
A24: Cash generated from operations | B24: Rs cr | C24: =SUM(C8:C18)+C23 | D24: =SUM(D8:D18)+D23 | E24: =SUM(E8:E18)+E23 | F24: =SUM(F8:F18)+F23 | G24: =SUM(G8:G18)+G23 | H24: =SUM(H8:H18)+H23 | I24: =SUM(I8:I18)+I23 | J24: =SUM(J8:J18)+J23
A25: Income taxes paid | B25: Rs cr | C25: -8794 | D25: -9231 | E25: -5602 | F25: =-IS!F23 | G25: =-IS!G23 | H25: =-IS!H23 | I25: =-IS!I23 | J25: =-IS!J23 | L25: Historical cash taxes include large refunds in FY25 (Rs5.6k crore paid vs Rs10.9k crore expense).
A26: NET CASH GENERATED BY OPERATING ACTIVITIES | B26: Rs cr | C26: =C24+C25 | D26: =D24+D25 | E26: =E24+E25 | F26: =F24+F25 | G26: =G24+G25 | H26: =H24+H25 | I26: =I24+I25 | J26: =J24+J25
A27: Cash flows from investing activities
A28: Expenditure on property, plant and equipment and intangibles | B28: Rs cr | C28: -2579 | D28: -2201 | E28: -2237 | F28: =-Sched!F7 | G28: =-Sched!G7 | H28: =-Sched!H7 | I28: =-Sched!I7 | J28: =-Sched!J7
A29: Deposits placed with corporation (net of redemptions) | B29: Rs cr | C29: -234 | D29: -137 | E29: -449 | F29: 0 | G29: 0 | H29: 0 | I29: 0 | J29: 0
A30: Interest and dividend received | B30: Rs cr | C30: 1525 | D30: 1768 | E30: 2040 | F30: 0 | G30: 0 | H30: 0 | I30: 0 | J30: 0
A31: Acquisition of business (net of cash) incl. contingent consideration | B31: Rs cr | C31: -970 | D31: -101 | E31: -3155 | F31: 0 | G31: 0 | H31: 0 | I31: 0 | J31: 0 | L31: FY25: in-tech Holding GmbH (Germany) acquisition. No acquisitions forecast.
A32: Other receipts | B32: Rs cr | C32: 71 | D32: 128 | E32: 10 | F32: 0 | G32: 0 | H32: 0 | I32: 0 | J32: 0
A33: Net (purchase) / sale of investments | B33: Rs cr | C33: 978 | D33: -4466 | E33: 1845 | F33: 0 | G33: 0 | H33: 0 | I33: 0 | J33: 0 | L33: Sum of purchases and sales of mutual funds, CDs, CPs, NCDs, G-secs. Held flat: surplus accumulates in cash.
A34: NET CASH USED IN INVESTING ACTIVITIES | B34: Rs cr | C34: =SUM(C28:C33) | D34: =SUM(D28:D33) | E34: =SUM(E28:E33) | F34: =SUM(F28:F33) | G34: =SUM(G28:G33) | H34: =SUM(H28:H33) | I34: =SUM(I28:I33) | J34: =SUM(J28:J33)
A35: Cash flows from financing activities
A36: Payment of lease liabilities (principal + interest) | B36: Rs cr | C36: -1231 | D36: -2024 | E36: -2355 | F36: =-Sched!F35 | G36: =-Sched!G35 | H36: =-Sched!H35 | I36: =-Sched!I35 | J36: =-Sched!J35
A37: Payment of dividends | B37: Rs cr | C37: -13631 | D37: -14692 | E37: -20287 | F37: =-Sched!F41 | G37: =-Sched!G41 | H37: =-Sched!H41 | I37: =-Sched!I41 | J37: =-Sched!J41
A38: Payment of dividend to non-controlling interest | B38: Rs cr | C38: -22 | D38: -39 | E38: -2 | F38: =-Sched!F42 | G38: =-Sched!G42 | H38: =-Sched!H42 | I38: =-Sched!I42 | J38: =-Sched!J42
A39: Buyback of equity shares incl. tax on buyback | B39: Rs cr | C39: -11499 | D39: 0 | E39: 0 | F39: 0 | G39: 0 | H39: 0 | I39: 0 | J39: 0 | L39: FY23: Rs11,499 crore buyback. None forecast (the Sept-2025 buyback post-dates the valuation date).
A40: Shares issued on exercise of employee stock options | B40: Rs cr | C40: 35 | D40: 5 | E40: 6 | F40: 0 | G40: 0 | H40: 0 | I40: 0 | J40: 0
A41: Loan repayment of in-tech Holding GmbH | B41: Rs cr | C41: 0 | D41: 0 | E41: -985 | F41: 0 | G41: 0 | H41: 0 | I41: 0 | J41: 0
A42: Buyback of shares of subsidiary from non-controlling interest | B42: Rs cr | C42: 0 | D42: -18 | E42: 0 | F42: 0 | G42: 0 | H42: 0 | I42: 0 | J42: 0
A43: Other receipts / (payments) | B43: Rs cr | C43: -347 | D43: -736 | E43: -538 | F43: 0 | G43: 0 | H43: 0 | I43: 0 | J43: 0
A44: NET CASH USED IN FINANCING ACTIVITIES | B44: Rs cr | C44: =SUM(C36:C43) | D44: =SUM(D36:D43) | E44: =SUM(E36:E43) | F44: =SUM(F36:F43) | G44: =SUM(G36:G43) | H44: =SUM(H36:H43) | I44: =SUM(I36:I43) | J44: =SUM(J36:J43)
A45: Net increase / (decrease) in cash and cash equivalents | B45: Rs cr | C45: =C26+C34+C44 | D45: =D26+D34+D44 | E45: =E26+E34+E44 | F45: =F26+F34+F44 | G45: =G26+G34+G44 | H45: =H26+H34+H44 | I45: =I26+I34+I44 | J45: =J26+J34+J44
A46: Effect of exchange rate changes on cash and cash equivalents | B46: Rs cr | C46: 138 | D46: -84 | E46: 82 | F46: 0 | G46: 0 | H46: 0 | I46: 0 | J46: 0
A47: Cash and cash equivalents - beginning of year | B47: Rs cr | C47: 17472 | D47: 12173 | E47: 14786 | F47: =BS!E23 | G47: =BS!F23 | H47: =BS!G23 | I47: =BS!H23 | J47: =BS!I23
A48: Cash and cash equivalents - end of year | B48: Rs cr | C48: =C45+C46+C47 | D48: =D45+D46+D47 | E48: =E45+E46+E47 | F48: =F45+F46+F47 | G48: =G45+G46+G47 | H48: =H45+H46+H47 | I48: =I45+I46+I47 | J48: =J45+J46+J47
A49: Difference to balance-sheet cash line | B49: Rs cr | C49: =BS!C23-C48 | D49: =BS!D23-D48 | E49: =BS!E23-E48 | F49: =BS!F23-F48 | G49: =BS!G23-G48 | H49: =BS!H23-H48 | I49: =BS!I23-I48 | J49: =BS!J23-J48
A51: Free cash flow memo (company definition: operating cash flow - capex)
A52: Free cash flow | B52: Rs cr | C52: =C26+C28 | D52: =D26+D28 | E52: =E26+E28 | F52: =F26+F28 | G52: =G26+G28 | H52: =H26+H28 | I52: =I26+I28 | J52: =J26+J28
A53: FCF conversion (FCF / net profit) | B53: % | C53: =C52/IS!C24 | D53: =D52/IS!D24 | E53: =E52/IS!E24 | F53: =F52/IS!F24 | G53: =G52/IS!G24 | H53: =H52/IS!H24 | I53: =I52/IS!I24 | J53: =J52/IS!J24

Sheet Sched
A1: Infosys Limited - Supporting Schedules
A2: Rs crore unless stated | Consolidated Ind AS financials | FY ends 31 March | Blue = hard-coded input / reported data, Black = formula, Green = cross-sheet link
A4: Rs crore | B4: Unit | C4: FY23A | D4: FY24A | E4: FY25A | F4: FY26E | G4: FY27E | H4: FY28E | I4: FY29E | J4: FY30E | L4: Notes / source
A6: A. FIXED-ASSET SCHEDULES (forecast: opening + additions - D&A = closing)
A7: Capex (PPE + intangibles, cash) | B7: Rs cr | C7: =-CF!C28 | D7: =-CF!D28 | E7: =-CF!E28 | F7: =Inputs!F49*IS!F7 | G7: =Inputs!G49*IS!G7 | H7: =Inputs!H49*IS!H7 | I7: =Inputs!I49*IS!I7 | J7: =Inputs!J49*IS!J7
A8: of which PPE | B8: Rs cr | F8: =F7*Inputs!F50 | G8: =G7*Inputs!G50 | H8: =H7*Inputs!H50 | I8: =I7*Inputs!I50 | J8: =J7*Inputs!J50
A9: of which intangibles | B9: Rs cr | F9: =F7-F8 | G9: =G7-G8 | H9: =H7-H8 | I9: =I7-I8 | J9: =J7-J8
A10: Lease additions - ROU (non-cash) | B10: Rs cr | D10: 2190 | E10: 2156 | F10: =Inputs!F51*IS!F7 | G10: =Inputs!G51*IS!G7 | H10: =Inputs!H51*IS!H7 | I10: =Inputs!I51*IS!I7 | J10: =Inputs!J51*IS!J7 | L10: Hist: Note 2.21.
A11: Capex % revenue | B11: % | C11: =C7/IS!C7 | D11: =D7/IS!D7 | E11: =E7/IS!E7 | F11: =F7/IS!F7 | G11: =G7/IS!G7 | H11: =H7/IS!H7 | I11: =I7/IS!I7 | J11: =J7/IS!J7
A13: Property, plant & equipment (CWIP held flat)
A14: Opening net block | B14: Rs cr | F14: =BS!E8 | G14: =BS!F8 | H14: =BS!G8 | I14: =BS!H8 | J14: =BS!I8
A15: + Additions | B15: Rs cr | F15: =F8 | G15: =G8 | H15: =H8 | I15: =I8 | J15: =J8
A16: - Depreciation | B16: Rs cr | F16: =Inputs!F52*F14 | G16: =Inputs!G52*G14 | H16: =Inputs!H52*H14 | I16: =Inputs!I52*I14 | J16: =Inputs!J52*J14
A17: Closing net block | B17: Rs cr | C17: =BS!C8 | D17: =BS!D8 | E17: =BS!E8 | F17: =F14+F15-F16 | G17: =G14+G15-G16 | H17: =H14+H15-H16 | I17: =I14+I15-I16 | J17: =J14+J15-J16
A18: Right-of-use assets
A19: Opening net block | B19: Rs cr | F19: =BS!E9 | G19: =BS!F9 | H19: =BS!G9 | I19: =BS!H9 | J19: =BS!I9
A20: + Additions | B20: Rs cr | F20: =F10 | G20: =G10 | H20: =H10 | I20: =I10 | J20: =J10
A21: - Depreciation | B21: Rs cr | F21: =Inputs!F52*F19 | G21: =Inputs!G52*G19 | H21: =Inputs!H52*H19 | I21: =Inputs!I52*I19 | J21: =Inputs!J52*J19
A22: Closing net block | B22: Rs cr | C22: =BS!C9 | D22: =BS!D9 | E22: =BS!E9 | F22: =F19+F20-F21 | G22: =G19+G20-G21 | H22: =H19+H20-H21 | I22: =I19+I20-I21 | J22: =J19+J20-J21
A23: Other intangible assets (goodwill held flat)
A24: Opening net block | B24: Rs cr | F24: =BS!E12 | G24: =BS!F12 | H24: =BS!G12 | I24: =BS!H12 | J24: =BS!I12
A25: + Additions | B25: Rs cr | F25: =F9 | G25: =G9 | H25: =H9 | I25: =I9 | J25: =J9
A26: - Amortisation | B26: Rs cr | F26: =Inputs!F52*F24 | G26: =Inputs!G52*G24 | H26: =Inputs!H52*H24 | I26: =Inputs!I52*I24 | J26: =Inputs!J52*J24
A27: Closing net block | B27: Rs cr | C27: =BS!C12 | D27: =BS!D12 | E27: =BS!E12 | F27: =F24+F25-F26 | G27: =G24+G25-G26 | H27: =H24+H25-H26 | I27: =I24+I25-I26 | J27: =J24+J25-J26
A28: Total depreciation & amortisation | B28: Rs cr | C28: =IS!C16 | D28: =IS!D16 | E28: =IS!E16 | F28: =F16+F21+F26 | G28: =G16+G21+G26 | H28: =H16+H21+H26 | I28: =I16+I21+I26 | J28: =J16+J21+J26
A29: D&A % revenue | B29: % | C29: =C28/IS!C7 | D29: =D28/IS!D7 | E29: =E28/IS!E7 | F29: =F28/IS!F7 | G29: =G28/IS!G7 | H29: =H28/IS!H7 | I29: =I28/IS!I7 | J29: =J28/IS!J7
A31: B. LEASE SCHEDULE (Ind AS 116) - Infosys has no borrowings
A32: Opening lease liabilities | B32: Rs cr | F32: =BS!E57 | G32: =BS!F57 | H32: =BS!G57 | I32: =BS!H57 | J32: =BS!I57
A33: + New leases (non-cash) | B33: Rs cr | F33: =F10 | G33: =G10 | H33: =H10 | I33: =I10 | J33: =J10
A34: + Interest accrued (= finance cost) | B34: Rs cr | C34: =IS!C17 | D34: =IS!D17 | E34: =IS!E17 | F34: =Inputs!F53*F32 | G34: =Inputs!G53*G32 | H34: =Inputs!H53*H32 | I34: =Inputs!I53*I32 | J34: =Inputs!J53*J32 | L34: Hist = total finance cost.
A35: - Lease payments (principal + interest) | B35: Rs cr | C35: =-CF!C36 | D35: =-CF!D36 | E35: =-CF!E36 | F35: =Inputs!F54*F32 | G35: =Inputs!G54*G32 | H35: =Inputs!H54*H32 | I35: =Inputs!I54*I32 | J35: =Inputs!J54*J32
A36: Closing lease liabilities | B36: Rs cr | C36: =BS!C57 | D36: =BS!D57 | E36: =BS!E57 | F36: =F32+F33+F34-F35 | G36: =G32+G33+G34-G35 | H36: =H32+H33+H34-H35 | I36: =I32+I33+I34-I35 | J36: =J32+J33+J34-J35
A37: current portion | B37: Rs cr | F37: =F36*Inputs!F55 | G37: =G36*Inputs!G55 | H37: =H36*Inputs!H55 | I37: =I36*Inputs!I55 | J37: =J36*Inputs!J55
A38: non-current portion | B38: Rs cr | F38: =F36-F37 | G38: =G36-G37 | H38: =H36-H37 | I38: =I36-I37 | J38: =J36-J37
A40: C. DIVIDENDS
A41: Dividends to owners (DPS x shares) | B41: Rs cr | C41: =-CF!C37 | D41: =-CF!D37 | E41: =-CF!E37 | F41: =Inputs!F46*Inputs!F48 | G41: =Inputs!G46*Inputs!G48 | H41: =Inputs!H46*Inputs!H48 | I41: =Inputs!I46*Inputs!I48 | J41: =Inputs!J46*Inputs!J48
A42: Dividends to non-controlling interests | B42: Rs cr | C42: =-CF!C38 | D42: =-CF!D38 | E42: =-CF!E38 | F42: =Inputs!F47*IS!F25 | G42: =Inputs!G47*IS!G25 | H42: =Inputs!H47*IS!H25 | I42: =Inputs!I47*IS!I25 | J42: =Inputs!J47*IS!J25
A43: Dividends as % of free cash flow | B43: % | C43: =C41/CF!C52 | D43: =D41/CF!D52 | E43: =E41/CF!E52 | F43: =F41/CF!F52 | G43: =G41/CF!G52 | H43: =H41/CF!H52 | I43: =I41/CF!I52 | J43: =J41/CF!J52 | L43: Policy: ~85% of FCF over five years.

Sheet WACC
A1: Infosys Limited - Cost of Capital (WACC)
A2: Rs crore unless stated | Consolidated Ind AS financials | FY ends 31 March | Blue = hard-coded input / reported data, Black = formula, Green = cross-sheet link
B4: Unit | C4: Value | L4: Notes / source
A6: COST OF CAPITAL (as at valuation date 31-Mar-2025)
A7: Risk-free rate (India 10-yr G-sec yield, 31-Mar-2025) | B7: % | C7: 0.0681 | L7: India 10Y government bond yield on 31-Mar-2025 = 6.81% (Trading Economics / Investing.com).
A8: Equity beta (levered) | B8: x | C8: 0.9 | L8: Published Infosys betas vs Nifty: 0.62 (one source) to 0.86-0.94 (3-5 yr windows). 0.90 = judgement; sensitised below.
A9: Equity risk premium | B9: % | C9: 0.055 | L9: Indian practice 5-6% over G-sec.
A10: Size / company-specific premium | B10: % | C10: 0
A11: Cost of equity (CAPM) | B11: % | C11: =C7+C8*C9+C10
A13: Pre-tax cost of debt (lease implicit rate) | B13: % | C13: 0.06 | L13: Only leases (Rs8,227 crore); lease interest ~5-6%.
A14: Tax rate | B14: % | C14: 0.2517
A15: After-tax cost of debt | B15: % | C15: =C13*(1-C14)
A17: Target debt / (debt + equity) | B17: % | C17: 0.01 | L17: Debt-free except leases (~1% of market capitalisation).
A18: Target equity / (debt + equity) | B18: % | C18: =1-C17
A19: WACC | B19: % | C19: =C18*C11+C17*C15
A21: CROSS-CHECK: CURRENT MARKET CAPITAL STRUCTURE
A22: Market capitalisation (Rs crore) | B22: Rs cr | C22: =Inputs!C75
A23: Debt = lease liabilities (Rs crore) | B23: Rs cr | C23: =BS!E57
A24: Implied market D/(D+E) | B24: % | C24: =C23/(C23+C22)
A25: Unlevered beta implied (Hamada) | B25: x | C25: =C8/(1+(1-C14)*C23/C22)

Sheet DCF
A1: Infosys Limited - DCF Valuation
A2: Rs crore unless stated | Consolidated Ind AS financials | FY ends 31 March | Blue = hard-coded input / reported data, Black = formula, Green = cross-sheet link
A4: Rs crore | B4: Unit | C4: FY23A | D4: FY24A | E4: FY25A | F4: FY26E | G4: FY27E | H4: FY28E | I4: FY29E | J4: FY30E | L4: Notes / source
A6: FREE CASH FLOW TO FIRM (derived from the consolidated income statement, balance sheet & cash flow statement)
A7: Revenue | B7: Rs cr | C7: =IS!C7 | D7: =IS!D7 | E7: =IS!E7 | F7: =IS!F7 | G7: =IS!G7 | H7: =IS!H7 | I7: =IS!I7 | J7: =IS!J7
A8: EBITDA (excl. other income) | B8: Rs cr | C8: =IS!C38 | D8: =IS!D38 | E8: =IS!E38 | F8: =IS!F38 | G8: =IS!G38 | H8: =IS!H38 | I8: =IS!I38 | J8: =IS!J38
A9: margin | B9: % | C9: =C8/C7 | D9: =D8/D7 | E9: =E8/E7 | F9: =F8/F7 | G9: =G8/G7 | H9: =H8/H7 | I9: =I8/I7 | J9: =J8/J7
A10: - Depreciation & amortisation | B10: Rs cr | C10: =IS!C16 | D10: =IS!D16 | E10: =IS!E16 | F10: =IS!F16 | G10: =IS!G16 | H10: =IS!H16 | I10: =IS!I16 | J10: =IS!J16
A11: Operating EBIT (company "operating profit") | B11: Rs cr | C11: =C8-C10 | D11: =D8-D10 | E11: =E8-E10 | F11: =F8-F10 | G11: =G8-G10 | H11: =H8-H10 | I11: =I8-I10 | J11: =J8-J10
A12: - Tax on EBIT (unlevered) | B12: Rs cr | F12: =Inputs!F44*F11 | G12: =Inputs!G44*G11 | H12: =Inputs!H44*H11 | I12: =Inputs!I44*I11 | J12: =Inputs!J44*J11
A13: NOPAT | B13: Rs cr | F13: =F11-F12 | G13: =G11-G12 | H13: =H11-H12 | I13: =I11-I12 | J13: =J11-J12
A14: + Depreciation & amortisation | B14: Rs cr | F14: =F10 | G14: =G10 | H14: =H10 | I14: =I10 | J14: =J10
A15: - Capex (PPE + intangibles) | B15: Rs cr | F15: =-Sched!F7 | G15: =-Sched!G7 | H15: =-Sched!H7 | I15: =-Sched!I7 | J15: =-Sched!J7
A16: - Acquisitions (none forecast) | B16: Rs cr | F16: 0 | G16: 0 | H16: 0 | I16: 0 | J16: 0
A17: +/- Change in working capital (from cash flow statement) | B17: Rs cr | F17: =CF!F23 | G17: =CF!G23 | H17: =CF!H23 | I17: =CF!I23 | J17: =CF!J23
A18: +/- Lease adjustment (see Inputs switch) | B18: Rs cr | F18: =IF(Inputs!$C$71=1,-Sched!F10,-Sched!F35+Inputs!F44*Sched!F34) | G18: =IF(Inputs!$C$71=1,-Sched!G10,-Sched!G35+Inputs!G44*Sched!G34) | H18: =IF(Inputs!$C$71=1,-Sched!H10,-Sched!H35+Inputs!H44*Sched!H34) | I18: =IF(Inputs!$C$71=1,-Sched!I10,-Sched!I35+Inputs!I44*Sched!I34) | J18: =IF(Inputs!$C$71=1,-Sched!J10,-Sched!J35+Inputs!J44*Sched!J34) | L18: Switch 1: new ROU additions treated as capex-equivalent. Switch 2: total lease cash cost net of tax shield on interest. SBC is NOT added back (treated as a real cost).
A19: FREE CASH FLOW TO FIRM (FCFF) | B19: Rs cr | F19: =F13+F14+F15+F16+F17+F18 | G19: =G13+G14+G15+G16+G17+G18 | H19: =H13+H14+H15+H16+H17+H18 | I19: =I13+I14+I15+I16+I17+I18 | J19: =J13+J14+J15+J16+J17+J18
A20: growth | B20: % | G20: =G19/F19-1 | H20: =H19/G19-1 | I20: =I19/H19-1 | J20: =J19/I19-1
A21: FCFF % of EBITDA (cash conversion) | B21: % | F21: =F19/F8 | G21: =G19/G8 | H21: =H19/H8 | I21: =I19/I8 | J21: =J19/J8
A23: DISCOUNTING
A24: Year number | B24: # | F24: =1 | G24: =2 | H24: =3 | I24: =4 | J24: =5
A25: Discount period (years from 31-Mar-2025) | B25: yrs | F25: =F24-0.5*Inputs!$C$70 | G25: =G24-0.5*Inputs!$C$70 | H25: =H24-0.5*Inputs!$C$70 | I25: =I24-0.5*Inputs!$C$70 | J25: =J24-0.5*Inputs!$C$70
A26: Discount factor @ WACC | B26: x | F26: =1/(1+WACC!$C$19)^F25 | G26: =1/(1+WACC!$C$19)^G25 | H26: =1/(1+WACC!$C$19)^H25 | I26: =1/(1+WACC!$C$19)^I25 | J26: =1/(1+WACC!$C$19)^J25
A27: PV of FCFF | B27: Rs cr | F27: =F19*F26 | G27: =G19*G26 | H27: =H19*H26 | I27: =I19*I26 | J27: =J19*J26
A29: TERMINAL VALUE & ENTERPRISE VALUE
A30: WACC | B30: % | C30: =WACC!C19
A31: Terminal growth | B31: % | C31: =Inputs!C67
A32: Final forecast year (N) | B32: # | C32: 5
A33: Terminal-year FCFF = (FCFF FY30E - excluded WC inflow) x (1+g) | B33: Rs cr | C33: =(J19-(1-Inputs!C72)*J17)*(1+C31)
A34: Sum of PV of FCFF (FY26E-FY30E) | B34: Rs cr | C34: =SUM(F27:J27)
A36: Method | C36: Gordon growth | D36: Exit multiple
A37: Terminal value (undiscounted) | B37: Rs cr | C37: =C33/(C30-C31) | D37: =Inputs!C68*J8
A38: Discount period for TV (years) | B38: yrs | C38: =C32-0.5*Inputs!C70 | D38: =C32
A39: PV of terminal value | B39: Rs cr | C39: =C37/(1+C30)^C38 | D39: =D37/(1+C30)^D38
A40: ENTERPRISE VALUE | B40: Rs cr | C40: =C34+C39 | D40: =C34+D39
A41: PV of TV as % of EV | B41: % | C41: =C39/C40 | D41: =D39/D40
A42: Implied exit EV/EBITDA (Gordon) | implied perpetual growth (exit multiple) | B42: x / % | C42: =C37/J8 | D42: =(D37*C30-J19)/(D37+J19)
A44: ENTERPRISE VALUE TO EQUITY BRIDGE
A45: Less: borrowings (nil - Infosys has no outstanding borrowings) | B45: Rs cr | C45: 0 | D45: =C45
A46: Less: other debt-like items | B46: Rs cr | C46: =-Inputs!C74 | D46: =C46
A47: Less: lease liabilities (only if lease switch = 1) | B47: Rs cr | C47: =-BS!E57*IF(Inputs!C71=1,1,0) | D47: =C47
A48: Add: cash, current and non-current investments | B48: Rs cr | C48: =BS!E56 | D48: =C48
A49: Add: other (none) | B49: Rs cr | C49: 0 | D49: =C49
A50: Less: non-controlling interests (book x multiple) | B50: Rs cr | C50: =-BS!E35*Inputs!C73 | D50: =C50
A51: EQUITY VALUE (attributable to Infosys shareholders) | B51: Rs cr | C51: =C40+SUM(C45:C50) | D51: =D40+SUM(D45:D50)
A52: Diluted shares (crore) | B52: crore | C52: =415.2 | D52: =C52 | L52: Diluted weighted average shares FY25: 415.2 crore (EPS note).
A53: INTRINSIC VALUE PER SHARE (Rs) | B53: Rs | C53: =C51/C52 | D53: =D51/D52
A55: BLENDED VALUE PER SHARE (Rs) | B55: Rs | C55: =Inputs!C69*C53+(1-Inputs!C69)*D53
A56: Market price at valuation date (Rs) | B56: Rs | C56: =Inputs!C76
A57: Upside / (downside) vs market price | B57: % | C57: =C55/C56-1
A58: Gordon growth only | Exit multiple only | B58: % | C58: =C53/C56-1 | D58: =D53/C56-1
A60: IMPLIED MULTIPLES
A61: EV / FY25 EBITDA | B61: x | C61: =C40/E8 | D61: =D40/E8
A62: EV / FY26E EBITDA | B62: x | C62: =C40/F8 | D62: =D40/F8
A63: Blended price / FY26E EPS | B63: x | C63: =C55/IS!F32
A64: Blended price / FY25 EPS | B64: x | C64: =C55/IS!E32
A65: Market-implied EV at market price (Rs crore) | B65: Rs cr | C65: =C56*C52-SUM(C45:C50)
A66: Market EV / FY25 EBITDA | B66: x | C66: =C65/E8
A67: Market price / FY25 EPS | B67: x | C67: =C56/IS!E32

Sheet Sens
A1: Infosys Limited - Sensitivity Analysis (live formulas, not data tables)
A2: Each cell re-computes enterprise value, bridge and per-share value directly from the DCF cash flows. Highlighted cell = current base inputs.
A4: 1. Value per share (Rs) - Gordon growth method: WACC vs terminal growth
A5: Rows: WACC | Columns: terminal growth
C6: =Inputs!$C$67-0.01 | D6: =Inputs!$C$67-0.005 | E6: =Inputs!$C$67 | F6: =Inputs!$C$67+0.005 | G6: =Inputs!$C$67+0.01
B7: =WACC!$C$19-0.01 | C7: =((DCF!$F$19/(1+$B7)^DCF!$F$25+DCF!$G$19/(1+$B7)^DCF!$G$25+DCF!$H$19/(1+$B7)^DCF!$H$25+DCF!$I$19/(1+$B7)^DCF!$I$25+DCF!$J$19/(1+$B7)^DCF!$J$25+(DCF!$J$19-(1-Inputs!$C$72)*DCF!$J$17)*(1+C$6)/($B7-C$6)/(1+$B7)^(5-0.5*Inputs!$C$70))+SUM(DCF!$C$45:$C$50))/DCF!$C$52 | D7: =((DCF!$F$19/(1+$B7)^DCF!$F$25+DCF!$G$19/(1+$B7)^DCF!$G$25+DCF!$H$19/(1+$B7)^DCF!$H$25+DCF!$I$19/(1+$B7)^DCF!$I$25+DCF!$J$19/(1+$B7)^DCF!$J$25+(DCF!$J$19-(1-Inputs!$C$72)*DCF!$J$17)*(1+D$6)/($B7-D$6)/(1+$B7)^(5-0.5*Inputs!$C$70))+SUM(DCF!$C$45:$C$50))/DCF!$C$52 | E7: =((DCF!$F$19/(1+$B7)^DCF!$F$25+DCF!$G$19/(1+$B7)^DCF!$G$25+DCF!$H$19/(1+$B7)^DCF!$H$25+DCF!$I$19/(1+$B7)^DCF!$I$25+DCF!$J$19/(1+$B7)^DCF!$J$25+(DCF!$J$19-(1-Inputs!$C$72)*DCF!$J$17)*(1+E$6)/($B7-E$6)/(1+$B7)^(5-0.5*Inputs!$C$70))+SUM(DCF!$C$45:$C$50))/DCF!$C$52 | F7: =((DCF!$F$19/(1+$B7)^DCF!$F$25+DCF!$G$19/(1+$B7)^DCF!$G$25+DCF!$H$19/(1+$B7)^DCF!$H$25+DCF!$I$19/(1+$B7)^DCF!$I$25+DCF!$J$19/(1+$B7)^DCF!$J$25+(DCF!$J$19-(1-Inputs!$C$72)*DCF!$J$17)*(1+F$6)/($B7-F$6)/(1+$B7)^(5-0.5*Inputs!$C$70))+SUM(DCF!$C$45:$C$50))/DCF!$C$52 | G7: =((DCF!$F$19/(1+$B7)^DCF!$F$25+DCF!$G$19/(1+$B7)^DCF!$G$25+DCF!$H$19/(1+$B7)^DCF!$H$25+DCF!$I$19/(1+$B7)^DCF!$I$25+DCF!$J$19/(1+$B7)^DCF!$J$25+(DCF!$J$19-(1-Inputs!$C$72)*DCF!$J$17)*(1+G$6)/($B7-G$6)/(1+$B7)^(5-0.5*Inputs!$C$70))+SUM(DCF!$C$45:$C$50))/DCF!$C$52
B8: =WACC!$C$19-0.005 | C8: =((DCF!$F$19/(1+$B8)^DCF!$F$25+DCF!$G$19/(1+$B8)^DCF!$G$25+DCF!$H$19/(1+$B8)^DCF!$H$25+DCF!$I$19/(1+$B8)^DCF!$I$25+DCF!$J$19/(1+$B8)^DCF!$J$25+(DCF!$J$19-(1-Inputs!$C$72)*DCF!$J$17)*(1+C$6)/($B8-C$6)/(1+$B8)^(5-0.5*Inputs!$C$70))+SUM(DCF!$C$45:$C$50))/DCF!$C$52 | D8: =((DCF!$F$19/(1+$B8)^DCF!$F$25+DCF!$G$19/(1+$B8)^DCF!$G$25+DCF!$H$19/(1+$B8)^DCF!$H$25+DCF!$I$19/(1+$B8)^DCF!$I$25+DCF!$J$19/(1+$B8)^DCF!$J$25+(DCF!$J$19-(1-Inputs!$C$72)*DCF!$J$17)*(1+D$6)/($B8-D$6)/(1+$B8)^(5-0.5*Inputs!$C$70))+SUM(DCF!$C$45:$C$50))/DCF!$C$52 | E8: =((DCF!$F$19/(1+$B8)^DCF!$F$25+DCF!$G$19/(1+$B8)^DCF!$G$25+DCF!$H$19/(1+$B8)^DCF!$H$25+DCF!$I$19/(1+$B8)^DCF!$I$25+DCF!$J$19/(1+$B8)^DCF!$J$25+(DCF!$J$19-(1-Inputs!$C$72)*DCF!$J$17)*(1+E$6)/($B8-E$6)/(1+$B8)^(5-0.5*Inputs!$C$70))+SUM(DCF!$C$45:$C$50))/DCF!$C$52 | F8: =((DCF!$F$19/(1+$B8)^DCF!$F$25+DCF!$G$19/(1+$B8)^DCF!$G$25+DCF!$H$19/(1+$B8)^DCF!$H$25+DCF!$I$19/(1+$B8)^DCF!$I$25+DCF!$J$19/(1+$B8)^DCF!$J$25+(DCF!$J$19-(1-Inputs!$C$72)*DCF!$J$17)*(1+F$6)/($B8-F$6)/(1+$B8)^(5-0.5*Inputs!$C$70))+SUM(DCF!$C$45:$C$50))/DCF!$C$52 | G8: =((DCF!$F$19/(1+$B8)^DCF!$F$25+DCF!$G$19/(1+$B8)^DCF!$G$25+DCF!$H$19/(1+$B8)^DCF!$H$25+DCF!$I$19/(1+$B8)^DCF!$I$25+DCF!$J$19/(1+$B8)^DCF!$J$25+(DCF!$J$19-(1-Inputs!$C$72)*DCF!$J$17)*(1+G$6)/($B8-G$6)/(1+$B8)^(5-0.5*Inputs!$C$70))+SUM(DCF!$C$45:$C$50))/DCF!$C$52
B9: =WACC!$C$19 | C9: =((DCF!$F$19/(1+$B9)^DCF!$F$25+DCF!$G$19/(1+$B9)^DCF!$G$25+DCF!$H$19/(1+$B9)^DCF!$H$25+DCF!$I$19/(1+$B9)^DCF!$I$25+DCF!$J$19/(1+$B9)^DCF!$J$25+(DCF!$J$19-(1-Inputs!$C$72)*DCF!$J$17)*(1+C$6)/($B9-C$6)/(1+$B9)^(5-0.5*Inputs!$C$70))+SUM(DCF!$C$45:$C$50))/DCF!$C$52 | D9: =((DCF!$F$19/(1+$B9)^DCF!$F$25+DCF!$G$19/(1+$B9)^DCF!$G$25+DCF!$H$19/(1+$B9)^DCF!$H$25+DCF!$I$19/(1+$B9)^DCF!$I$25+DCF!$J$19/(1+$B9)^DCF!$J$25+(DCF!$J$19-(1-Inputs!$C$72)*DCF!$J$17)*(1+D$6)/($B9-D$6)/(1+$B9)^(5-0.5*Inputs!$C$70))+SUM(DCF!$C$45:$C$50))/DCF!$C$52 | E9: =((DCF!$F$19/(1+$B9)^DCF!$F$25+DCF!$G$19/(1+$B9)^DCF!$G$25+DCF!$H$19/(1+$B9)^DCF!$H$25+DCF!$I$19/(1+$B9)^DCF!$I$25+DCF!$J$19/(1+$B9)^DCF!$J$25+(DCF!$J$19-(1-Inputs!$C$72)*DCF!$J$17)*(1+E$6)/($B9-E$6)/(1+$B9)^(5-0.5*Inputs!$C$70))+SUM(DCF!$C$45:$C$50))/DCF!$C$52 | F9: =((DCF!$F$19/(1+$B9)^DCF!$F$25+DCF!$G$19/(1+$B9)^DCF!$G$25+DCF!$H$19/(1+$B9)^DCF!$H$25+DCF!$I$19/(1+$B9)^DCF!$I$25+DCF!$J$19/(1+$B9)^DCF!$J$25+(DCF!$J$19-(1-Inputs!$C$72)*DCF!$J$17)*(1+F$6)/($B9-F$6)/(1+$B9)^(5-0.5*Inputs!$C$70))+SUM(DCF!$C$45:$C$50))/DCF!$C$52 | G9: =((DCF!$F$19/(1+$B9)^DCF!$F$25+DCF!$G$19/(1+$B9)^DCF!$G$25+DCF!$H$19/(1+$B9)^DCF!$H$25+DCF!$I$19/(1+$B9)^DCF!$I$25+DCF!$J$19/(1+$B9)^DCF!$J$25+(DCF!$J$19-(1-Inputs!$C$72)*DCF!$J$17)*(1+G$6)/($B9-G$6)/(1+$B9)^(5-0.5*Inputs!$C$70))+SUM(DCF!$C$45:$C$50))/DCF!$C$52
B10: =WACC!$C$19+0.005 | C10: =((DCF!$F$19/(1+$B10)^DCF!$F$25+DCF!$G$19/(1+$B10)^DCF!$G$25+DCF!$H$19/(1+$B10)^DCF!$H$25+DCF!$I$19/(1+$B10)^DCF!$I$25+DCF!$J$19/(1+$B10)^DCF!$J$25+(DCF!$J$19-(1-Inputs!$C$72)*DCF!$J$17)*(1+C$6)/($B10-C$6)/(1+$B10)^(5-0.5*Inputs!$C$70))+SUM(DCF!$C$45:$C$50))/DCF!$C$52 | D10: =((DCF!$F$19/(1+$B10)^DCF!$F$25+DCF!$G$19/(1+$B10)^DCF!$G$25+DCF!$H$19/(1+$B10)^DCF!$H$25+DCF!$I$19/(1+$B10)^DCF!$I$25+DCF!$J$19/(1+$B10)^DCF!$J$25+(DCF!$J$19-(1-Inputs!$C$72)*DCF!$J$17)*(1+D$6)/($B10-D$6)/(1+$B10)^(5-0.5*Inputs!$C$70))+SUM(DCF!$C$45:$C$50))/DCF!$C$52 | E10: =((DCF!$F$19/(1+$B10)^DCF!$F$25+DCF!$G$19/(1+$B10)^DCF!$G$25+DCF!$H$19/(1+$B10)^DCF!$H$25+DCF!$I$19/(1+$B10)^DCF!$I$25+DCF!$J$19/(1+$B10)^DCF!$J$25+(DCF!$J$19-(1-Inputs!$C$72)*DCF!$J$17)*(1+E$6)/($B10-E$6)/(1+$B10)^(5-0.5*Inputs!$C$70))+SUM(DCF!$C$45:$C$50))/DCF!$C$52 | F10: =((DCF!$F$19/(1+$B10)^DCF!$F$25+DCF!$G$19/(1+$B10)^DCF!$G$25+DCF!$H$19/(1+$B10)^DCF!$H$25+DCF!$I$19/(1+$B10)^DCF!$I$25+DCF!$J$19/(1+$B10)^DCF!$J$25+(DCF!$J$19-(1-Inputs!$C$72)*DCF!$J$17)*(1+F$6)/($B10-F$6)/(1+$B10)^(5-0.5*Inputs!$C$70))+SUM(DCF!$C$45:$C$50))/DCF!$C$52 | G10: =((DCF!$F$19/(1+$B10)^DCF!$F$25+DCF!$G$19/(1+$B10)^DCF!$G$25+DCF!$H$19/(1+$B10)^DCF!$H$25+DCF!$I$19/(1+$B10)^DCF!$I$25+DCF!$J$19/(1+$B10)^DCF!$J$25+(DCF!$J$19-(1-Inputs!$C$72)*DCF!$J$17)*(1+G$6)/($B10-G$6)/(1+$B10)^(5-0.5*Inputs!$C$70))+SUM(DCF!$C$45:$C$50))/DCF!$C$52
B11: =WACC!$C$19+0.01 | C11: =((DCF!$F$19/(1+$B11)^DCF!$F$25+DCF!$G$19/(1+$B11)^DCF!$G$25+DCF!$H$19/(1+$B11)^DCF!$H$25+DCF!$I$19/(1+$B11)^DCF!$I$25+DCF!$J$19/(1+$B11)^DCF!$J$25+(DCF!$J$19-(1-Inputs!$C$72)*DCF!$J$17)*(1+C$6)/($B11-C$6)/(1+$B11)^(5-0.5*Inputs!$C$70))+SUM(DCF!$C$45:$C$50))/DCF!$C$52 | D11: =((DCF!$F$19/(1+$B11)^DCF!$F$25+DCF!$G$19/(1+$B11)^DCF!$G$25+DCF!$H$19/(1+$B11)^DCF!$H$25+DCF!$I$19/(1+$B11)^DCF!$I$25+DCF!$J$19/(1+$B11)^DCF!$J$25+(DCF!$J$19-(1-Inputs!$C$72)*DCF!$J$17)*(1+D$6)/($B11-D$6)/(1+$B11)^(5-0.5*Inputs!$C$70))+SUM(DCF!$C$45:$C$50))/DCF!$C$52 | E11: =((DCF!$F$19/(1+$B11)^DCF!$F$25+DCF!$G$19/(1+$B11)^DCF!$G$25+DCF!$H$19/(1+$B11)^DCF!$H$25+DCF!$I$19/(1+$B11)^DCF!$I$25+DCF!$J$19/(1+$B11)^DCF!$J$25+(DCF!$J$19-(1-Inputs!$C$72)*DCF!$J$17)*(1+E$6)/($B11-E$6)/(1+$B11)^(5-0.5*Inputs!$C$70))+SUM(DCF!$C$45:$C$50))/DCF!$C$52 | F11: =((DCF!$F$19/(1+$B11)^DCF!$F$25+DCF!$G$19/(1+$B11)^DCF!$G$25+DCF!$H$19/(1+$B11)^DCF!$H$25+DCF!$I$19/(1+$B11)^DCF!$I$25+DCF!$J$19/(1+$B11)^DCF!$J$25+(DCF!$J$19-(1-Inputs!$C$72)*DCF!$J$17)*(1+F$6)/($B11-F$6)/(1+$B11)^(5-0.5*Inputs!$C$70))+SUM(DCF!$C$45:$C$50))/DCF!$C$52 | G11: =((DCF!$F$19/(1+$B11)^DCF!$F$25+DCF!$G$19/(1+$B11)^DCF!$G$25+DCF!$H$19/(1+$B11)^DCF!$H$25+DCF!$I$19/(1+$B11)^DCF!$I$25+DCF!$J$19/(1+$B11)^DCF!$J$25+(DCF!$J$19-(1-Inputs!$C$72)*DCF!$J$17)*(1+G$6)/($B11-G$6)/(1+$B11)^(5-0.5*Inputs!$C$70))+SUM(DCF!$C$45:$C$50))/DCF!$C$52
A14: 2. Value per share (Rs) - exit-multiple method: WACC vs exit EV/EBITDA
A15: Rows: WACC | Columns: exit multiple (x)
C16: =Inputs!$C$68-2 | D16: =Inputs!$C$68-1 | E16: =Inputs!$C$68 | F16: =Inputs!$C$68+1 | G16: =Inputs!$C$68+2
B17: =WACC!$C$19-0.01 | C17: =((DCF!$F$19/(1+$B17)^DCF!$F$25+DCF!$G$19/(1+$B17)^DCF!$G$25+DCF!$H$19/(1+$B17)^DCF!$H$25+DCF!$I$19/(1+$B17)^DCF!$I$25+DCF!$J$19/(1+$B17)^DCF!$J$25+C$16*DCF!$J$8/(1+$B17)^5)+SUM(DCF!$C$45:$C$50))/DCF!$C$52 | D17: =((DCF!$F$19/(1+$B17)^DCF!$F$25+DCF!$G$19/(1+$B17)^DCF!$G$25+DCF!$H$19/(1+$B17)^DCF!$H$25+DCF!$I$19/(1+$B17)^DCF!$I$25+DCF!$J$19/(1+$B17)^DCF!$J$25+D$16*DCF!$J$8/(1+$B17)^5)+SUM(DCF!$C$45:$C$50))/DCF!$C$52 | E17: =((DCF!$F$19/(1+$B17)^DCF!$F$25+DCF!$G$19/(1+$B17)^DCF!$G$25+DCF!$H$19/(1+$B17)^DCF!$H$25+DCF!$I$19/(1+$B17)^DCF!$I$25+DCF!$J$19/(1+$B17)^DCF!$J$25+E$16*DCF!$J$8/(1+$B17)^5)+SUM(DCF!$C$45:$C$50))/DCF!$C$52 | F17: =((DCF!$F$19/(1+$B17)^DCF!$F$25+DCF!$G$19/(1+$B17)^DCF!$G$25+DCF!$H$19/(1+$B17)^DCF!$H$25+DCF!$I$19/(1+$B17)^DCF!$I$25+DCF!$J$19/(1+$B17)^DCF!$J$25+F$16*DCF!$J$8/(1+$B17)^5)+SUM(DCF!$C$45:$C$50))/DCF!$C$52 | G17: =((DCF!$F$19/(1+$B17)^DCF!$F$25+DCF!$G$19/(1+$B17)^DCF!$G$25+DCF!$H$19/(1+$B17)^DCF!$H$25+DCF!$I$19/(1+$B17)^DCF!$I$25+DCF!$J$19/(1+$B17)^DCF!$J$25+G$16*DCF!$J$8/(1+$B17)^5)+SUM(DCF!$C$45:$C$50))/DCF!$C$52
B18: =WACC!$C$19-0.005 | C18: =((DCF!$F$19/(1+$B18)^DCF!$F$25+DCF!$G$19/(1+$B18)^DCF!$G$25+DCF!$H$19/(1+$B18)^DCF!$H$25+DCF!$I$19/(1+$B18)^DCF!$I$25+DCF!$J$19/(1+$B18)^DCF!$J$25+C$16*DCF!$J$8/(1+$B18)^5)+SUM(DCF!$C$45:$C$50))/DCF!$C$52 | D18: =((DCF!$F$19/(1+$B18)^DCF!$F$25+DCF!$G$19/(1+$B18)^DCF!$G$25+DCF!$H$19/(1+$B18)^DCF!$H$25+DCF!$I$19/(1+$B18)^DCF!$I$25+DCF!$J$19/(1+$B18)^DCF!$J$25+D$16*DCF!$J$8/(1+$B18)^5)+SUM(DCF!$C$45:$C$50))/DCF!$C$52 | E18: =((DCF!$F$19/(1+$B18)^DCF!$F$25+DCF!$G$19/(1+$B18)^DCF!$G$25+DCF!$H$19/(1+$B18)^DCF!$H$25+DCF!$I$19/(1+$B18)^DCF!$I$25+DCF!$J$19/(1+$B18)^DCF!$J$25+E$16*DCF!$J$8/(1+$B18)^5)+SUM(DCF!$C$45:$C$50))/DCF!$C$52 | F18: =((DCF!$F$19/(1+$B18)^DCF!$F$25+DCF!$G$19/(1+$B18)^DCF!$G$25+DCF!$H$19/(1+$B18)^DCF!$H$25+DCF!$I$19/(1+$B18)^DCF!$I$25+DCF!$J$19/(1+$B18)^DCF!$J$25+F$16*DCF!$J$8/(1+$B18)^5)+SUM(DCF!$C$45:$C$50))/DCF!$C$52 | G18: =((DCF!$F$19/(1+$B18)^DCF!$F$25+DCF!$G$19/(1+$B18)^DCF!$G$25+DCF!$H$19/(1+$B18)^DCF!$H$25+DCF!$I$19/(1+$B18)^DCF!$I$25+DCF!$J$19/(1+$B18)^DCF!$J$25+G$16*DCF!$J$8/(1+$B18)^5)+SUM(DCF!$C$45:$C$50))/DCF!$C$52
B19: =WACC!$C$19 | C19: =((DCF!$F$19/(1+$B19)^DCF!$F$25+DCF!$G$19/(1+$B19)^DCF!$G$25+DCF!$H$19/(1+$B19)^DCF!$H$25+DCF!$I$19/(1+$B19)^DCF!$I$25+DCF!$J$19/(1+$B19)^DCF!$J$25+C$16*DCF!$J$8/(1+$B19)^5)+SUM(DCF!$C$45:$C$50))/DCF!$C$52 | D19: =((DCF!$F$19/(1+$B19)^DCF!$F$25+DCF!$G$19/(1+$B19)^DCF!$G$25+DCF!$H$19/(1+$B19)^DCF!$H$25+DCF!$I$19/(1+$B19)^DCF!$I$25+DCF!$J$19/(1+$B19)^DCF!$J$25+D$16*DCF!$J$8/(1+$B19)^5)+SUM(DCF!$C$45:$C$50))/DCF!$C$52 | E19: =((DCF!$F$19/(1+$B19)^DCF!$F$25+DCF!$G$19/(1+$B19)^DCF!$G$25+DCF!$H$19/(1+$B19)^DCF!$H$25+DCF!$I$19/(1+$B19)^DCF!$I$25+DCF!$J$19/(1+$B19)^DCF!$J$25+E$16*DCF!$J$8/(1+$B19)^5)+SUM(DCF!$C$45:$C$50))/DCF!$C$52 | F19: =((DCF!$F$19/(1+$B19)^DCF!$F$25+DCF!$G$19/(1+$B19)^DCF!$G$25+DCF!$H$19/(1+$B19)^DCF!$H$25+DCF!$I$19/(1+$B19)^DCF!$I$25+DCF!$J$19/(1+$B19)^DCF!$J$25+F$16*DCF!$J$8/(1+$B19)^5)+SUM(DCF!$C$45:$C$50))/DCF!$C$52 | G19: =((DCF!$F$19/(1+$B19)^DCF!$F$25+DCF!$G$19/(1+$B19)^DCF!$G$25+DCF!$H$19/(1+$B19)^DCF!$H$25+DCF!$I$19/(1+$B19)^DCF!$I$25+DCF!$J$19/(1+$B19)^DCF!$J$25+G$16*DCF!$J$8/(1+$B19)^5)+SUM(DCF!$C$45:$C$50))/DCF!$C$52
B20: =WACC!$C$19+0.005 | C20: =((DCF!$F$19/(1+$B20)^DCF!$F$25+DCF!$G$19/(1+$B20)^DCF!$G$25+DCF!$H$19/(1+$B20)^DCF!$H$25+DCF!$I$19/(1+$B20)^DCF!$I$25+DCF!$J$19/(1+$B20)^DCF!$J$25+C$16*DCF!$J$8/(1+$B20)^5)+SUM(DCF!$C$45:$C$50))/DCF!$C$52 | D20: =((DCF!$F$19/(1+$B20)^DCF!$F$25+DCF!$G$19/(1+$B20)^DCF!$G$25+DCF!$H$19/(1+$B20)^DCF!$H$25+DCF!$I$19/(1+$B20)^DCF!$I$25+DCF!$J$19/(1+$B20)^DCF!$J$25+D$16*DCF!$J$8/(1+$B20)^5)+SUM(DCF!$C$45:$C$50))/DCF!$C$52 | E20: =((DCF!$F$19/(1+$B20)^DCF!$F$25+DCF!$G$19/(1+$B20)^DCF!$G$25+DCF!$H$19/(1+$B20)^DCF!$H$25+DCF!$I$19/(1+$B20)^DCF!$I$25+DCF!$J$19/(1+$B20)^DCF!$J$25+E$16*DCF!$J$8/(1+$B20)^5)+SUM(DCF!$C$45:$C$50))/DCF!$C$52 | F20: =((DCF!$F$19/(1+$B20)^DCF!$F$25+DCF!$G$19/(1+$B20)^DCF!$G$25+DCF!$H$19/(1+$B20)^DCF!$H$25+DCF!$I$19/(1+$B20)^DCF!$I$25+DCF!$J$19/(1+$B20)^DCF!$J$25+F$16*DCF!$J$8/(1+$B20)^5)+SUM(DCF!$C$45:$C$50))/DCF!$C$52 | G20: =((DCF!$F$19/(1+$B20)^DCF!$F$25+DCF!$G$19/(1+$B20)^DCF!$G$25+DCF!$H$19/(1+$B20)^DCF!$H$25+DCF!$I$19/(1+$B20)^DCF!$I$25+DCF!$J$19/(1+$B20)^DCF!$J$25+G$16*DCF!$J$8/(1+$B20)^5)+SUM(DCF!$C$45:$C$50))/DCF!$C$52
B21: =WACC!$C$19+0.01 | C21: =((DCF!$F$19/(1+$B21)^DCF!$F$25+DCF!$G$19/(1+$B21)^DCF!$G$25+DCF!$H$19/(1+$B21)^DCF!$H$25+DCF!$I$19/(1+$B21)^DCF!$I$25+DCF!$J$19/(1+$B21)^DCF!$J$25+C$16*DCF!$J$8/(1+$B21)^5)+SUM(DCF!$C$45:$C$50))/DCF!$C$52 | D21: =((DCF!$F$19/(1+$B21)^DCF!$F$25+DCF!$G$19/(1+$B21)^DCF!$G$25+DCF!$H$19/(1+$B21)^DCF!$H$25+DCF!$I$19/(1+$B21)^DCF!$I$25+DCF!$J$19/(1+$B21)^DCF!$J$25+D$16*DCF!$J$8/(1+$B21)^5)+SUM(DCF!$C$45:$C$50))/DCF!$C$52 | E21: =((DCF!$F$19/(1+$B21)^DCF!$F$25+DCF!$G$19/(1+$B21)^DCF!$G$25+DCF!$H$19/(1+$B21)^DCF!$H$25+DCF!$I$19/(1+$B21)^DCF!$I$25+DCF!$J$19/(1+$B21)^DCF!$J$25+E$16*DCF!$J$8/(1+$B21)^5)+SUM(DCF!$C$45:$C$50))/DCF!$C$52 | F21: =((DCF!$F$19/(1+$B21)^DCF!$F$25+DCF!$G$19/(1+$B21)^DCF!$G$25+DCF!$H$19/(1+$B21)^DCF!$H$25+DCF!$I$19/(1+$B21)^DCF!$I$25+DCF!$J$19/(1+$B21)^DCF!$J$25+F$16*DCF!$J$8/(1+$B21)^5)+SUM(DCF!$C$45:$C$50))/DCF!$C$52 | G21: =((DCF!$F$19/(1+$B21)^DCF!$F$25+DCF!$G$19/(1+$B21)^DCF!$G$25+DCF!$H$19/(1+$B21)^DCF!$H$25+DCF!$I$19/(1+$B21)^DCF!$I$25+DCF!$J$19/(1+$B21)^DCF!$J$25+G$16*DCF!$J$8/(1+$B21)^5)+SUM(DCF!$C$45:$C$50))/DCF!$C$52
A24: 3. Upside / (downside) vs CMP - Gordon growth: WACC vs terminal growth
A25: Rows: WACC | Columns: terminal growth
C26: =Inputs!$C$67-0.01 | D26: =Inputs!$C$67-0.005 | E26: =Inputs!$C$67 | F26: =Inputs!$C$67+0.005 | G26: =Inputs!$C$67+0.01
B27: =WACC!$C$19-0.01 | C27: =((DCF!$F$19/(1+$B27)^DCF!$F$25+DCF!$G$19/(1+$B27)^DCF!$G$25+DCF!$H$19/(1+$B27)^DCF!$H$25+DCF!$I$19/(1+$B27)^DCF!$I$25+DCF!$J$19/(1+$B27)^DCF!$J$25+(DCF!$J$19-(1-Inputs!$C$72)*DCF!$J$17)*(1+C$26)/($B27-C$26)/(1+$B27)^(5-0.5*Inputs!$C$70))+SUM(DCF!$C$45:$C$50))/DCF!$C$52/Inputs!$C$76-1 | D27: =((DCF!$F$19/(1+$B27)^DCF!$F$25+DCF!$G$19/(1+$B27)^DCF!$G$25+DCF!$H$19/(1+$B27)^DCF!$H$25+DCF!$I$19/(1+$B27)^DCF!$I$25+DCF!$J$19/(1+$B27)^DCF!$J$25+(DCF!$J$19-(1-Inputs!$C$72)*DCF!$J$17)*(1+D$26)/($B27-D$26)/(1+$B27)^(5-0.5*Inputs!$C$70))+SUM(DCF!$C$45:$C$50))/DCF!$C$52/Inputs!$C$76-1 | E27: =((DCF!$F$19/(1+$B27)^DCF!$F$25+DCF!$G$19/(1+$B27)^DCF!$G$25+DCF!$H$19/(1+$B27)^DCF!$H$25+DCF!$I$19/(1+$B27)^DCF!$I$25+DCF!$J$19/(1+$B27)^DCF!$J$25+(DCF!$J$19-(1-Inputs!$C$72)*DCF!$J$17)*(1+E$26)/($B27-E$26)/(1+$B27)^(5-0.5*Inputs!$C$70))+SUM(DCF!$C$45:$C$50))/DCF!$C$52/Inputs!$C$76-1 | F27: =((DCF!$F$19/(1+$B27)^DCF!$F$25+DCF!$G$19/(1+$B27)^DCF!$G$25+DCF!$H$19/(1+$B27)^DCF!$H$25+DCF!$I$19/(1+$B27)^DCF!$I$25+DCF!$J$19/(1+$B27)^DCF!$J$25+(DCF!$J$19-(1-Inputs!$C$72)*DCF!$J$17)*(1+F$26)/($B27-F$26)/(1+$B27)^(5-0.5*Inputs!$C$70))+SUM(DCF!$C$45:$C$50))/DCF!$C$52/Inputs!$C$76-1 | G27: =((DCF!$F$19/(1+$B27)^DCF!$F$25+DCF!$G$19/(1+$B27)^DCF!$G$25+DCF!$H$19/(1+$B27)^DCF!$H$25+DCF!$I$19/(1+$B27)^DCF!$I$25+DCF!$J$19/(1+$B27)^DCF!$J$25+(DCF!$J$19-(1-Inputs!$C$72)*DCF!$J$17)*(1+G$26)/($B27-G$26)/(1+$B27)^(5-0.5*Inputs!$C$70))+SUM(DCF!$C$45:$C$50))/DCF!$C$52/Inputs!$C$76-1
B28: =WACC!$C$19-0.005 | C28: =((DCF!$F$19/(1+$B28)^DCF!$F$25+DCF!$G$19/(1+$B28)^DCF!$G$25+DCF!$H$19/(1+$B28)^DCF!$H$25+DCF!$I$19/(1+$B28)^DCF!$I$25+DCF!$J$19/(1+$B28)^DCF!$J$25+(DCF!$J$19-(1-Inputs!$C$72)*DCF!$J$17)*(1+C$26)/($B28-C$26)/(1+$B28)^(5-0.5*Inputs!$C$70))+SUM(DCF!$C$45:$C$50))/DCF!$C$52/Inputs!$C$76-1 | D28: =((DCF!$F$19/(1+$B28)^DCF!$F$25+DCF!$G$19/(1+$B28)^DCF!$G$25+DCF!$H$19/(1+$B28)^DCF!$H$25+DCF!$I$19/(1+$B28)^DCF!$I$25+DCF!$J$19/(1+$B28)^DCF!$J$25+(DCF!$J$19-(1-Inputs!$C$72)*DCF!$J$17)*(1+D$26)/($B28-D$26)/(1+$B28)^(5-0.5*Inputs!$C$70))+SUM(DCF!$C$45:$C$50))/DCF!$C$52/Inputs!$C$76-1 | E28: =((DCF!$F$19/(1+$B28)^DCF!$F$25+DCF!$G$19/(1+$B28)^DCF!$G$25+DCF!$H$19/(1+$B28)^DCF!$H$25+DCF!$I$19/(1+$B28)^DCF!$I$25+DCF!$J$19/(1+$B28)^DCF!$J$25+(DCF!$J$19-(1-Inputs!$C$72)*DCF!$J$17)*(1+E$26)/($B28-E$26)/(1+$B28)^(5-0.5*Inputs!$C$70))+SUM(DCF!$C$45:$C$50))/DCF!$C$52/Inputs!$C$76-1 | F28: =((DCF!$F$19/(1+$B28)^DCF!$F$25+DCF!$G$19/(1+$B28)^DCF!$G$25+DCF!$H$19/(1+$B28)^DCF!$H$25+DCF!$I$19/(1+$B28)^DCF!$I$25+DCF!$J$19/(1+$B28)^DCF!$J$25+(DCF!$J$19-(1-Inputs!$C$72)*DCF!$J$17)*(1+F$26)/($B28-F$26)/(1+$B28)^(5-0.5*Inputs!$C$70))+SUM(DCF!$C$45:$C$50))/DCF!$C$52/Inputs!$C$76-1 | G28: =((DCF!$F$19/(1+$B28)^DCF!$F$25+DCF!$G$19/(1+$B28)^DCF!$G$25+DCF!$H$19/(1+$B28)^DCF!$H$25+DCF!$I$19/(1+$B28)^DCF!$I$25+DCF!$J$19/(1+$B28)^DCF!$J$25+(DCF!$J$19-(1-Inputs!$C$72)*DCF!$J$17)*(1+G$26)/($B28-G$26)/(1+$B28)^(5-0.5*Inputs!$C$70))+SUM(DCF!$C$45:$C$50))/DCF!$C$52/Inputs!$C$76-1
B29: =WACC!$C$19 | C29: =((DCF!$F$19/(1+$B29)^DCF!$F$25+DCF!$G$19/(1+$B29)^DCF!$G$25+DCF!$H$19/(1+$B29)^DCF!$H$25+DCF!$I$19/(1+$B29)^DCF!$I$25+DCF!$J$19/(1+$B29)^DCF!$J$25+(DCF!$J$19-(1-Inputs!$C$72)*DCF!$J$17)*(1+C$26)/($B29-C$26)/(1+$B29)^(5-0.5*Inputs!$C$70))+SUM(DCF!$C$45:$C$50))/DCF!$C$52/Inputs!$C$76-1 | D29: =((DCF!$F$19/(1+$B29)^DCF!$F$25+DCF!$G$19/(1+$B29)^DCF!$G$25+DCF!$H$19/(1+$B29)^DCF!$H$25+DCF!$I$19/(1+$B29)^DCF!$I$25+DCF!$J$19/(1+$B29)^DCF!$J$25+(DCF!$J$19-(1-Inputs!$C$72)*DCF!$J$17)*(1+D$26)/($B29-D$26)/(1+$B29)^(5-0.5*Inputs!$C$70))+SUM(DCF!$C$45:$C$50))/DCF!$C$52/Inputs!$C$76-1 | E29: =((DCF!$F$19/(1+$B29)^DCF!$F$25+DCF!$G$19/(1+$B29)^DCF!$G$25+DCF!$H$19/(1+$B29)^DCF!$H$25+DCF!$I$19/(1+$B29)^DCF!$I$25+DCF!$J$19/(1+$B29)^DCF!$J$25+(DCF!$J$19-(1-Inputs!$C$72)*DCF!$J$17)*(1+E$26)/($B29-E$26)/(1+$B29)^(5-0.5*Inputs!$C$70))+SUM(DCF!$C$45:$C$50))/DCF!$C$52/Inputs!$C$76-1 | F29: =((DCF!$F$19/(1+$B29)^DCF!$F$25+DCF!$G$19/(1+$B29)^DCF!$G$25+DCF!$H$19/(1+$B29)^DCF!$H$25+DCF!$I$19/(1+$B29)^DCF!$I$25+DCF!$J$19/(1+$B29)^DCF!$J$25+(DCF!$J$19-(1-Inputs!$C$72)*DCF!$J$17)*(1+F$26)/($B29-F$26)/(1+$B29)^(5-0.5*Inputs!$C$70))+SUM(DCF!$C$45:$C$50))/DCF!$C$52/Inputs!$C$76-1 | G29: =((DCF!$F$19/(1+$B29)^DCF!$F$25+DCF!$G$19/(1+$B29)^DCF!$G$25+DCF!$H$19/(1+$B29)^DCF!$H$25+DCF!$I$19/(1+$B29)^DCF!$I$25+DCF!$J$19/(1+$B29)^DCF!$J$25+(DCF!$J$19-(1-Inputs!$C$72)*DCF!$J$17)*(1+G$26)/($B29-G$26)/(1+$B29)^(5-0.5*Inputs!$C$70))+SUM(DCF!$C$45:$C$50))/DCF!$C$52/Inputs!$C$76-1
B30: =WACC!$C$19+0.005 | C30: =((DCF!$F$19/(1+$B30)^DCF!$F$25+DCF!$G$19/(1+$B30)^DCF!$G$25+DCF!$H$19/(1+$B30)^DCF!$H$25+DCF!$I$19/(1+$B30)^DCF!$I$25+DCF!$J$19/(1+$B30)^DCF!$J$25+(DCF!$J$19-(1-Inputs!$C$72)*DCF!$J$17)*(1+C$26)/($B30-C$26)/(1+$B30)^(5-0.5*Inputs!$C$70))+SUM(DCF!$C$45:$C$50))/DCF!$C$52/Inputs!$C$76-1 | D30: =((DCF!$F$19/(1+$B30)^DCF!$F$25+DCF!$G$19/(1+$B30)^DCF!$G$25+DCF!$H$19/(1+$B30)^DCF!$H$25+DCF!$I$19/(1+$B30)^DCF!$I$25+DCF!$J$19/(1+$B30)^DCF!$J$25+(DCF!$J$19-(1-Inputs!$C$72)*DCF!$J$17)*(1+D$26)/($B30-D$26)/(1+$B30)^(5-0.5*Inputs!$C$70))+SUM(DCF!$C$45:$C$50))/DCF!$C$52/Inputs!$C$76-1 | E30: =((DCF!$F$19/(1+$B30)^DCF!$F$25+DCF!$G$19/(1+$B30)^DCF!$G$25+DCF!$H$19/(1+$B30)^DCF!$H$25+DCF!$I$19/(1+$B30)^DCF!$I$25+DCF!$J$19/(1+$B30)^DCF!$J$25+(DCF!$J$19-(1-Inputs!$C$72)*DCF!$J$17)*(1+E$26)/($B30-E$26)/(1+$B30)^(5-0.5*Inputs!$C$70))+SUM(DCF!$C$45:$C$50))/DCF!$C$52/Inputs!$C$76-1 | F30: =((DCF!$F$19/(1+$B30)^DCF!$F$25+DCF!$G$19/(1+$B30)^DCF!$G$25+DCF!$H$19/(1+$B30)^DCF!$H$25+DCF!$I$19/(1+$B30)^DCF!$I$25+DCF!$J$19/(1+$B30)^DCF!$J$25+(DCF!$J$19-(1-Inputs!$C$72)*DCF!$J$17)*(1+F$26)/($B30-F$26)/(1+$B30)^(5-0.5*Inputs!$C$70))+SUM(DCF!$C$45:$C$50))/DCF!$C$52/Inputs!$C$76-1 | G30: =((DCF!$F$19/(1+$B30)^DCF!$F$25+DCF!$G$19/(1+$B30)^DCF!$G$25+DCF!$H$19/(1+$B30)^DCF!$H$25+DCF!$I$19/(1+$B30)^DCF!$I$25+DCF!$J$19/(1+$B30)^DCF!$J$25+(DCF!$J$19-(1-Inputs!$C$72)*DCF!$J$17)*(1+G$26)/($B30-G$26)/(1+$B30)^(5-0.5*Inputs!$C$70))+SUM(DCF!$C$45:$C$50))/DCF!$C$52/Inputs!$C$76-1
B31: =WACC!$C$19+0.01 | C31: =((DCF!$F$19/(1+$B31)^DCF!$F$25+DCF!$G$19/(1+$B31)^DCF!$G$25+DCF!$H$19/(1+$B31)^DCF!$H$25+DCF!$I$19/(1+$B31)^DCF!$I$25+DCF!$J$19/(1+$B31)^DCF!$J$25+(DCF!$J$19-(1-Inputs!$C$72)*DCF!$J$17)*(1+C$26)/($B31-C$26)/(1+$B31)^(5-0.5*Inputs!$C$70))+SUM(DCF!$C$45:$C$50))/DCF!$C$52/Inputs!$C$76-1 | D31: =((DCF!$F$19/(1+$B31)^DCF!$F$25+DCF!$G$19/(1+$B31)^DCF!$G$25+DCF!$H$19/(1+$B31)^DCF!$H$25+DCF!$I$19/(1+$B31)^DCF!$I$25+DCF!$J$19/(1+$B31)^DCF!$J$25+(DCF!$J$19-(1-Inputs!$C$72)*DCF!$J$17)*(1+D$26)/($B31-D$26)/(1+$B31)^(5-0.5*Inputs!$C$70))+SUM(DCF!$C$45:$C$50))/DCF!$C$52/Inputs!$C$76-1 | E31: =((DCF!$F$19/(1+$B31)^DCF!$F$25+DCF!$G$19/(1+$B31)^DCF!$G$25+DCF!$H$19/(1+$B31)^DCF!$H$25+DCF!$I$19/(1+$B31)^DCF!$I$25+DCF!$J$19/(1+$B31)^DCF!$J$25+(DCF!$J$19-(1-Inputs!$C$72)*DCF!$J$17)*(1+E$26)/($B31-E$26)/(1+$B31)^(5-0.5*Inputs!$C$70))+SUM(DCF!$C$45:$C$50))/DCF!$C$52/Inputs!$C$76-1 | F31: =((DCF!$F$19/(1+$B31)^DCF!$F$25+DCF!$G$19/(1+$B31)^DCF!$G$25+DCF!$H$19/(1+$B31)^DCF!$H$25+DCF!$I$19/(1+$B31)^DCF!$I$25+DCF!$J$19/(1+$B31)^DCF!$J$25+(DCF!$J$19-(1-Inputs!$C$72)*DCF!$J$17)*(1+F$26)/($B31-F$26)/(1+$B31)^(5-0.5*Inputs!$C$70))+SUM(DCF!$C$45:$C$50))/DCF!$C$52/Inputs!$C$76-1 | G31: =((DCF!$F$19/(1+$B31)^DCF!$F$25+DCF!$G$19/(1+$B31)^DCF!$G$25+DCF!$H$19/(1+$B31)^DCF!$H$25+DCF!$I$19/(1+$B31)^DCF!$I$25+DCF!$J$19/(1+$B31)^DCF!$J$25+(DCF!$J$19-(1-Inputs!$C$72)*DCF!$J$17)*(1+G$26)/($B31-G$26)/(1+$B31)^(5-0.5*Inputs!$C$70))+SUM(DCF!$C$45:$C$50))/DCF!$C$52/Inputs!$C$76-1
A34: 4. Value per share (Rs) - Gordon growth: equity beta vs equity risk premium (WACC recomputed)
A35: Rows: equity beta | Columns: ERP. Cost of debt and capital structure held at WACC-sheet values.
C36: 0.045 | D36: 0.05 | E36: 0.055 | F36: 0.06 | G36: 0.065
B37: 0.7 | C37: =((DCF!$F$19/(1+(WACC!$C$18*(WACC!$C$7+$B37*C$36+WACC!$C$10)+WACC!$C$17*WACC!$C$15))^DCF!$F$25+DCF!$G$19/(1+(WACC!$C$18*(WACC!$C$7+$B37*C$36+WACC!$C$10)+WACC!$C$17*WACC!$C$15))^DCF!$G$25+DCF!$H$19/(1+(WACC!$C$18*(WACC!$C$7+$B37*C$36+WACC!$C$10)+WACC!$C$17*WACC!$C$15))^DCF!$H$25+DCF!$I$19/(1+(WACC!$C$18*(WACC!$C$7+$B37*C$36+WACC!$C$10)+WACC!$C$17*WACC!$C$15))^DCF!$I$25+DCF!$J$19/(1+(WACC!$C$18*(WACC!$C$7+$B37*C$36+WACC!$C$10)+WACC!$C$17*WACC!$C$15))^DCF!$J$25+(DCF!$J$19-(1-Inputs!$C$72)*DCF!$J$17)*(1+Inputs!$C$67)/((WACC!$C$18*(WACC!$C$7+$B37*C$36+WACC!$C$10)+WACC!$C$17*WACC!$C$15)-Inputs!$C$67)/(1+(WACC!$C$18*(WACC!$C$7+$B37*C$36+WACC!$C$10)+WACC!$C$17*WACC!$C$15))^(5-0.5*Inputs!$C$70))+SUM(DCF!$C$45:$C$50))/DCF!$C$52 | D37: =((DCF!$F$19/(1+(WACC!$C$18*(WACC!$C$7+$B37*D$36+WACC!$C$10)+WACC!$C$17*WACC!$C$15))^DCF!$F$25+DCF!$G$19/(1+(WACC!$C$18*(WACC!$C$7+$B37*D$36+WACC!$C$10)+WACC!$C$17*WACC!$C$15))^DCF!$G$25+DCF!$H$19/(1+(WACC!$C$18*(WACC!$C$7+$B37*D$36+WACC!$C$10)+WACC!$C$17*WACC!$C$15))^DCF!$H$25+DCF!$I$19/(1+(WACC!$C$18*(WACC!$C$7+$B37*D$36+WACC!$C$10)+WACC!$C$17*WACC!$C$15))^DCF!$I$25+DCF!$J$19/(1+(WACC!$C$18*(WACC!$C$7+$B37*D$36+WACC!$C$10)+WACC!$C$17*WACC!$C$15))^DCF!$J$25+(DCF!$J$19-(1-Inputs!$C$72)*DCF!$J$17)*(1+Inputs!$C$67)/((WACC!$C$18*(WACC!$C$7+$B37*D$36+WACC!$C$10)+WACC!$C$17*WACC!$C$15)-Inputs!$C$67)/(1+(WACC!$C$18*(WACC!$C$7+$B37*D$36+WACC!$C$10)+WACC!$C$17*WACC!$C$15))^(5-0.5*Inputs!$C$70))+SUM(DCF!$C$45:$C$50))/DCF!$C$52 | E37: =((DCF!$F$19/(1+(WACC!$C$18*(WACC!$C$7+$B37*E$36+WACC!$C$10)+WACC!$C$17*WACC!$C$15))^DCF!$F$25+DCF!$G$19/(1+(WACC!$C$18*(WACC!$C$7+$B37*E$36+WACC!$C$10)+WACC!$C$17*WACC!$C$15))^DCF!$G$25+DCF!$H$19/(1+(WACC!$C$18*(WACC!$C$7+$B37*E$36+WACC!$C$10)+WACC!$C$17*WACC!$C$15))^DCF!$H$25+DCF!$I$19/(1+(WACC!$C$18*(WACC!$C$7+$B37*E$36+WACC!$C$10)+WACC!$C$17*WACC!$C$15))^DCF!$I$25+DCF!$J$19/(1+(WACC!$C$18*(WACC!$C$7+$B37*E$36+WACC!$C$10)+WACC!$C$17*WACC!$C$15))^DCF!$J$25+(DCF!$J$19-(1-Inputs!$C$72)*DCF!$J$17)*(1+Inputs!$C$67)/((WACC!$C$18*(WACC!$C$7+$B37*E$36+WACC!$C$10)+WACC!$C$17*WACC!$C$15)-Inputs!$C$67)/(1+(WACC!$C$18*(WACC!$C$7+$B37*E$36+WACC!$C$10)+WACC!$C$17*WACC!$C$15))^(5-0.5*Inputs!$C$70))+SUM(DCF!$C$45:$C$50))/DCF!$C$52 | F37: =((DCF!$F$19/(1+(WACC!$C$18*(WACC!$C$7+$B37*F$36+WACC!$C$10)+WACC!$C$17*WACC!$C$15))^DCF!$F$25+DCF!$G$19/(1+(WACC!$C$18*(WACC!$C$7+$B37*F$36+WACC!$C$10)+WACC!$C$17*WACC!$C$15))^DCF!$G$25+DCF!$H$19/(1+(WACC!$C$18*(WACC!$C$7+$B37*F$36+WACC!$C$10)+WACC!$C$17*WACC!$C$15))^DCF!$H$25+DCF!$I$19/(1+(WACC!$C$18*(WACC!$C$7+$B37*F$36+WACC!$C$10)+WACC!$C$17*WACC!$C$15))^DCF!$I$25+DCF!$J$19/(1+(WACC!$C$18*(WACC!$C$7+$B37*F$36+WACC!$C$10)+WACC!$C$17*WACC!$C$15))^DCF!$J$25+(DCF!$J$19-(1-Inputs!$C$72)*DCF!$J$17)*(1+Inputs!$C$67)/((WACC!$C$18*(WACC!$C$7+$B37*F$36+WACC!$C$10)+WACC!$C$17*WACC!$C$15)-Inputs!$C$67)/(1+(WACC!$C$18*(WACC!$C$7+$B37*F$36+WACC!$C$10)+WACC!$C$17*WACC!$C$15))^(5-0.5*Inputs!$C$70))+SUM(DCF!$C$45:$C$50))/DCF!$C$52 | G37: =((DCF!$F$19/(1+(WACC!$C$18*(WACC!$C$7+$B37*G$36+WACC!$C$10)+WACC!$C$17*WACC!$C$15))^DCF!$F$25+DCF!$G$19/(1+(WACC!$C$18*(WACC!$C$7+$B37*G$36+WACC!$C$10)+WACC!$C$17*WACC!$C$15))^DCF!$G$25+DCF!$H$19/(1+(WACC!$C$18*(WACC!$C$7+$B37*G$36+WACC!$C$10)+WACC!$C$17*WACC!$C$15))^DCF!$H$25+DCF!$I$19/(1+(WACC!$C$18*(WACC!$C$7+$B37*G$36+WACC!$C$10)+WACC!$C$17*WACC!$C$15))^DCF!$I$25+DCF!$J$19/(1+(WACC!$C$18*(WACC!$C$7+$B37*G$36+WACC!$C$10)+WACC!$C$17*WACC!$C$15))^DCF!$J$25+(DCF!$J$19-(1-Inputs!$C$72)*DCF!$J$17)*(1+Inputs!$C$67)/((WACC!$C$18*(WACC!$C$7+$B37*G$36+WACC!$C$10)+WACC!$C$17*WACC!$C$15)-Inputs!$C$67)/(1+(WACC!$C$18*(WACC!$C$7+$B37*G$36+WACC!$C$10)+WACC!$C$17*WACC!$C$15))^(5-0.5*Inputs!$C$70))+SUM(DCF!$C$45:$C$50))/DCF!$C$52
B38: 0.8 | C38: =((DCF!$F$19/(1+(WACC!$C$18*(WACC!$C$7+$B38*C$36+WACC!$C$10)+WACC!$C$17*WACC!$C$15))^DCF!$F$25+DCF!$G$19/(1+(WACC!$C$18*(WACC!$C$7+$B38*C$36+WACC!$C$10)+WACC!$C$17*WACC!$C$15))^DCF!$G$25+DCF!$H$19/(1+(WACC!$C$18*(WACC!$C$7+$B38*C$36+WACC!$C$10)+WACC!$C$17*WACC!$C$15))^DCF!$H$25+DCF!$I$19/(1+(WACC!$C$18*(WACC!$C$7+$B38*C$36+WACC!$C$10)+WACC!$C$17*WACC!$C$15))^DCF!$I$25+DCF!$J$19/(1+(WACC!$C$18*(WACC!$C$7+$B38*C$36+WACC!$C$10)+WACC!$C$17*WACC!$C$15))^DCF!$J$25+(DCF!$J$19-(1-Inputs!$C$72)*DCF!$J$17)*(1+Inputs!$C$67)/((WACC!$C$18*(WACC!$C$7+$B38*C$36+WACC!$C$10)+WACC!$C$17*WACC!$C$15)-Inputs!$C$67)/(1+(WACC!$C$18*(WACC!$C$7+$B38*C$36+WACC!$C$10)+WACC!$C$17*WACC!$C$15))^(5-0.5*Inputs!$C$70))+SUM(DCF!$C$45:$C$50))/DCF!$C$52 | D38: =((DCF!$F$19/(1+(WACC!$C$18*(WACC!$C$7+$B38*D$36+WACC!$C$10)+WACC!$C$17*WACC!$C$15))^DCF!$F$25+DCF!$G$19/(1+(WACC!$C$18*(WACC!$C$7+$B38*D$36+WACC!$C$10)+WACC!$C$17*WACC!$C$15))^DCF!$G$25+DCF!$H$19/(1+(WACC!$C$18*(WACC!$C$7+$B38*D$36+WACC!$C$10)+WACC!$C$17*WACC!$C$15))^DCF!$H$25+DCF!$I$19/(1+(WACC!$C$18*(WACC!$C$7+$B38*D$36+WACC!$C$10)+WACC!$C$17*WACC!$C$15))^DCF!$I$25+DCF!$J$19/(1+(WACC!$C$18*(WACC!$C$7+$B38*D$36+WACC!$C$10)+WACC!$C$17*WACC!$C$15))^DCF!$J$25+(DCF!$J$19-(1-Inputs!$C$72)*DCF!$J$17)*(1+Inputs!$C$67)/((WACC!$C$18*(WACC!$C$7+$B38*D$36+WACC!$C$10)+WACC!$C$17*WACC!$C$15)-Inputs!$C$67)/(1+(WACC!$C$18*(WACC!$C$7+$B38*D$36+WACC!$C$10)+WACC!$C$17*WACC!$C$15))^(5-0.5*Inputs!$C$70))+SUM(DCF!$C$45:$C$50))/DCF!$C$52 | E38: =((DCF!$F$19/(1+(WACC!$C$18*(WACC!$C$7+$B38*E$36+WACC!$C$10)+WACC!$C$17*WACC!$C$15))^DCF!$F$25+DCF!$G$19/(1+(WACC!$C$18*(WACC!$C$7+$B38*E$36+WACC!$C$10)+WACC!$C$17*WACC!$C$15))^DCF!$G$25+DCF!$H$19/(1+(WACC!$C$18*(WACC!$C$7+$B38*E$36+WACC!$C$10)+WACC!$C$17*WACC!$C$15))^DCF!$H$25+DCF!$I$19/(1+(WACC!$C$18*(WACC!$C$7+$B38*E$36+WACC!$C$10)+WACC!$C$17*WACC!$C$15))^DCF!$I$25+DCF!$J$19/(1+(WACC!$C$18*(WACC!$C$7+$B38*E$36+WACC!$C$10)+WACC!$C$17*WACC!$C$15))^DCF!$J$25+(DCF!$J$19-(1-Inputs!$C$72)*DCF!$J$17)*(1+Inputs!$C$67)/((WACC!$C$18*(WACC!$C$7+$B38*E$36+WACC!$C$10)+WACC!$C$17*WACC!$C$15)-Inputs!$C$67)/(1+(WACC!$C$18*(WACC!$C$7+$B38*E$36+WACC!$C$10)+WACC!$C$17*WACC!$C$15))^(5-0.5*Inputs!$C$70))+SUM(DCF!$C$45:$C$50))/DCF!$C$52 | F38: =((DCF!$F$19/(1+(WACC!$C$18*(WACC!$C$7+$B38*F$36+WACC!$C$10)+WACC!$C$17*WACC!$C$15))^DCF!$F$25+DCF!$G$19/(1+(WACC!$C$18*(WACC!$C$7+$B38*F$36+WACC!$C$10)+WACC!$C$17*WACC!$C$15))^DCF!$G$25+DCF!$H$19/(1+(WACC!$C$18*(WACC!$C$7+$B38*F$36+WACC!$C$10)+WACC!$C$17*WACC!$C$15))^DCF!$H$25+DCF!$I$19/(1+(WACC!$C$18*(WACC!$C$7+$B38*F$36+WACC!$C$10)+WACC!$C$17*WACC!$C$15))^DCF!$I$25+DCF!$J$19/(1+(WACC!$C$18*(WACC!$C$7+$B38*F$36+WACC!$C$10)+WACC!$C$17*WACC!$C$15))^DCF!$J$25+(DCF!$J$19-(1-Inputs!$C$72)*DCF!$J$17)*(1+Inputs!$C$67)/((WACC!$C$18*(WACC!$C$7+$B38*F$36+WACC!$C$10)+WACC!$C$17*WACC!$C$15)-Inputs!$C$67)/(1+(WACC!$C$18*(WACC!$C$7+$B38*F$36+WACC!$C$10)+WACC!$C$17*WACC!$C$15))^(5-0.5*Inputs!$C$70))+SUM(DCF!$C$45:$C$50))/DCF!$C$52 | G38: =((DCF!$F$19/(1+(WACC!$C$18*(WACC!$C$7+$B38*G$36+WACC!$C$10)+WACC!$C$17*WACC!$C$15))^DCF!$F$25+DCF!$G$19/(1+(WACC!$C$18*(WACC!$C$7+$B38*G$36+WACC!$C$10)+WACC!$C$17*WACC!$C$15))^DCF!$G$25+DCF!$H$19/(1+(WACC!$C$18*(WACC!$C$7+$B38*G$36+WACC!$C$10)+WACC!$C$17*WACC!$C$15))^DCF!$H$25+DCF!$I$19/(1+(WACC!$C$18*(WACC!$C$7+$B38*G$36+WACC!$C$10)+WACC!$C$17*WACC!$C$15))^DCF!$I$25+DCF!$J$19/(1+(WACC!$C$18*(WACC!$C$7+$B38*G$36+WACC!$C$10)+WACC!$C$17*WACC!$C$15))^DCF!$J$25+(DCF!$J$19-(1-Inputs!$C$72)*DCF!$J$17)*(1+Inputs!$C$67)/((WACC!$C$18*(WACC!$C$7+$B38*G$36+WACC!$C$10)+WACC!$C$17*WACC!$C$15)-Inputs!$C$67)/(1+(WACC!$C$18*(WACC!$C$7+$B38*G$36+WACC!$C$10)+WACC!$C$17*WACC!$C$15))^(5-0.5*Inputs!$C$70))+SUM(DCF!$C$45:$C$50))/DCF!$C$52
B39: 0.9 | C39: =((DCF!$F$19/(1+(WACC!$C$18*(WACC!$C$7+$B39*C$36+WACC!$C$10)+WACC!$C$17*WACC!$C$15))^DCF!$F$25+DCF!$G$19/(1+(WACC!$C$18*(WACC!$C$7+$B39*C$36+WACC!$C$10)+WACC!$C$17*WACC!$C$15))^DCF!$G$25+DCF!$H$19/(1+(WACC!$C$18*(WACC!$C$7+$B39*C$36+WACC!$C$10)+WACC!$C$17*WACC!$C$15))^DCF!$H$25+DCF!$I$19/(1+(WACC!$C$18*(WACC!$C$7+$B39*C$36+WACC!$C$10)+WACC!$C$17*WACC!$C$15))^DCF!$I$25+DCF!$J$19/(1+(WACC!$C$18*(WACC!$C$7+$B39*C$36+WACC!$C$10)+WACC!$C$17*WACC!$C$15))^DCF!$J$25+(DCF!$J$19-(1-Inputs!$C$72)*DCF!$J$17)*(1+Inputs!$C$67)/((WACC!$C$18*(WACC!$C$7+$B39*C$36+WACC!$C$10)+WACC!$C$17*WACC!$C$15)-Inputs!$C$67)/(1+(WACC!$C$18*(WACC!$C$7+$B39*C$36+WACC!$C$10)+WACC!$C$17*WACC!$C$15))^(5-0.5*Inputs!$C$70))+SUM(DCF!$C$45:$C$50))/DCF!$C$52 | D39: =((DCF!$F$19/(1+(WACC!$C$18*(WACC!$C$7+$B39*D$36+WACC!$C$10)+WACC!$C$17*WACC!$C$15))^DCF!$F$25+DCF!$G$19/(1+(WACC!$C$18*(WACC!$C$7+$B39*D$36+WACC!$C$10)+WACC!$C$17*WACC!$C$15))^DCF!$G$25+DCF!$H$19/(1+(WACC!$C$18*(WACC!$C$7+$B39*D$36+WACC!$C$10)+WACC!$C$17*WACC!$C$15))^DCF!$H$25+DCF!$I$19/(1+(WACC!$C$18*(WACC!$C$7+$B39*D$36+WACC!$C$10)+WACC!$C$17*WACC!$C$15))^DCF!$I$25+DCF!$J$19/(1+(WACC!$C$18*(WACC!$C$7+$B39*D$36+WACC!$C$10)+WACC!$C$17*WACC!$C$15))^DCF!$J$25+(DCF!$J$19-(1-Inputs!$C$72)*DCF!$J$17)*(1+Inputs!$C$67)/((WACC!$C$18*(WACC!$C$7+$B39*D$36+WACC!$C$10)+WACC!$C$17*WACC!$C$15)-Inputs!$C$67)/(1+(WACC!$C$18*(WACC!$C$7+$B39*D$36+WACC!$C$10)+WACC!$C$17*WACC!$C$15))^(5-0.5*Inputs!$C$70))+SUM(DCF!$C$45:$C$50))/DCF!$C$52 | E39: =((DCF!$F$19/(1+(WACC!$C$18*(WACC!$C$7+$B39*E$36+WACC!$C$10)+WACC!$C$17*WACC!$C$15))^DCF!$F$25+DCF!$G$19/(1+(WACC!$C$18*(WACC!$C$7+$B39*E$36+WACC!$C$10)+WACC!$C$17*WACC!$C$15))^DCF!$G$25+DCF!$H$19/(1+(WACC!$C$18*(WACC!$C$7+$B39*E$36+WACC!$C$10)+WACC!$C$17*WACC!$C$15))^DCF!$H$25+DCF!$I$19/(1+(WACC!$C$18*(WACC!$C$7+$B39*E$36+WACC!$C$10)+WACC!$C$17*WACC!$C$15))^DCF!$I$25+DCF!$J$19/(1+(WACC!$C$18*(WACC!$C$7+$B39*E$36+WACC!$C$10)+WACC!$C$17*WACC!$C$15))^DCF!$J$25+(DCF!$J$19-(1-Inputs!$C$72)*DCF!$J$17)*(1+Inputs!$C$67)/((WACC!$C$18*(WACC!$C$7+$B39*E$36+WACC!$C$10)+WACC!$C$17*WACC!$C$15)-Inputs!$C$67)/(1+(WACC!$C$18*(WACC!$C$7+$B39*E$36+WACC!$C$10)+WACC!$C$17*WACC!$C$15))^(5-0.5*Inputs!$C$70))+SUM(DCF!$C$45:$C$50))/DCF!$C$52 | F39: =((DCF!$F$19/(1+(WACC!$C$18*(WACC!$C$7+$B39*F$36+WACC!$C$10)+WACC!$C$17*WACC!$C$15))^DCF!$F$25+DCF!$G$19/(1+(WACC!$C$18*(WACC!$C$7+$B39*F$36+WACC!$C$10)+WACC!$C$17*WACC!$C$15))^DCF!$G$25+DCF!$H$19/(1+(WACC!$C$18*(WACC!$C$7+$B39*F$36+WACC!$C$10)+WACC!$C$17*WACC!$C$15))^DCF!$H$25+DCF!$I$19/(1+(WACC!$C$18*(WACC!$C$7+$B39*F$36+WACC!$C$10)+WACC!$C$17*WACC!$C$15))^DCF!$I$25+DCF!$J$19/(1+(WACC!$C$18*(WACC!$C$7+$B39*F$36+WACC!$C$10)+WACC!$C$17*WACC!$C$15))^DCF!$J$25+(DCF!$J$19-(1-Inputs!$C$72)*DCF!$J$17)*(1+Inputs!$C$67)/((WACC!$C$18*(WACC!$C$7+$B39*F$36+WACC!$C$10)+WACC!$C$17*WACC!$C$15)-Inputs!$C$67)/(1+(WACC!$C$18*(WACC!$C$7+$B39*F$36+WACC!$C$10)+WACC!$C$17*WACC!$C$15))^(5-0.5*Inputs!$C$70))+SUM(DCF!$C$45:$C$50))/DCF!$C$52 | G39: =((DCF!$F$19/(1+(WACC!$C$18*(WACC!$C$7+$B39*G$36+WACC!$C$10)+WACC!$C$17*WACC!$C$15))^DCF!$F$25+DCF!$G$19/(1+(WACC!$C$18*(WACC!$C$7+$B39*G$36+WACC!$C$10)+WACC!$C$17*WACC!$C$15))^DCF!$G$25+DCF!$H$19/(1+(WACC!$C$18*(WACC!$C$7+$B39*G$36+WACC!$C$10)+WACC!$C$17*WACC!$C$15))^DCF!$H$25+DCF!$I$19/(1+(WACC!$C$18*(WACC!$C$7+$B39*G$36+WACC!$C$10)+WACC!$C$17*WACC!$C$15))^DCF!$I$25+DCF!$J$19/(1+(WACC!$C$18*(WACC!$C$7+$B39*G$36+WACC!$C$10)+WACC!$C$17*WACC!$C$15))^DCF!$J$25+(DCF!$J$19-(1-Inputs!$C$72)*DCF!$J$17)*(1+Inputs!$C$67)/((WACC!$C$18*(WACC!$C$7+$B39*G$36+WACC!$C$10)+WACC!$C$17*WACC!$C$15)-Inputs!$C$67)/(1+(WACC!$C$18*(WACC!$C$7+$B39*G$36+WACC!$C$10)+WACC!$C$17*WACC!$C$15))^(5-0.5*Inputs!$C$70))+SUM(DCF!$C$45:$C$50))/DCF!$C$52
B40: 1 | C40: =((DCF!$F$19/(1+(WACC!$C$18*(WACC!$C$7+$B40*C$36+WACC!$C$10)+WACC!$C$17*WACC!$C$15))^DCF!$F$25+DCF!$G$19/(1+(WACC!$C$18*(WACC!$C$7+$B40*C$36+WACC!$C$10)+WACC!$C$17*WACC!$C$15))^DCF!$G$25+DCF!$H$19/(1+(WACC!$C$18*(WACC!$C$7+$B40*C$36+WACC!$C$10)+WACC!$C$17*WACC!$C$15))^DCF!$H$25+DCF!$I$19/(1+(WACC!$C$18*(WACC!$C$7+$B40*C$36+WACC!$C$10)+WACC!$C$17*WACC!$C$15))^DCF!$I$25+DCF!$J$19/(1+(WACC!$C$18*(WACC!$C$7+$B40*C$36+WACC!$C$10)+WACC!$C$17*WACC!$C$15))^DCF!$J$25+(DCF!$J$19-(1-Inputs!$C$72)*DCF!$J$17)*(1+Inputs!$C$67)/((WACC!$C$18*(WACC!$C$7+$B40*C$36+WACC!$C$10)+WACC!$C$17*WACC!$C$15)-Inputs!$C$67)/(1+(WACC!$C$18*(WACC!$C$7+$B40*C$36+WACC!$C$10)+WACC!$C$17*WACC!$C$15))^(5-0.5*Inputs!$C$70))+SUM(DCF!$C$45:$C$50))/DCF!$C$52 | D40: =((DCF!$F$19/(1+(WACC!$C$18*(WACC!$C$7+$B40*D$36+WACC!$C$10)+WACC!$C$17*WACC!$C$15))^DCF!$F$25+DCF!$G$19/(1+(WACC!$C$18*(WACC!$C$7+$B40*D$36+WACC!$C$10)+WACC!$C$17*WACC!$C$15))^DCF!$G$25+DCF!$H$19/(1+(WACC!$C$18*(WACC!$C$7+$B40*D$36+WACC!$C$10)+WACC!$C$17*WACC!$C$15))^DCF!$H$25+DCF!$I$19/(1+(WACC!$C$18*(WACC!$C$7+$B40*D$36+WACC!$C$10)+WACC!$C$17*WACC!$C$15))^DCF!$I$25+DCF!$J$19/(1+(WACC!$C$18*(WACC!$C$7+$B40*D$36+WACC!$C$10)+WACC!$C$17*WACC!$C$15))^DCF!$J$25+(DCF!$J$19-(1-Inputs!$C$72)*DCF!$J$17)*(1+Inputs!$C$67)/((WACC!$C$18*(WACC!$C$7+$B40*D$36+WACC!$C$10)+WACC!$C$17*WACC!$C$15)-Inputs!$C$67)/(1+(WACC!$C$18*(WACC!$C$7+$B40*D$36+WACC!$C$10)+WACC!$C$17*WACC!$C$15))^(5-0.5*Inputs!$C$70))+SUM(DCF!$C$45:$C$50))/DCF!$C$52 | E40: =((DCF!$F$19/(1+(WACC!$C$18*(WACC!$C$7+$B40*E$36+WACC!$C$10)+WACC!$C$17*WACC!$C$15))^DCF!$F$25+DCF!$G$19/(1+(WACC!$C$18*(WACC!$C$7+$B40*E$36+WACC!$C$10)+WACC!$C$17*WACC!$C$15))^DCF!$G$25+DCF!$H$19/(1+(WACC!$C$18*(WACC!$C$7+$B40*E$36+WACC!$C$10)+WACC!$C$17*WACC!$C$15))^DCF!$H$25+DCF!$I$19/(1+(WACC!$C$18*(WACC!$C$7+$B40*E$36+WACC!$C$10)+WACC!$C$17*WACC!$C$15))^DCF!$I$25+DCF!$J$19/(1+(WACC!$C$18*(WACC!$C$7+$B40*E$36+WACC!$C$10)+WACC!$C$17*WACC!$C$15))^DCF!$J$25+(DCF!$J$19-(1-Inputs!$C$72)*DCF!$J$17)*(1+Inputs!$C$67)/((WACC!$C$18*(WACC!$C$7+$B40*E$36+WACC!$C$10)+WACC!$C$17*WACC!$C$15)-Inputs!$C$67)/(1+(WACC!$C$18*(WACC!$C$7+$B40*E$36+WACC!$C$10)+WACC!$C$17*WACC!$C$15))^(5-0.5*Inputs!$C$70))+SUM(DCF!$C$45:$C$50))/DCF!$C$52 | F40: =((DCF!$F$19/(1+(WACC!$C$18*(WACC!$C$7+$B40*F$36+WACC!$C$10)+WACC!$C$17*WACC!$C$15))^DCF!$F$25+DCF!$G$19/(1+(WACC!$C$18*(WACC!$C$7+$B40*F$36+WACC!$C$10)+WACC!$C$17*WACC!$C$15))^DCF!$G$25+DCF!$H$19/(1+(WACC!$C$18*(WACC!$C$7+$B40*F$36+WACC!$C$10)+WACC!$C$17*WACC!$C$15))^DCF!$H$25+DCF!$I$19/(1+(WACC!$C$18*(WACC!$C$7+$B40*F$36+WACC!$C$10)+WACC!$C$17*WACC!$C$15))^DCF!$I$25+DCF!$J$19/(1+(WACC!$C$18*(WACC!$C$7+$B40*F$36+WACC!$C$10)+WACC!$C$17*WACC!$C$15))^DCF!$J$25+(DCF!$J$19-(1-Inputs!$C$72)*DCF!$J$17)*(1+Inputs!$C$67)/((WACC!$C$18*(WACC!$C$7+$B40*F$36+WACC!$C$10)+WACC!$C$17*WACC!$C$15)-Inputs!$C$67)/(1+(WACC!$C$18*(WACC!$C$7+$B40*F$36+WACC!$C$10)+WACC!$C$17*WACC!$C$15))^(5-0.5*Inputs!$C$70))+SUM(DCF!$C$45:$C$50))/DCF!$C$52 | G40: =((DCF!$F$19/(1+(WACC!$C$18*(WACC!$C$7+$B40*G$36+WACC!$C$10)+WACC!$C$17*WACC!$C$15))^DCF!$F$25+DCF!$G$19/(1+(WACC!$C$18*(WACC!$C$7+$B40*G$36+WACC!$C$10)+WACC!$C$17*WACC!$C$15))^DCF!$G$25+DCF!$H$19/(1+(WACC!$C$18*(WACC!$C$7+$B40*G$36+WACC!$C$10)+WACC!$C$17*WACC!$C$15))^DCF!$H$25+DCF!$I$19/(1+(WACC!$C$18*(WACC!$C$7+$B40*G$36+WACC!$C$10)+WACC!$C$17*WACC!$C$15))^DCF!$I$25+DCF!$J$19/(1+(WACC!$C$18*(WACC!$C$7+$B40*G$36+WACC!$C$10)+WACC!$C$17*WACC!$C$15))^DCF!$J$25+(DCF!$J$19-(1-Inputs!$C$72)*DCF!$J$17)*(1+Inputs!$C$67)/((WACC!$C$18*(WACC!$C$7+$B40*G$36+WACC!$C$10)+WACC!$C$17*WACC!$C$15)-Inputs!$C$67)/(1+(WACC!$C$18*(WACC!$C$7+$B40*G$36+WACC!$C$10)+WACC!$C$17*WACC!$C$15))^(5-0.5*Inputs!$C$70))+SUM(DCF!$C$45:$C$50))/DCF!$C$52
B41: 1.1 | C41: =((DCF!$F$19/(1+(WACC!$C$18*(WACC!$C$7+$B41*C$36+WACC!$C$10)+WACC!$C$17*WACC!$C$15))^DCF!$F$25+DCF!$G$19/(1+(WACC!$C$18*(WACC!$C$7+$B41*C$36+WACC!$C$10)+WACC!$C$17*WACC!$C$15))^DCF!$G$25+DCF!$H$19/(1+(WACC!$C$18*(WACC!$C$7+$B41*C$36+WACC!$C$10)+WACC!$C$17*WACC!$C$15))^DCF!$H$25+DCF!$I$19/(1+(WACC!$C$18*(WACC!$C$7+$B41*C$36+WACC!$C$10)+WACC!$C$17*WACC!$C$15))^DCF!$I$25+DCF!$J$19/(1+(WACC!$C$18*(WACC!$C$7+$B41*C$36+WACC!$C$10)+WACC!$C$17*WACC!$C$15))^DCF!$J$25+(DCF!$J$19-(1-Inputs!$C$72)*DCF!$J$17)*(1+Inputs!$C$67)/((WACC!$C$18*(WACC!$C$7+$B41*C$36+WACC!$C$10)+WACC!$C$17*WACC!$C$15)-Inputs!$C$67)/(1+(WACC!$C$18*(WACC!$C$7+$B41*C$36+WACC!$C$10)+WACC!$C$17*WACC!$C$15))^(5-0.5*Inputs!$C$70))+SUM(DCF!$C$45:$C$50))/DCF!$C$52 | D41: =((DCF!$F$19/(1+(WACC!$C$18*(WACC!$C$7+$B41*D$36+WACC!$C$10)+WACC!$C$17*WACC!$C$15))^DCF!$F$25+DCF!$G$19/(1+(WACC!$C$18*(WACC!$C$7+$B41*D$36+WACC!$C$10)+WACC!$C$17*WACC!$C$15))^DCF!$G$25+DCF!$H$19/(1+(WACC!$C$18*(WACC!$C$7+$B41*D$36+WACC!$C$10)+WACC!$C$17*WACC!$C$15))^DCF!$H$25+DCF!$I$19/(1+(WACC!$C$18*(WACC!$C$7+$B41*D$36+WACC!$C$10)+WACC!$C$17*WACC!$C$15))^DCF!$I$25+DCF!$J$19/(1+(WACC!$C$18*(WACC!$C$7+$B41*D$36+WACC!$C$10)+WACC!$C$17*WACC!$C$15))^DCF!$J$25+(DCF!$J$19-(1-Inputs!$C$72)*DCF!$J$17)*(1+Inputs!$C$67)/((WACC!$C$18*(WACC!$C$7+$B41*D$36+WACC!$C$10)+WACC!$C$17*WACC!$C$15)-Inputs!$C$67)/(1+(WACC!$C$18*(WACC!$C$7+$B41*D$36+WACC!$C$10)+WACC!$C$17*WACC!$C$15))^(5-0.5*Inputs!$C$70))+SUM(DCF!$C$45:$C$50))/DCF!$C$52 | E41: =((DCF!$F$19/(1+(WACC!$C$18*(WACC!$C$7+$B41*E$36+WACC!$C$10)+WACC!$C$17*WACC!$C$15))^DCF!$F$25+DCF!$G$19/(1+(WACC!$C$18*(WACC!$C$7+$B41*E$36+WACC!$C$10)+WACC!$C$17*WACC!$C$15))^DCF!$G$25+DCF!$H$19/(1+(WACC!$C$18*(WACC!$C$7+$B41*E$36+WACC!$C$10)+WACC!$C$17*WACC!$C$15))^DCF!$H$25+DCF!$I$19/(1+(WACC!$C$18*(WACC!$C$7+$B41*E$36+WACC!$C$10)+WACC!$C$17*WACC!$C$15))^DCF!$I$25+DCF!$J$19/(1+(WACC!$C$18*(WACC!$C$7+$B41*E$36+WACC!$C$10)+WACC!$C$17*WACC!$C$15))^DCF!$J$25+(DCF!$J$19-(1-Inputs!$C$72)*DCF!$J$17)*(1+Inputs!$C$67)/((WACC!$C$18*(WACC!$C$7+$B41*E$36+WACC!$C$10)+WACC!$C$17*WACC!$C$15)-Inputs!$C$67)/(1+(WACC!$C$18*(WACC!$C$7+$B41*E$36+WACC!$C$10)+WACC!$C$17*WACC!$C$15))^(5-0.5*Inputs!$C$70))+SUM(DCF!$C$45:$C$50))/DCF!$C$52 | F41: =((DCF!$F$19/(1+(WACC!$C$18*(WACC!$C$7+$B41*F$36+WACC!$C$10)+WACC!$C$17*WACC!$C$15))^DCF!$F$25+DCF!$G$19/(1+(WACC!$C$18*(WACC!$C$7+$B41*F$36+WACC!$C$10)+WACC!$C$17*WACC!$C$15))^DCF!$G$25+DCF!$H$19/(1+(WACC!$C$18*(WACC!$C$7+$B41*F$36+WACC!$C$10)+WACC!$C$17*WACC!$C$15))^DCF!$H$25+DCF!$I$19/(1+(WACC!$C$18*(WACC!$C$7+$B41*F$36+WACC!$C$10)+WACC!$C$17*WACC!$C$15))^DCF!$I$25+DCF!$J$19/(1+(WACC!$C$18*(WACC!$C$7+$B41*F$36+WACC!$C$10)+WACC!$C$17*WACC!$C$15))^DCF!$J$25+(DCF!$J$19-(1-Inputs!$C$72)*DCF!$J$17)*(1+Inputs!$C$67)/((WACC!$C$18*(WACC!$C$7+$B41*F$36+WACC!$C$10)+WACC!$C$17*WACC!$C$15)-Inputs!$C$67)/(1+(WACC!$C$18*(WACC!$C$7+$B41*F$36+WACC!$C$10)+WACC!$C$17*WACC!$C$15))^(5-0.5*Inputs!$C$70))+SUM(DCF!$C$45:$C$50))/DCF!$C$52 | G41: =((DCF!$F$19/(1+(WACC!$C$18*(WACC!$C$7+$B41*G$36+WACC!$C$10)+WACC!$C$17*WACC!$C$15))^DCF!$F$25+DCF!$G$19/(1+(WACC!$C$18*(WACC!$C$7+$B41*G$36+WACC!$C$10)+WACC!$C$17*WACC!$C$15))^DCF!$G$25+DCF!$H$19/(1+(WACC!$C$18*(WACC!$C$7+$B41*G$36+WACC!$C$10)+WACC!$C$17*WACC!$C$15))^DCF!$H$25+DCF!$I$19/(1+(WACC!$C$18*(WACC!$C$7+$B41*G$36+WACC!$C$10)+WACC!$C$17*WACC!$C$15))^DCF!$I$25+DCF!$J$19/(1+(WACC!$C$18*(WACC!$C$7+$B41*G$36+WACC!$C$10)+WACC!$C$17*WACC!$C$15))^DCF!$J$25+(DCF!$J$19-(1-Inputs!$C$72)*DCF!$J$17)*(1+Inputs!$C$67)/((WACC!$C$18*(WACC!$C$7+$B41*G$36+WACC!$C$10)+WACC!$C$17*WACC!$C$15)-Inputs!$C$67)/(1+(WACC!$C$18*(WACC!$C$7+$B41*G$36+WACC!$C$10)+WACC!$C$17*WACC!$C$15))^(5-0.5*Inputs!$C$70))+SUM(DCF!$C$45:$C$50))/DCF!$C$52
A43: 5. Upside / (downside) vs market price - exit-multiple method: WACC vs exit EV/EBITDA
A44: Rows: WACC | Columns: exit multiple (x).
C45: =Inputs!$C$68-2 | D45: =Inputs!$C$68-1 | E45: =Inputs!$C$68 | F45: =Inputs!$C$68+1 | G45: =Inputs!$C$68+2
B46: =WACC!$C$19-0.01 | C46: =((DCF!$F$19/(1+$B46)^DCF!$F$25+DCF!$G$19/(1+$B46)^DCF!$G$25+DCF!$H$19/(1+$B46)^DCF!$H$25+DCF!$I$19/(1+$B46)^DCF!$I$25+DCF!$J$19/(1+$B46)^DCF!$J$25+C$45*DCF!$J$8/(1+$B46)^5)+SUM(DCF!$C$45:$C$50))/DCF!$C$52/Inputs!$C$76-1 | D46: =((DCF!$F$19/(1+$B46)^DCF!$F$25+DCF!$G$19/(1+$B46)^DCF!$G$25+DCF!$H$19/(1+$B46)^DCF!$H$25+DCF!$I$19/(1+$B46)^DCF!$I$25+DCF!$J$19/(1+$B46)^DCF!$J$25+D$45*DCF!$J$8/(1+$B46)^5)+SUM(DCF!$C$45:$C$50))/DCF!$C$52/Inputs!$C$76-1 | E46: =((DCF!$F$19/(1+$B46)^DCF!$F$25+DCF!$G$19/(1+$B46)^DCF!$G$25+DCF!$H$19/(1+$B46)^DCF!$H$25+DCF!$I$19/(1+$B46)^DCF!$I$25+DCF!$J$19/(1+$B46)^DCF!$J$25+E$45*DCF!$J$8/(1+$B46)^5)+SUM(DCF!$C$45:$C$50))/DCF!$C$52/Inputs!$C$76-1 | F46: =((DCF!$F$19/(1+$B46)^DCF!$F$25+DCF!$G$19/(1+$B46)^DCF!$G$25+DCF!$H$19/(1+$B46)^DCF!$H$25+DCF!$I$19/(1+$B46)^DCF!$I$25+DCF!$J$19/(1+$B46)^DCF!$J$25+F$45*DCF!$J$8/(1+$B46)^5)+SUM(DCF!$C$45:$C$50))/DCF!$C$52/Inputs!$C$76-1 | G46: =((DCF!$F$19/(1+$B46)^DCF!$F$25+DCF!$G$19/(1+$B46)^DCF!$G$25+DCF!$H$19/(1+$B46)^DCF!$H$25+DCF!$I$19/(1+$B46)^DCF!$I$25+DCF!$J$19/(1+$B46)^DCF!$J$25+G$45*DCF!$J$8/(1+$B46)^5)+SUM(DCF!$C$45:$C$50))/DCF!$C$52/Inputs!$C$76-1
B47: =WACC!$C$19-0.005 | C47: =((DCF!$F$19/(1+$B47)^DCF!$F$25+DCF!$G$19/(1+$B47)^DCF!$G$25+DCF!$H$19/(1+$B47)^DCF!$H$25+DCF!$I$19/(1+$B47)^DCF!$I$25+DCF!$J$19/(1+$B47)^DCF!$J$25+C$45*DCF!$J$8/(1+$B47)^5)+SUM(DCF!$C$45:$C$50))/DCF!$C$52/Inputs!$C$76-1 | D47: =((DCF!$F$19/(1+$B47)^DCF!$F$25+DCF!$G$19/(1+$B47)^DCF!$G$25+DCF!$H$19/(1+$B47)^DCF!$H$25+DCF!$I$19/(1+$B47)^DCF!$I$25+DCF!$J$19/(1+$B47)^DCF!$J$25+D$45*DCF!$J$8/(1+$B47)^5)+SUM(DCF!$C$45:$C$50))/DCF!$C$52/Inputs!$C$76-1 | E47: =((DCF!$F$19/(1+$B47)^DCF!$F$25+DCF!$G$19/(1+$B47)^DCF!$G$25+DCF!$H$19/(1+$B47)^DCF!$H$25+DCF!$I$19/(1+$B47)^DCF!$I$25+DCF!$J$19/(1+$B47)^DCF!$J$25+E$45*DCF!$J$8/(1+$B47)^5)+SUM(DCF!$C$45:$C$50))/DCF!$C$52/Inputs!$C$76-1 | F47: =((DCF!$F$19/(1+$B47)^DCF!$F$25+DCF!$G$19/(1+$B47)^DCF!$G$25+DCF!$H$19/(1+$B47)^DCF!$H$25+DCF!$I$19/(1+$B47)^DCF!$I$25+DCF!$J$19/(1+$B47)^DCF!$J$25+F$45*DCF!$J$8/(1+$B47)^5)+SUM(DCF!$C$45:$C$50))/DCF!$C$52/Inputs!$C$76-1 | G47: =((DCF!$F$19/(1+$B47)^DCF!$F$25+DCF!$G$19/(1+$B47)^DCF!$G$25+DCF!$H$19/(1+$B47)^DCF!$H$25+DCF!$I$19/(1+$B47)^DCF!$I$25+DCF!$J$19/(1+$B47)^DCF!$J$25+G$45*DCF!$J$8/(1+$B47)^5)+SUM(DCF!$C$45:$C$50))/DCF!$C$52/Inputs!$C$76-1
B48: =WACC!$C$19 | C48: =((DCF!$F$19/(1+$B48)^DCF!$F$25+DCF!$G$19/(1+$B48)^DCF!$G$25+DCF!$H$19/(1+$B48)^DCF!$H$25+DCF!$I$19/(1+$B48)^DCF!$I$25+DCF!$J$19/(1+$B48)^DCF!$J$25+C$45*DCF!$J$8/(1+$B48)^5)+SUM(DCF!$C$45:$C$50))/DCF!$C$52/Inputs!$C$76-1 | D48: =((DCF!$F$19/(1+$B48)^DCF!$F$25+DCF!$G$19/(1+$B48)^DCF!$G$25+DCF!$H$19/(1+$B48)^DCF!$H$25+DCF!$I$19/(1+$B48)^DCF!$I$25+DCF!$J$19/(1+$B48)^DCF!$J$25+D$45*DCF!$J$8/(1+$B48)^5)+SUM(DCF!$C$45:$C$50))/DCF!$C$52/Inputs!$C$76-1 | E48: =((DCF!$F$19/(1+$B48)^DCF!$F$25+DCF!$G$19/(1+$B48)^DCF!$G$25+DCF!$H$19/(1+$B48)^DCF!$H$25+DCF!$I$19/(1+$B48)^DCF!$I$25+DCF!$J$19/(1+$B48)^DCF!$J$25+E$45*DCF!$J$8/(1+$B48)^5)+SUM(DCF!$C$45:$C$50))/DCF!$C$52/Inputs!$C$76-1 | F48: =((DCF!$F$19/(1+$B48)^DCF!$F$25+DCF!$G$19/(1+$B48)^DCF!$G$25+DCF!$H$19/(1+$B48)^DCF!$H$25+DCF!$I$19/(1+$B48)^DCF!$I$25+DCF!$J$19/(1+$B48)^DCF!$J$25+F$45*DCF!$J$8/(1+$B48)^5)+SUM(DCF!$C$45:$C$50))/DCF!$C$52/Inputs!$C$76-1 | G48: =((DCF!$F$19/(1+$B48)^DCF!$F$25+DCF!$G$19/(1+$B48)^DCF!$G$25+DCF!$H$19/(1+$B48)^DCF!$H$25+DCF!$I$19/(1+$B48)^DCF!$I$25+DCF!$J$19/(1+$B48)^DCF!$J$25+G$45*DCF!$J$8/(1+$B48)^5)+SUM(DCF!$C$45:$C$50))/DCF!$C$52/Inputs!$C$76-1
B49: =WACC!$C$19+0.005 | C49: =((DCF!$F$19/(1+$B49)^DCF!$F$25+DCF!$G$19/(1+$B49)^DCF!$G$25+DCF!$H$19/(1+$B49)^DCF!$H$25+DCF!$I$19/(1+$B49)^DCF!$I$25+DCF!$J$19/(1+$B49)^DCF!$J$25+C$45*DCF!$J$8/(1+$B49)^5)+SUM(DCF!$C$45:$C$50))/DCF!$C$52/Inputs!$C$76-1 | D49: =((DCF!$F$19/(1+$B49)^DCF!$F$25+DCF!$G$19/(1+$B49)^DCF!$G$25+DCF!$H$19/(1+$B49)^DCF!$H$25+DCF!$I$19/(1+$B49)^DCF!$I$25+DCF!$J$19/(1+$B49)^DCF!$J$25+D$45*DCF!$J$8/(1+$B49)^5)+SUM(DCF!$C$45:$C$50))/DCF!$C$52/Inputs!$C$76-1 | E49: =((DCF!$F$19/(1+$B49)^DCF!$F$25+DCF!$G$19/(1+$B49)^DCF!$G$25+DCF!$H$19/(1+$B49)^DCF!$H$25+DCF!$I$19/(1+$B49)^DCF!$I$25+DCF!$J$19/(1+$B49)^DCF!$J$25+E$45*DCF!$J$8/(1+$B49)^5)+SUM(DCF!$C$45:$C$50))/DCF!$C$52/Inputs!$C$76-1 | F49: =((DCF!$F$19/(1+$B49)^DCF!$F$25+DCF!$G$19/(1+$B49)^DCF!$G$25+DCF!$H$19/(1+$B49)^DCF!$H$25+DCF!$I$19/(1+$B49)^DCF!$I$25+DCF!$J$19/(1+$B49)^DCF!$J$25+F$45*DCF!$J$8/(1+$B49)^5)+SUM(DCF!$C$45:$C$50))/DCF!$C$52/Inputs!$C$76-1 | G49: =((DCF!$F$19/(1+$B49)^DCF!$F$25+DCF!$G$19/(1+$B49)^DCF!$G$25+DCF!$H$19/(1+$B49)^DCF!$H$25+DCF!$I$19/(1+$B49)^DCF!$I$25+DCF!$J$19/(1+$B49)^DCF!$J$25+G$45*DCF!$J$8/(1+$B49)^5)+SUM(DCF!$C$45:$C$50))/DCF!$C$52/Inputs!$C$76-1
B50: =WACC!$C$19+0.01 | C50: =((DCF!$F$19/(1+$B50)^DCF!$F$25+DCF!$G$19/(1+$B50)^DCF!$G$25+DCF!$H$19/(1+$B50)^DCF!$H$25+DCF!$I$19/(1+$B50)^DCF!$I$25+DCF!$J$19/(1+$B50)^DCF!$J$25+C$45*DCF!$J$8/(1+$B50)^5)+SUM(DCF!$C$45:$C$50))/DCF!$C$52/Inputs!$C$76-1 | D50: =((DCF!$F$19/(1+$B50)^DCF!$F$25+DCF!$G$19/(1+$B50)^DCF!$G$25+DCF!$H$19/(1+$B50)^DCF!$H$25+DCF!$I$19/(1+$B50)^DCF!$I$25+DCF!$J$19/(1+$B50)^DCF!$J$25+D$45*DCF!$J$8/(1+$B50)^5)+SUM(DCF!$C$45:$C$50))/DCF!$C$52/Inputs!$C$76-1 | E50: =((DCF!$F$19/(1+$B50)^DCF!$F$25+DCF!$G$19/(1+$B50)^DCF!$G$25+DCF!$H$19/(1+$B50)^DCF!$H$25+DCF!$I$19/(1+$B50)^DCF!$I$25+DCF!$J$19/(1+$B50)^DCF!$J$25+E$45*DCF!$J$8/(1+$B50)^5)+SUM(DCF!$C$45:$C$50))/DCF!$C$52/Inputs!$C$76-1 | F50: =((DCF!$F$19/(1+$B50)^DCF!$F$25+DCF!$G$19/(1+$B50)^DCF!$G$25+DCF!$H$19/(1+$B50)^DCF!$H$25+DCF!$I$19/(1+$B50)^DCF!$I$25+DCF!$J$19/(1+$B50)^DCF!$J$25+F$45*DCF!$J$8/(1+$B50)^5)+SUM(DCF!$C$45:$C$50))/DCF!$C$52/Inputs!$C$76-1 | G50: =((DCF!$F$19/(1+$B50)^DCF!$F$25+DCF!$G$19/(1+$B50)^DCF!$G$25+DCF!$H$19/(1+$B50)^DCF!$H$25+DCF!$I$19/(1+$B50)^DCF!$I$25+DCF!$J$19/(1+$B50)^DCF!$J$25+G$45*DCF!$J$8/(1+$B50)^5)+SUM(DCF!$C$45:$C$50))/DCF!$C$52/Inputs!$C$76-1

Sheet Scenarios
A1: Infosys Limited - Scenario Summary (Bear / Base / Bull)
A2: STATIC SNAPSHOT: values pasted from running the model with the selector on 3 / 1 / 2. To refresh after changing any assumption, flip Inputs!C6 through 1-2-3 and paste the DCF outputs here.
A4: Metric | B4: Bear | C4: Base | D4: Bull
A5: FY26E revenue (Rs crore) | B5: 166503.02 | C5: 169828.02 | D5: 172321.76
A6: FY30E revenue (Rs crore) | B6: 204703.88 | C6: 228578.11 | D6: 249916.73
A7: Revenue CAGR FY25-FY30E (INR) | B7: 0.046629628 | C7: 0.069977718 | D7: 0.089248254
A8: FY30E operating margin | B8: 0.18072687 | C8: 0.21068024 | D8: 0.23425544
A9: FY30E EBITDA (Rs crore) | B9: 42203.456 | C9: 53602.656 | D9: 64185.676
A10: FY30E FCFF (Rs crore) | B10: 24488.85 | C10: 31406.627 | D10: 37736.48
A11: Enterprise value - Gordon (Rs crore) | B11: 360156.26 | C11: 453039.82 | D11: 538463.53
A12: Enterprise value - Exit multiple (Rs crore) | B12: 430640.78 | C12: 536285.48 | D12: 633375.81
A13: Value per share - Gordon growth (Rs) | B13: 962.28388 | C13: 1185.9919 | D13: 1391.733
A14: Value per share - Exit multiple (Rs) | B14: 1132.0443 | C14: 1386.4872 | D14: 1620.3271
A15: Blended value per share (Rs) | B15: 1047.1641 | C15: 1286.2395 | D15: 1506.03
A16: Upside / (downside) vs market price Rs1,573 | B16: -0.33445818 | C16: -0.18250998 | D16: -0.042818611
A19: Scenario definitions (see Inputs sheet section A):
A20: Base: constant-currency USD growth 2% (FY26E) rising to ~6-7%, INR depreciation 1.5-2% p.a., employee cost per head +4-4.5%, operating margin ~21-22%.
A21: Bull: +1.5 to +2.0pp faster growth in every vertical (GenAI-led deal ramp-up, discretionary recovery), cost per head 0.4pp lower (pyramid, automation).
A22: Bear: -2.0 to -2.5pp slower growth (weak discretionary spend, AI-led deflation of effort-based pricing), cost per head 0.5pp higher (wage and skill pressure).

Sheet Checks
A1: Infosys Limited - Model Checks
A2: Rs crore unless stated | Consolidated Ind AS financials | FY ends 31 March | Blue = hard-coded input / reported data, Black = formula, Green = cross-sheet link
A4: Check | B4: Unit | C4: FY23A | D4: FY24A | E4: FY25A | F4: FY26E | G4: FY27E | H4: FY28E | I4: FY29E | J4: FY30E | L4: Notes / source
A6: MODEL INTEGRITY CHECKS (all should read OK)
A7: Balance sheet balances (assets = equity + liabilities), all years | C7: =IF(ABS(BS!C53)<1,"OK","ERROR") | D7: =IF(ABS(BS!D53)<1,"OK","ERROR") | E7: =IF(ABS(BS!E53)<1,"OK","ERROR") | F7: =IF(ABS(BS!F53)<1,"OK","ERROR") | G7: =IF(ABS(BS!G53)<1,"OK","ERROR") | H7: =IF(ABS(BS!H53)<1,"OK","ERROR") | I7: =IF(ABS(BS!I53)<1,"OK","ERROR") | J7: =IF(ABS(BS!J53)<1,"OK","ERROR")
A8: Cash flow closing cash = balance sheet cash (all years) | C8: =IF(ABS(CF!C49)<1,"OK","ERROR") | D8: =IF(ABS(CF!D49)<1,"OK","ERROR") | E8: =IF(ABS(CF!E49)<1,"OK","ERROR") | F8: =IF(ABS(CF!F49)<1,"OK","ERROR") | G8: =IF(ABS(CF!G49)<1,"OK","ERROR") | H8: =IF(ABS(CF!H49)<1,"OK","ERROR") | I8: =IF(ABS(CF!I49)<1,"OK","ERROR") | J8: =IF(ABS(CF!J49)<1,"OK","ERROR")
A9: Cash balance stays positive (forecast) | F9: =IF(BS!F23>0,"OK","NEGATIVE CASH") | G9: =IF(BS!G23>0,"OK","NEGATIVE CASH") | H9: =IF(BS!H23>0,"OK","NEGATIVE CASH") | I9: =IF(BS!I23>0,"OK","NEGATIVE CASH") | J9: =IF(BS!J23>0,"OK","NEGATIVE CASH")
A10: Vertical revenue ties to consolidated revenue (historical) | C10: =IF(ABS(Segments!C16-IS!C7)<1,"OK","ERROR") | D10: =IF(ABS(Segments!D16-IS!D7)<1,"OK","ERROR") | E10: =IF(ABS(Segments!E16-IS!E7)<1,"OK","ERROR")
A11: Segment operating profit ties to income statement (historical) | C11: =IF(ABS(Segments!C28-IS!C36)<1,"OK","ERROR") | D11: =IF(ABS(Segments!D28-IS!D36)<1,"OK","ERROR") | E11: =IF(ABS(Segments!E28-IS!E36)<1,"OK","ERROR")
A12: Geography revenue ties to consolidated revenue (historical) | C12: =IF(ABS(Segments!C44-IS!C7)<1,"OK","ERROR") | D12: =IF(ABS(Segments!D44-IS!D7)<1,"OK","ERROR") | E12: =IF(ABS(Segments!E44-IS!E7)<1,"OK","ERROR")
A13: PAT = owners + NCI (all years) | C13: =IF(ABS(IS!C24-IS!C26-IS!C25)<1,"OK","ERROR") | D13: =IF(ABS(IS!D24-IS!D26-IS!D25)<1,"OK","ERROR") | E13: =IF(ABS(IS!E24-IS!E26-IS!E25)<1,"OK","ERROR") | F13: =IF(ABS(IS!F24-IS!F26-IS!F25)<1,"OK","ERROR") | G13: =IF(ABS(IS!G24-IS!G26-IS!G25)<1,"OK","ERROR") | H13: =IF(ABS(IS!H24-IS!H26-IS!H25)<1,"OK","ERROR") | I13: =IF(ABS(IS!I24-IS!I26-IS!I25)<1,"OK","ERROR") | J13: =IF(ABS(IS!J24-IS!J26-IS!J25)<1,"OK","ERROR")
A14: Operating cash flow ties to reported (hist) | C14: =IF(ABS(CF!C26-C22)<2,"OK","ERROR") | D14: =IF(ABS(CF!D26-D22)<2,"OK","ERROR") | E14: =IF(ABS(CF!E26-E22)<2,"OK","ERROR")
A15: Net cash movement ties to reported (hist) | C15: =IF(ABS(CF!C45-C23)<2,"OK","ERROR") | D15: =IF(ABS(CF!D45-D23)<2,"OK","ERROR") | E15: =IF(ABS(CF!E45-E23)<2,"OK","ERROR")
A16: Total assets tie to reported (hist) | C16: =IF(ABS(BS!C29-C24)<1,"OK","ERROR") | D16: =IF(ABS(BS!D29-D24)<1,"OK","ERROR") | E16: =IF(ABS(BS!E29-E24)<1,"OK","ERROR")
A17: PBT ties to reported (hist) | C17: =IF(ABS(IS!C20-C25)<1,"OK","ERROR") | D17: =IF(ABS(IS!D20-D25)<1,"OK","ERROR") | E17: =IF(ABS(IS!E20-E25)<1,"OK","ERROR")
A18: WACC > terminal growth | C18: =IF(WACC!C19>Inputs!C67,"OK","ERROR")
A19: OVERALL MODEL STATUS | C19: =IF(COUNTIF(C7:J18,"ERROR")+COUNTIF(C7:J18,"NEG*")=0,"ALL CHECKS PASS","REVIEW ERRORS")
A21: Reported figures used for tie-out (hard-coded from audited statements)
A22: Reported net cash generated by operating activities | B22: Rs cr | C22: 22467 | D22: 25210 | E22: 35694
A23: Reported net increase in cash | B23: Rs cr | C23: -5437 | D23: 2697 | E23: 9587
A24: Reported total assets | B24: Rs cr | C24: 125816 | D24: 137814 | E24: 148903
A25: Reported profit before tax | B25: Rs cr | C25: 33322 | D25: 35988 | E25: 37608

Sheet Notes
A1: Infosys Limited - DCF Valuation Model: Methodology & Notes
A3: PURPOSE
A4: Estimate the intrinsic value per share of Infosys Ltd as at 31-Mar-2025 (end FY25) using an integrated forecast of the CONSOLIDATED income statement, balance sheet and cash flow statement for FY26E-FY30E and a DCF of free cash flow to firm. All amounts are in Rs crore (1 crore = 10 million) unless stated.
A6: SOURCES
A7: Infosys Integrated Annual Report 2024-25 (FY25, FY24 comparatives) and 2023-24 (FY23 comparatives): consolidated Ind AS balance sheet, statement of profit and loss and statement of cash flows; Note 2.26 segment reporting; Note 2.21 leases; MD&A; five-year summary (US$ revenue). Market capitalisation at 31-Mar-2025 is the company-reported Rs6,52,332 crore. Rf: 10-yr G-sec 6.81%.
A9: MODEL FLOW
A10: Inputs -> Segments (US$ revenue by industry vertical x INR/USD; headcount x cost per head) -> consolidated revenue and employee cost -> IS -> Sched (capex, D&A, leases, dividends) -> BS -> CF -> DCF (FCFF) -> equity bridge -> Sens / Scenarios -> Checks.
A12: KEY JUDGEMENTS (be ready to defend in an interview)
A13: 1. IT SERVICES REVENUE: built bottom-up by industry vertical in US$ (the currency clients pay in) and translated at an assumed average INR/USD. Constant-currency growth is the scenario lever; INR depreciation (1.5-2% p.a.) adds to reported growth and is an explicit assumption, not a free lunch.
A14: 2. MARGINS: employee cost is built from headcount x cost per head (about 53% of revenue), the single biggest cost. Revenue per head vs cost per head is the margin engine (utilisation, pyramid, pricing, automation). Third-party software / hardware costs are held at 9.75% of revenue.
A15: 3. NET CASH BUSINESS: Infosys has no borrowings. Cash and investments (Rs47,996 crore incl. non-current) are added in the equity bridge; other income is excluded from FCFF so the cash is not counted twice. Lease liabilities are the only debt-like item.
A16: 4. LEASES (Ind AS 116): default = leases as debt, new ROU additions deducted from FCFF; switch 2 gives the pre-Ind AS 116 view.
... A23: No explicit client-concentration, pricing-model or AI-deflation module; the scenario growth adjustment stands in for these. FX is a single average-rate path (no hedging P&L). Deferred tax, OCI and acquisitions are not forecast. The FY26 guidance cited on the Inputs sheet comes from the Q4 FY25 results release (public, April 2025), not the Annual Report - verify. Scenarios sheet is a pasted snapshot.
